Workbook

Sheet Table_of_Contents_&_Acronym
A1: Future Growth & Industry Trends Analysis
A2: Individual Analysis supporting the project: Using Data to Support Career Decision-Making in Computer Science
A5: Tab | B5: Content | D5: Acronyms and Abbreviations
A6: 01_Overview | B6: Research purpose, main question, supporting questions and analytical framework | D6: Acronym | E6: Full term
A7: 02_Raw_Baseline | B7: Original Baseline employment projection data | D7: AI | E7: Artificial Intelligence
A8: 03_Raw_Technical | B8: Original Technical Opportunities scenario data | D8: APS | E8: Annual Population Survey
A9: 04_Raw_HumanCentric | B9: Original Human-Centric scenario data | D9: CS | E9: Computer Science
A10: 05_Data_Preparation | B10: Data cleaning, preparation and allocation steps before analysis | D10: DfE | E10: Department for Education
A11: 06_Career_Area_Map | B11: Mapping of Standard Occupational Classification (SOC) occupations to the five Computer Science Career Areas | D11: ID | E11: Identifier
A12: 07_Analysis_Base | B12: Main prepared analytical dataset used across Q1–Q4 | D12: IT | E12: Information Technology
A13: 08_WEF_Technology | B13: World Economic Forum (WEF) technology trends and United Kingdom (UK)/Global employer expectations | D13: MA | E13: Moving Average
A14: 09_WEF_Jobs_Outlook | B14: WEF jobs outlook evidence, including growth and structural change | D14: ML | E14: Machine Learning
A15: 10_WEF_AI_Strategy | B15: WEF evidence on organisational Artificial Intelligence (AI) strategies and workforce responses | D15: MSE | E15: Mean Squared Error
A16: 11_WEF_Skills_Outlook | B16: WEF evidence on skills expected to grow in importance | D16: N/A | E16: Not Applicable
A17: 12_WEF_Fastest_Growing | B17: WEF fastest-growing jobs and their relevance to the Career Areas | D17: ONS | E17: Office for National Statistics
... A26: 19_Visual_Summary | B26: Visual summary of the main analytical results | D26: YoY | E26: Year-on-Year
A27: 20_Main_Formulas | B27: Key formulas and analytical logic used throughout the workbook
A28: 21_References | B28: External datasets and supporting sources used in the analysis

Sheet 01_Overview
A1: Future Growth & Industry Trends Analysis
A2: Individual Analysis supporting the project: Using Data to Support Career Decision-Making in Computer Science
A4: Purpose
A5: This workbook analyses future employment growth, employment projections, technology trends and curriculum alignment across five Computer Science Career Areas. It combines official UK employment projections with structured evidence from the World Economic Forum and the supporting Career Map methodology to identify which areas show stronger future potential and what these findings imply for students making career decisions.
A7: Main Research Question | D7: Analytical Framework
A8: Which Computer Science Career Areas show the strongest future growth potential?
D9: Research Question | E9: Analytics Type | F9: Method
A10: Supporting Questions
A11: Q1. How do employment growth and job creation differ across the five Career Areas? | D11: Q1 — Growth and job creation | E11: Descriptive | F11: Descriptive Analysis
A12: Q2. How do employment projections change over time and across future scenarios? | D12: Q2 — Employment projections and scenarios | E12: Predictive | F12: Time Series Analysis + Exploratory Forecasting
A13: Q3. Which technology trends are linked to the future outlook of Computer Science careers, and how does the UK compare globally? | D13: Q3 — UK vs Global technology expectations | E13: Diagnostic | F13: Descriptive comparison + Simple Linear Regression
A14: Q4. Do high-growth occupations also show strong curriculum alignment, or important skills gaps? | D14: Q4 — Growth × curriculum alignment/gaps | E14: Diagnostic | F14: Cluster Analysis
A15: Decision-Support Question | D15: Decision-Support Question | E15: Prescriptive | F15: Decision Analysis
A16: What do these findings imply for students choosing a Computer Science career with stronger future potential?
D17: Methodological Note: Q2 combines official Department for Education (DfE) long-term employment projections with an exploratory short-term 2026 forecast based on Office for National Statistics (ONS) Annual Population Survey (APS) employment estimates for 2021–2025. Moving Average and Simple Exponential Smoothing models were compared using Mean Squared Error (MSE). Due to the short time series, the forecast is exploratory and is not extended to 2035.
A18: Data Sources
A19: Evidence | B19: Role in the Analysis
A20: UK Labour Market and Skills Projections 2020–2035 | B20: Employment levels and future scenarios at Standard Occupational Classification 2020 (SOC2020) Unit Group level
A21: World Economic Forum (WEF) Future of Jobs Report 2025 – UK Economy Profile + Global Report Evidence | B21: Technology trends, jobs outlook, AI strategy, skills and global fastest-growing occupations.
A22: Career Map & Curriculum Alignment Supporting Workbook | B22: SOC-to-Career-Area classification, mixed-SOC methodology and curriculum alignment/gap evidence
A24: WEF evidence was manually extracted and structured from the original PDF/report and is therefore treated as Extracted / Structured Data, rather than raw data.
A26: Analytical Stages
A27: Analytical Workflow
A28: Sources → Raw Scenarios → Data Preparation → Career Area Mapping → Analysis Base → WEF Structured Evidence → Descriptive → Predictive → Diagnostic → Prescriptive → Key Findings → Visual Summary
A30: Workbook Section | B30: Sheets
A31: Sources & Preparation | B31: 21_References – 07_Analysis_Base
A32: WEF Evidence | B32: 08_WEF_Technology – 12_WEF_Fastest_Growing
A33: Analytical Methods | B33: 13_Descriptive_Q1 – 17_Prescriptive_Analysis
A34: Final Communication | B34: 18_Key_Findings – 19_Visual_Summary
A36: Career Areas in Scope
A37: Career Area | B37: Main SOC Coverage
A38: Software Development & Testing | B38: 2134, 2136 + proportional share of 2139
A39: Data, Analytics & Databases | B39: 3544, 3133 + proportional share of 2133
A40: Cybersecurity | B40: 2135
A41: Web, Applications & UX/UI | B41: 2141 + proportional share of 2139
A42: IT Infrastructure, Networks & Support | B42: 2137, 3131, 3132 + proportional share of 2133
A43: Supporting classification: Cross-functional / Mixed IT is retained for occupations within mixed SOC Unit Groups that cannot be assigned exclusively to one of the five Career Areas.
A47: Key Methodological Notes
A48: Mixed SOC Unit Groups: SOC 2133 and 2139 contain occupations spanning multiple Career Areas. Because official employment projections are available at Unit Group level rather than Extended SOC Sub-Unit level, validated Adzuna vacancy-search proportions are used as a methodological proxy for proportional Career Area allocation. These proportions are not official SOC employment weights.
A49: Important distinction: Proportional allocation of 2133 and 2139 is used for Career Area employment and forecast analysis. For curriculum alignment and gap analysis at SOC Unit Group level, Overall Alignment is not proportionally divided; 2133 and 2139 remain mixed methodological cases.

Sheet 02_Raw_Baseline
A1: Table 2: Employment by occupation (SOC2020 unit group), baseline scenario, 2021 to 2035, United Kingdom
A2: SOC2020 sub-major group | B2: SOC2020 unit group | C2: Occupation description | D2: 2021 | E2: 2022 | F2: 2023 | G2: 2024 | H2: 2025 | I2: 2026 | J2: 2027 | K2: 2028 | L2: 2029 | M2: 2030 | N2: 2031 | O2: 2032 | P2: 2033 | Q2: 2034 | R2: 2035
A3: 11 | B3: 1111 | C3: Chief executives and senior officials | D3: 141827.42 | E3: 143276.75 | F3: 144998.02 | G3: 146818.83 | H3: 148315.69 | I3: 149722.57 | J3: 151076.34 | K3: 152440.7 | L3: 153811.24 | M3: 155249.46 | N3: 156682.28 | O3: 158128.11 | P3: 159591.11 | Q3: 161061 | R3: 162543.89
A4: 11 | B4: 1112 | C4: Elected officers and representatives | D4: 11808.071 | E4: 11928.737 | F4: 12072.044 | G4: 12223.639 | H4: 12348.262 | I4: 12465.394 | J4: 12578.105 | K4: 12691.697 | L4: 12805.803 | M4: 12925.545 | N4: 13044.836 | O4: 13165.211 | P4: 13287.016 | Q4: 13409.393 | R4: 13532.854
A5: 11 | B5: 1121 | C5: Production managers and directors in manufacturing | D5: 258484.04 | E5: 261125.49 | F5: 264262.54 | G5: 267581.01 | H5: 270309.07 | I5: 272873.15 | J5: 275340.44 | K5: 277827.01 | L5: 280324.86 | M5: 282946.05 | N5: 285557.39 | O5: 288192.46 | P5: 290858.82 | Q5: 293537.72 | R5: 296240.33
A6: 11 | B6: 1122 | C6: Production managers and directors in construction | D6: 168634.73 | E6: 170358.01 | F6: 172404.62 | G6: 174569.59 | H6: 176349.37 | I6: 178022.17 | J6: 179631.83 | K6: 181254.07 | L6: 182883.66 | M6: 184593.72 | N6: 186297.36 | O6: 188016.47 | P6: 189756 | Q6: 191503.72 | R6: 193266.9
A7: 11 | B7: 1123 | C7: Production managers and directors in mining and energy | D7: 28061.589 | E7: 28348.35 | F7: 28688.916 | G7: 29049.176 | H7: 29345.34 | I7: 29623.702 | J7: 29891.556 | K7: 30161.504 | L7: 30432.675 | M7: 30717.238 | N7: 31000.731 | O7: 31286.8 | P7: 31576.265 | Q7: 31867.092 | R7: 32160.493
A8: 11 | B8: 1131 | C8: Financial managers and directors | D8: 332477.63 | E8: 335875.22 | F8: 339910.29 | G8: 344178.7 | H8: 347687.69 | I8: 350985.77 | J8: 354159.34 | K8: 357357.72 | L8: 360570.59 | M8: 363942.13 | N8: 367301 | O8: 370690.38 | P8: 374120.01 | Q8: 377565.77 | R8: 381042.03
A9: 11 | B9: 1132 | C9: Marketing, sales and advertising directors | D9: 268296.36 | E9: 271038.08 | F9: 274294.22 | G9: 277738.67 | H9: 280570.28 | I9: 283231.7 | J9: 285792.65 | K9: 288373.61 | L9: 290966.28 | M9: 293686.98 | N9: 296397.45 | O9: 299132.55 | P9: 301900.12 | Q9: 304680.72 | R9: 307485.92
A10: 11 | B10: 1133 | C10: Public relations and communications directors | D10: 13905.976 | E10: 14048.081 | F10: 14216.849 | G10: 14395.376 | H10: 14542.141 | I10: 14680.084 | J10: 14812.819 | K10: 14946.592 | L10: 15080.972 | M10: 15221.987 | N10: 15362.473 | O10: 15504.235 | P10: 15647.68 | Q10: 15791.8 | R10: 15937.196
A11: 11 | B11: 1134 | C11: Purchasing managers and directors | D11: 58443.659 | E11: 59040.895 | F11: 59750.188 | G11: 60500.499 | H11: 61117.317 | I11: 61697.06 | J11: 62254.918 | K11: 62817.136 | L11: 63381.902 | M11: 63974.559 | N11: 64564.988 | O11: 65160.781 | P11: 65763.648 | Q11: 66369.353 | R11: 66980.417
A12: 11 | B12: 1135 | C12: Charitable organisation managers and directors | D12: 52923.213 | E12: 53464.035 | F12: 54106.331 | G12: 54785.769 | H12: 55344.324 | I12: 55869.306 | J12: 56374.47 | K12: 56883.582 | L12: 57395.002 | M12: 57931.678 | N12: 58466.336 | O12: 59005.852 | P12: 59551.774 | Q12: 60100.265 | R12: 60653.61
A13: 11 | B13: 1136 | C13: Human resource managers and directors | D13: 238409.85 | E13: 240846.16 | F13: 243739.59 | G13: 246800.34 | H13: 249316.53 | I13: 251681.48 | J13: 253957.16 | K13: 256250.62 | L13: 258554.48 | M13: 260972.11 | N13: 263380.65 | O13: 265811.08 | P13: 268270.36 | Q13: 270741.22 | R13: 273233.94
A14: 11 | B14: 1137 | C14: Information technology directors | D14: 187680.61 | E14: 189598.51 | F14: 191876.27 | G14: 194285.75 | H14: 196266.55 | I14: 198128.28 | J14: 199919.73 | K14: 201725.19 | L14: 203538.83 | M14: 205442.03 | N14: 207338.08 | O14: 209251.36 | P14: 211187.35 | Q14: 213132.45 | R14: 215094.77
... A414: 92 | B414: 9269 | C414: Other elementary services occupations n.e.c. | D414: 30781.396 | E414: 30708.604 | F414: 30686.517 | G414: 30687.589 | H414: 30620.005 | I414: 30524.894 | J414: 30414.593 | K414: 30300.63 | L414: 30183.582 | M414: 30073.841 | N414: 29959.807 | O414: 29844.017 | P414: 29728.133 | Q414: 29609.498 | R414: 29489.128

Sheet 03_Raw_Technical
A1: Table 6: Employment by occupation (SOC2020 unit group), technical opportunities scenario, 2021 to 2035, United Kingdom
A2: SOC2020 sub-major group | B2: SOC2020 unit group | C2: Occupation description | D2: 2021 | E2: 2022 | F2: 2023 | G2: 2024 | H2: 2025 | I2: 2026 | J2: 2027 | K2: 2028 | L2: 2029 | M2: 2030 | N2: 2031 | O2: 2032 | P2: 2033 | Q2: 2034 | R2: 2035
A3: 11 | B3: 1111 | C3: Chief executives and senior officials | D3: 142155.58 | E3: 143848.41 | F3: 145507.23 | G3: 147045.66 | H3: 148143.43 | I3: 149155.19 | J3: 150105.55 | K3: 151057.38 | L3: 152000.13 | M3: 152997.91 | N3: 153957.82 | O3: 154910.51 | P3: 155860.82 | Q3: 156799.39 | R3: 157736.64
A4: 11 | B4: 1112 | C4: Elected officers and representatives | D4: 11835.393 | E4: 11976.332 | F4: 12114.439 | G4: 12242.524 | H4: 12333.921 | I4: 12418.156 | J4: 12497.28 | K4: 12576.526 | L4: 12655.017 | M4: 12738.088 | N4: 12818.007 | O4: 12897.325 | P4: 12976.444 | Q4: 13054.586 | R4: 13132.619
A5: 11 | B5: 1121 | C5: Production managers and directors in manufacturing | D5: 259082.13 | E5: 262167.35 | F5: 265190.59 | G5: 267994.41 | H5: 269995.14 | I5: 271839.09 | J5: 273571.14 | K5: 275305.88 | L5: 277024.07 | M5: 278842.53 | N5: 280592 | O5: 282328.31 | P5: 284060.27 | Q5: 285770.83 | R5: 287479
A6: 11 | B6: 1122 | C6: Production managers and directors in construction | D6: 169024.92 | E6: 171037.72 | F6: 173010.08 | G6: 174839.29 | H6: 176144.56 | I6: 177347.55 | J6: 178477.54 | K6: 179609.28 | L6: 180730.23 | M6: 181916.59 | N6: 183057.94 | O6: 184190.71 | P6: 185320.63 | Q6: 186436.61 | R6: 187551.01
A7: 11 | B7: 1123 | C7: Production managers and directors in mining and energy | D7: 28126.518 | E7: 28461.456 | F7: 28789.666 | G7: 29094.055 | H7: 29311.258 | I7: 29511.442 | J7: 29699.477 | K7: 29887.804 | L7: 30074.334 | M7: 30271.751 | N7: 30461.676 | O7: 30650.174 | P7: 30838.199 | Q7: 31023.902 | R7: 31209.344
A8: 11 | B8: 1131 | C8: Financial managers and directors | D8: 333246.93 | E8: 337215.32 | F8: 341104 | G8: 344710.44 | H8: 347283.89 | I8: 349655.69 | J8: 351883.56 | K8: 354114.88 | L8: 356324.92 | M8: 358663.94 | N8: 360914.21 | O8: 363147.55 | P8: 365375.3 | Q8: 367575.54 | R8: 369772.68
A9: 11 | B9: 1132 | C9: Marketing, sales and advertising directors | D9: 268917.15 | E9: 272119.49 | F9: 275257.5 | G9: 278167.76 | H9: 280244.43 | I9: 282158.38 | J9: 283956.18 | K9: 285756.77 | L9: 287540.19 | M9: 289427.68 | N9: 291243.56 | O9: 293045.78 | P9: 294843.49 | Q9: 296618.99 | R9: 298392
A10: 11 | B10: 1133 | C10: Public relations and communications directors | D10: 13938.151 | E10: 14104.131 | F10: 14266.776 | G10: 14417.616 | H10: 14525.252 | I10: 14624.453 | J10: 14717.634 | K10: 14810.96 | L10: 14903.396 | M10: 15001.226 | N10: 15095.344 | O10: 15188.754 | P10: 15281.93 | Q10: 15373.956 | R10: 15465.852
A11: 11 | B11: 1134 | C11: Purchasing managers and directors | D11: 58578.887 | E11: 59276.46 | F11: 59960.021 | G11: 60593.969 | H11: 61046.336 | I11: 61463.256 | J11: 61854.876 | K11: 62247.103 | L11: 62635.589 | M11: 63046.747 | N11: 63442.303 | O11: 63834.886 | P11: 64226.485 | Q11: 64613.247 | R11: 64999.465
A12: 11 | B12: 1135 | C12: Charitable organisation managers and directors | D12: 53045.668 | E12: 53677.35 | F12: 54296.343 | G12: 54870.41 | H12: 55280.048 | I12: 55657.587 | J12: 56012.215 | K12: 56367.393 | L12: 56719.184 | M12: 57091.505 | N12: 57449.698 | O12: 57805.198 | P12: 58159.808 | Q12: 58510.037 | R12: 58859.774
A13: 11 | B13: 1136 | C13: Human resource managers and directors | D13: 238961.49 | E13: 241807.1 | F13: 244595.56 | G13: 247181.63 | H13: 249026.98 | I13: 250727.72 | J13: 252325.26 | K13: 253925.28 | L13: 255510.03 | M13: 257187.27 | N13: 258800.87 | O13: 260402.34 | P13: 261999.79 | Q13: 263577.51 | R13: 265153.02
A14: 11 | B14: 1137 | C14: Information technology directors | D14: 188114.87 | E14: 190354.99 | F14: 192550.11 | G14: 194585.91 | H14: 196038.6 | I14: 197377.46 | J14: 198635.08 | K14: 199894.64 | L14: 201142.19 | M14: 202462.54 | N14: 203732.79 | O14: 204993.5 | P14: 206251.04 | Q14: 207493.05 | R14: 208733.32
... A414: 92 | B414: 9269 | C414: Other elementary services occupations n.e.c. | D414: 30851.148 | E414: 30881.867 | F414: 30893.519 | G414: 30861.376 | H414: 30726.027 | I414: 30563.409 | J414: 30384.773 | K414: 30201.658 | L414: 30013.108 | M414: 29829.214 | N414: 29641.627 | O414: 29449.672 | P414: 29254.858 | Q414: 29054.584 | R414: 28850.586

Sheet 04_Raw_HumanCentric
A1: Table 8: Employment by occupation (SOC2020 unit group), human-centric scenario, 2021 to 2035, United Kingdom
A2: SOC2020 sub-major group | B2: SOC2020 unit group | C2: Occupation description | D2: 2021 | E2: 2022 | F2: 2023 | G2: 2024 | H2: 2025 | I2: 2026 | J2: 2027 | K2: 2028 | L2: 2029 | M2: 2030 | N2: 2031 | O2: 2032 | P2: 2033 | Q2: 2034 | R2: 2035
A3: 11 | B3: 1111 | C3: Chief executives and senior officials | D3: 142099.52 | E3: 143708.95 | F3: 145315.58 | G3: 146809.29 | H3: 147841.24 | I3: 148788.04 | J3: 149676.09 | K3: 150568.35 | L3: 151453.8 | M3: 152396.57 | N3: 153304.52 | O3: 154208.16 | P3: 155111.23 | Q3: 156005.66 | R3: 156901.21
A4: 11 | B4: 1112 | C4: Elected officers and representatives | D4: 11830.725 | E4: 11964.721 | F4: 12098.483 | G4: 12222.844 | H4: 12308.762 | I4: 12387.588 | J4: 12461.525 | K4: 12535.811 | L4: 12609.531 | M4: 12688.022 | N4: 12763.615 | O4: 12838.849 | P4: 12914.036 | Q4: 12988.503 | R4: 13063.063
A5: 11 | B5: 1121 | C5: Production managers and directors in manufacturing | D5: 258979.95 | E5: 261913.18 | F5: 264841.3 | G5: 267563.62 | H5: 269444.39 | I5: 271169.94 | J5: 272788.45 | K5: 274414.6 | L5: 276028.37 | M5: 277746.58 | N5: 279401.34 | O5: 281048.25 | P5: 282694.12 | Q5: 284324.24 | R5: 285956.4
A6: 11 | B6: 1122 | C6: Production managers and directors in construction | D6: 168958.26 | E6: 170871.9 | F6: 172782.2 | G6: 174558.24 | H6: 175785.25 | I6: 176911 | J6: 177966.91 | K6: 179027.81 | L6: 180080.63 | M6: 181201.59 | N6: 182281.16 | O6: 183355.6 | P6: 184429.36 | Q6: 185492.85 | R6: 186557.67
A7: 11 | B7: 1123 | C7: Production managers and directors in mining and energy | D7: 28115.426 | E7: 28433.864 | F7: 28751.746 | G7: 29047.288 | H7: 29251.468 | I7: 29438.797 | J7: 29614.506 | K7: 29791.045 | L7: 29966.239 | M7: 30152.772 | N7: 30332.416 | O7: 30511.208 | P7: 30689.888 | Q7: 30866.857 | R7: 31044.047
A8: 11 | B8: 1131 | C8: Financial managers and directors | D8: 333115.5 | E8: 336888.4 | F8: 340654.72 | G8: 344156.33 | H8: 346575.49 | I8: 348794.99 | J8: 350876.82 | K8: 352968.47 | L8: 355044.2 | M8: 357254.26 | N8: 359382.72 | O8: 361501.07 | P8: 363618.09 | Q8: 365714.84 | R8: 367814.22
A9: 11 | B9: 1132 | C9: Marketing, sales and advertising directors | D9: 268811.1 | E9: 271855.68 | F9: 274894.95 | G9: 277720.61 | H9: 279672.78 | I9: 281463.83 | J9: 283143.78 | K9: 284831.67 | L9: 286506.69 | M9: 288290.13 | N9: 290007.71 | O9: 291717.13 | P9: 293425.49 | Q9: 295117.48 | R9: 296811.6
A10: 11 | B10: 1133 | C10: Public relations and communications directors | D10: 13932.655 | E10: 14090.457 | F10: 14247.984 | G10: 14394.441 | H10: 14495.622 | I10: 14588.454 | J10: 14675.527 | K10: 14763.011 | L10: 14849.829 | M10: 14942.265 | N10: 15031.289 | O10: 15119.889 | P10: 15208.434 | Q10: 15296.132 | R10: 15383.939
A11: 11 | B11: 1134 | C11: Purchasing managers and directors | D11: 58555.785 | E11: 59218.993 | F11: 59881.045 | G11: 60496.567 | H11: 60921.811 | I11: 61311.961 | J11: 61677.908 | K11: 62045.584 | L11: 62410.46 | M11: 62798.95 | N11: 63173.094 | O11: 63545.463 | P11: 63917.598 | Q11: 64286.169 | R11: 64655.203
A12: 11 | B12: 1135 | C12: Charitable organisation managers and directors | D12: 53024.748 | E12: 53625.311 | F12: 54224.827 | G12: 54782.209 | H12: 55167.285 | I12: 55520.583 | J12: 55851.963 | K12: 56184.91 | L12: 56515.32 | M12: 56867.114 | N12: 57205.918 | O12: 57543.113 | P12: 57880.097 | Q12: 58213.854 | R12: 58548.03
A13: 11 | B13: 1136 | C13: Human resource managers and directors | D13: 238867.24 | E13: 241572.68 | F13: 244273.39 | G13: 246784.3 | H13: 248519 | I13: 250110.54 | J13: 251603.36 | K13: 253103.22 | L13: 254591.66 | M13: 256176.44 | N13: 257702.68 | O13: 259221.69 | P13: 260739.74 | Q13: 262243.26 | R13: 263748.67
A14: 11 | B14: 1137 | C14: Information technology directors | D14: 188040.68 | E14: 190170.44 | F14: 192296.5 | G14: 194273.13 | H14: 195638.72 | I14: 196891.61 | J14: 198066.78 | K14: 199247.5 | L14: 200419.23 | M14: 201666.79 | N14: 202868.28 | O14: 204064.07 | P14: 205259.11 | Q14: 206442.71 | R14: 207627.79
... A414: 92 | B414: 9269 | C414: Other elementary services occupations n.e.c. | D414: 30849.914 | E414: 30884.128 | F414: 30906.882 | G414: 30888.576 | H414: 30762.732 | I414: 30610.354 | J414: 30442.618 | K414: 30270.737 | L414: 30093.62 | M414: 29921.742 | N414: 29746.787 | O414: 29567.766 | P414: 29385.872 | Q414: 29198.676 | R414: 29007.964

Sheet 05_Data_Preparation
A1: Data Selection
A2: The original government projection datasets contain all SOC2020 Unit Groups. For this analysis, only the 11 Unit Groups previously identified as relevant to the five Computer Science Career Areas were selected. The same SOC selection was applied consistently to the Baseline, Technical Opportunities and Human-Centric scenarios for the full 2021–2035 period. The complete source datasets remain preserved in 02_Raw_Baseline, 03_Raw_Technical and 04_Raw_HumanCentric.
A3: Selected SOC2020 Unit Groups: 2133, 2134, 2135, 2136, 2137, 2139, 2141, 3131, 3132, 3133, 3544.
A5: Table 2: Employment by occupation (SOC2020 unit group), baseline scenario, 2021 to 2035, United Kingdom
A6: SOC2020 sub-major group | B6: SOC2020 unit group | C6: Occupation description | D6: 2021 | E6: 2022 | F6: 2023 | G6: 2024 | H6: 2025 | I6: 2026 | J6: 2027 | K6: 2028 | L6: 2029 | M6: 2030 | N6: 2031 | O6: 2032 | P6: 2033 | Q6: 2034 | R6: 2035
A7: 21 | B7: 2133 | C7: IT business analysts, architects and systems designers | D7: 141540.94 | E7: 143224.09 | F7: 145173.45 | G7: 147214.07 | H7: 148934.05 | I7: 150571.13 | J7: 152152.3 | K7: 153747.5 | L7: 155349.42 | M7: 157022.74 | N7: 158688.32 | O7: 160366.75 | P7: 162061.72 | Q7: 163763.55 | R7: 165479.01
A8: 21 | B8: 2134 | C8: Programmers and software development professionals | D8: 471632.45 | E8: 477240.91 | F8: 483736.44 | G8: 490536.05 | H8: 496267.24 | I8: 501722.19 | J8: 506990.84 | K8: 512306.26 | L8: 517644.07 | M8: 523219.79 | N8: 528769.7 | O8: 534362.46 | P8: 540010.29 | Q8: 545681.01 | R8: 551397.16
A9: 21 | B9: 2135 | C9: Cyber security professionals | D9: 34245.903 | E9: 34653.141 | F9: 35124.791 | G9: 35618.52 | H9: 36034.67 | I9: 36430.761 | J9: 36813.326 | K9: 37199.286 | L9: 37586.872 | M9: 37991.733 | N9: 38394.72 | O9: 38800.818 | P9: 39210.915 | Q9: 39622.674 | R9: 40037.732
A10: 21 | B10: 2136 | C10: IT quality and testing professionals | D10: 32583.629 | E10: 32971.101 | F10: 33419.857 | G10: 33889.62 | H10: 34285.571 | I10: 34662.436 | J10: 35026.431 | K10: 35393.657 | L10: 35762.43 | M10: 36147.639 | N10: 36531.066 | O10: 36917.452 | P10: 37307.643 | Q10: 37699.416 | R10: 38094.327
A11: 21 | B11: 2137 | C11: IT network professionals | D11: 33216.023 | E11: 33611.014 | F11: 34068.48 | G11: 34547.361 | H11: 34950.997 | I11: 35335.176 | J11: 35706.236 | K11: 36080.589 | L11: 36456.519 | M11: 36849.204 | N11: 37240.072 | O11: 37633.958 | P11: 38031.722 | Q11: 38431.098 | R11: 38833.674
A12: 21 | B12: 2139 | C12: Information technology professionals n.e.c. | D12: 139762.49 | E12: 141424.49 | F12: 143349.36 | G12: 145364.34 | H12: 147062.71 | I12: 148679.22 | J12: 150240.52 | K12: 151815.68 | L12: 153397.47 | M12: 155049.77 | N12: 156694.42 | O12: 158351.76 | P12: 160025.43 | Q12: 161705.88 | R12: 163399.79
A13: 21 | B13: 2141 | C13: Web design professionals | D13: 32259.752 | E13: 32643.371 | F13: 33087.667 | G13: 33552.761 | H13: 33944.776 | I13: 34317.896 | J13: 34678.273 | K13: 35041.848 | L13: 35406.956 | M13: 35788.336 | N13: 36167.951 | O13: 36550.497 | P13: 36936.809 | Q13: 37324.688 | R13: 37715.674
A14: 31 | B14: 3131 | C14: IT operations technicians | D14: 115929.23 | E14: 116850.37 | F14: 117968.09 | G14: 119160.44 | H14: 120097.62 | I14: 120962.77 | J14: 121782.42 | K14: 122611.23 | L14: 123444.24 | M14: 124330.63 | N14: 125209.8 | O14: 126097.33 | P14: 126996.86 | Q14: 127900.34 | R14: 128812.86
A15: 31 | B15: 3132 | C15: IT user support technicians | D15: 97466.749 | E15: 98241.196 | F15: 99180.905 | G15: 100183.37 | H15: 100971.3 | I15: 101698.67 | J15: 102387.79 | K15: 103084.6 | L15: 103784.95 | M15: 104530.17 | N15: 105269.33 | O15: 106015.51 | P15: 106771.79 | Q15: 107531.38 | R15: 108298.58
A16: 31 | B16: 3133 | C16: Database administrators and web content technicians | D16: 73066.8 | E16: 73647.371 | F16: 74351.832 | G16: 75103.337 | H16: 75694.018 | I16: 76239.295 | J16: 76755.898 | K16: 77278.268 | L16: 77803.295 | M16: 78361.957 | N16: 78916.073 | O16: 79475.457 | P16: 80042.402 | Q16: 80611.841 | R16: 81186.978
A17: 35 | B17: 3544 | C17: Data analysts | D17: 120549.87 | E17: 121234.66 | F17: 122102.35 | G17: 123049.98 | H17: 123733.28 | I17: 124328.87 | J17: 124875.43 | K17: 125421.84 | L17: 125966.64 | M17: 126556.31 | N17: 127133.8 | O17: 127713.35 | P17: 128299.38 | Q17: 128883.22 | R17: 129469.6
A19: Table 6: Employment by occupation (SOC2020 unit group), technical opportunities scenario, 2021 to 2035, United Kingdom
A20: SOC2020 sub-major group | B20: SOC2020 unit group | C20: Occupation description | D20: 2021 | E20: 2022 | F20: 2023 | G20: 2024 | H20: 2025 | I20: 2026 | J20: 2027 | K20: 2028 | L20: 2029 | M20: 2030 | N20: 2031 | O20: 2032 | P20: 2033 | Q20: 2034 | R20: 2035
A21: 21 | B21: 2133 | C21: IT business analysts, architects and systems designers | D21: 141836.24 | E21: 145829.16 | F21: 149821.15 | G21: 153721.8 | H21: 157194.52 | I21: 160596.21 | J21: 163938.82 | K21: 167293.44 | L21: 170646.9 | M21: 174075.69 | N21: 177456.32 | O21: 180835.3 | P21: 184218.08 | Q21: 187593.52 | R21: 190974.19
A22: 21 | B22: 2134 | C22: Programmers and software development professionals | D22: 472616.42 | E22: 485921.34 | F22: 499223.17 | G22: 512220.63 | H22: 523792.16 | I22: 535127.04 | J22: 546265.05 | K22: 557443.06 | L22: 568617.23 | M22: 580042.39 | N22: 591307.08 | O22: 602566.25 | P22: 613838.11 | Q22: 625085.5 | R22: 636350.34
A23: 21 | B23: 2135 | C23: Cyber security professionals | D23: 34317.35 | E23: 35283.439 | F23: 36249.304 | G23: 37193.068 | H23: 38033.294 | I23: 38856.335 | J23: 39665.082 | K23: 40476.733 | L23: 41288.105 | M23: 42117.703 | N23: 42935.647 | O23: 43753.192 | P23: 44571.658 | Q23: 45388.347 | R23: 46206.303
A24: 21 | B24: 2136 | C24: IT quality and testing professionals | D24: 32651.609 | E24: 33570.805 | F24: 34489.787 | G24: 35387.742 | H24: 36187.183 | I24: 36970.275 | J24: 37739.765 | K24: 38512.019 | L24: 39284.008 | M24: 40073.338 | N24: 40851.58 | O24: 41629.441 | P24: 42408.179 | Q24: 43185.227 | R24: 43963.48
A25: 21 | B25: 2137 | C25: IT network professionals | D25: 33285.322 | E25: 34222.358 | F25: 35159.176 | G25: 36074.558 | H25: 36889.515 | I25: 37687.806 | J25: 38472.231 | K25: 39259.473 | L25: 40046.445 | M25: 40851.094 | N25: 41644.44 | O25: 42437.399 | P25: 43231.251 | Q25: 44023.379 | R25: 44816.737
A26: 21 | B26: 2139 | C26: Information technology professionals n.e.c. | D26: 140054.08 | E26: 143996.83 | F26: 147938.67 | G26: 151790.3 | H26: 155219.39 | I26: 158578.34 | J26: 161878.95 | K26: 165191.42 | L26: 168502.74 | M26: 171888.45 | N26: 175226.6 | O26: 178563.12 | P26: 181903.4 | Q26: 185236.42 | R26: 188574.62
A27: 21 | B27: 2141 | C27: Web design professionals | D27: 32327.055 | E27: 33237.115 | F27: 34146.962 | G27: 35035.991 | H27: 35827.486 | I27: 36602.794 | J27: 37364.636 | K27: 38129.214 | L27: 38893.53 | M27: 39675.013 | N27: 40445.52 | O27: 41215.649 | P27: 41986.647 | Q27: 42755.97 | R27: 43526.488
A28: 31 | B28: 3131 | C28: IT operations technicians | D28: 116169.53 | E28: 120703.71 | F28: 125238.24 | G28: 129714.43 | H28: 133850.97 | I28: 137937.12 | J28: 141984.51 | K28: 146051.99 | L28: 150128.94 | M28: 154280.97 | N28: 158407.5 | O28: 162542.9 | P28: 166691.89 | Q28: 170843.95 | R28: 175010.17
A29: 31 | B29: 3132 | C29: IT user support technicians | D29: 97668.782 | E29: 101480.86 | F29: 105293.24 | G29: 109056.57 | H29: 112534.34 | I29: 115969.74 | J29: 119372.56 | K29: 122792.27 | L29: 126219.94 | M29: 129710.72 | N29: 133180.08 | O29: 136656.89 | P29: 140145.13 | Q29: 143635.95 | R29: 147138.67
A30: 31 | B30: 3133 | C30: Database administrators and web content technicians | D30: 73218.256 | E30: 76076.016 | F30: 78933.995 | G30: 81755.212 | H30: 84362.35 | I30: 86937.73 | J30: 89488.682 | K30: 92052.297 | L30: 94621.879 | M30: 97238.778 | N30: 99839.612 | O30: 102446.03 | P30: 105061.02 | Q30: 107677.94 | R30: 110303.79
A31: 35 | B31: 3544 | C31: Data analysts | D31: 120821.56 | E31: 121405.93 | F31: 121901.55 | G31: 122277.86 | H31: 122285.97 | I31: 122208.23 | J31: 122072.17 | K31: 121925.38 | L31: 121761.54 | M31: 121628.19 | N31: 121467.56 | O31: 121292.33 | P31: 121107.04 | Q31: 120903.98 | R31: 120691.29
A33: Table 8: Employment by occupation (SOC2020 unit group), human-centric scenario, 2021 to 2035, United Kingdom
A34: SOC2020 sub-major group | B34: SOC2020 unit group | C34: Occupation description | D34: 2021 | E34: 2022 | F34: 2023 | G34: 2024 | H34: 2025 | I34: 2026 | J34: 2027 | K34: 2028 | L34: 2029 | M34: 2030 | N34: 2031 | O34: 2032 | P34: 2033 | Q34: 2034 | R34: 2035
A35: 21 | B35: 2133 | C35: IT business analysts, architects and systems designers | D35: 141764.44 | E35: 145942.69 | F35: 150153.27 | G35: 154280.79 | H35: 157956.45 | I35: 161559.47 | J35: 165104.59 | K35: 168664.16 | L35: 172224.39 | M35: 175862.47 | N35: 179454.02 | O35: 183046.68 | P35: 186644.87 | Q35: 190238.77 | R35: 193840.23
A36: 21 | B36: 2134 | C36: Programmers and software development professionals | D36: 472377.19 | E36: 486299.63 | F36: 500329.83 | G36: 514083.26 | H36: 526331.02 | I36: 538336.73 | J36: 550149.52 | K36: 562010.48 | L36: 573873.61 | M36: 585996.16 | N36: 597963.66 | O36: 609934.85 | P36: 621924.48 | Q36: 633899.83 | R36: 645900.33
A37: 21 | B37: 2135 | C37: Cyber security professionals | D37: 34299.979 | E37: 35310.908 | F37: 36329.661 | G37: 37328.316 | H37: 38217.644 | I37: 39089.395 | J37: 39947.139 | K37: 40808.38 | L37: 41669.779 | M37: 42550.014 | N37: 43418.991 | O37: 44288.237 | P37: 45158.821 | Q37: 46028.368 | R37: 46899.742
A38: 21 | B38: 2136 | C38: IT quality and testing professionals | D38: 32635.081 | E38: 33596.94 | F38: 34566.243 | G38: 35516.425 | H38: 36362.585 | I38: 37192.022 | J38: 38008.131 | K38: 38827.569 | L38: 39647.155 | M38: 40484.665 | N38: 41311.462 | O38: 42138.515 | P38: 42966.842 | Q38: 43794.181 | R38: 44623.259
A39: 21 | B39: 2137 | C39: IT network professionals | D39: 33268.473 | E39: 34249 | F39: 35237.116 | G39: 36205.739 | H39: 37068.321 | I39: 37913.857 | J39: 38745.805 | K39: 39581.146 | L39: 40416.64 | M39: 41270.404 | N39: 42113.249 | O39: 42956.353 | P39: 43800.756 | Q39: 44644.153 | R39: 45489.322
A40: 21 | B40: 2139 | C40: Information technology professionals n.e.c. | D40: 139983.19 | E40: 144108.93 | F40: 148266.61 | G40: 152342.27 | H40: 155971.74 | I40: 159529.49 | J40: 163030.07 | K40: 166544.92 | L40: 170060.41 | M40: 173652.78 | N40: 177199.2 | O40: 180746.72 | P40: 184299.69 | Q40: 187848.44 | R40: 191404.64
A41: 21 | B41: 2141 | C41: Web design professionals | D41: 32310.692 | E41: 33262.99 | F41: 34222.658 | G41: 35163.396 | H41: 36001.145 | I41: 36822.338 | J41: 37630.335 | K41: 38441.627 | L41: 39253.067 | M41: 40082.252 | N41: 40900.831 | O41: 41719.663 | P41: 42539.756 | Q41: 43358.872 | R41: 44179.709
A42: 31 | B42: 3131 | C42: IT operations technicians | D42: 116120.97 | E42: 119953.82 | F42: 123803.33 | G42: 127592.53 | H42: 131020.42 | I42: 134393.32 | J42: 137726.03 | K42: 141076.75 | L42: 144434.92 | M42: 147863.58 | N42: 151267.85 | O42: 154680.52 | P42: 158105.42 | Q42: 161533.98 | R42: 164976.07
A43: 31 | B43: 3132 | C43: IT user support technicians | D43: 97627.952 | E43: 100850.4 | F43: 104086.85 | G43: 107272.6 | H43: 110154.57 | I43: 112990.31 | J43: 115792.27 | K43: 118609.37 | L43: 121432.72 | M43: 124315.35 | N43: 127177.47 | O43: 130046.65 | P43: 132926.11 | Q43: 135808.65 | R43: 138702.56
A44: 31 | B44: 3133 | C44: Database administrators and web content technicians | D44: 73187.647 | E44: 75603.384 | F44: 78029.618 | G44: 80417.84 | H44: 82578.338 | I44: 84704.176 | J44: 86804.686 | K44: 88916.548 | L44: 91033.102 | M44: 93194.088 | N44: 95339.698 | O44: 97490.608 | P44: 99649.218 | Q44: 101810.14 | R44: 103979.59
A45: 35 | B45: 3544 | C45: Data analysts | D45: 120792.5 | E45: 121348.85 | F45: 121847.07 | G45: 122235.77 | H45: 122237.33 | I45: 122155.2 | J45: 122017.72 | K45: 121872.1 | L45: 121711.56 | M45: 121584.09 | N45: 121432.52 | O45: 121268.89 | P45: 121096.57 | Q45: 120908.91 | R45: 120713.42
A48: Data Harmonisation | E48: Check | F48: Result
A49: Before analysis, the Baseline, Technical Opportunities and Human-Centric datasets were checked for completeness, consistency, validity and structural comparability. All three scenarios use the same SOC2020 Unit Group classification, the same 11 selected occupations and the same annual projection period from 2021 to 2035. No missing employment values, duplicate SOC–Year–Scenario records, invalid negative employment values or structural incompatibilities were identified. Employment values were retained in their original numerical form; therefore, no imputation, record removal or scenario-specific transformation was required at this stage. | E49: Missing employment values | F49: 0
E50: Duplicate SOC–Year–Scenario records | F50: 0
E51: Invalid negative employment values | F51: 0
E52: SOC 2133 allocation total | F52: 1
E53: SOC 2139 allocation total | F53: 1
E54: Original versus allocated employment | F54: Reconciled
A56: Career Area Classification & Mixed SOC Treatment
A57: The selected SOC2020 Unit Groups were mapped to the five Computer Science Career Areas using the final classification documented in 06_Career_Area_Map and the supporting Career Map workbook. Unit Groups with a clear occupational fit were assigned directly, while SOC 2133 and 2139 were treated as mixed groups because their Extended SOC Sub-Units span multiple Career Areas.
A58: For Career Area employment analysis, SOC 2133 and 2139 values are proportionally allocated using the validated Adzuna vacancy-search shares. The same allocation is applied consistently across all years and projection scenarios.
A59: Important Distinction: This proportional allocation is used only for Career Area employment and forecast aggregation. Curriculum Overall Alignment remains assessed at SOC Unit Group level and is not proportionally divided for Q4.
A60: Limitation: Adzuna shares are methodological proxy weights based on validated vacancy searches, not official SOC employment weights.
A62: Derived Variables
A63: Derived variables were created to support the research questions and analytical methods used in the project. These measures were calculated from the prepared employment, scenario, technology and curriculum-alignment data where applicable. The table below summarises each derived variable, its calculation or source, unit of measurement and analytical purpose.
A67: Core / Prepared Variables
A68: Variable | B68: Type | C68: Source / Preparation | D68: Unit / Format | E68: Used For
A69: Scenario | B69: Core | C69: DfE employment projection datasets: Baseline, Technical Opportunities, Human-Centric | D69: Category | E69: Q1, Q2
A70: SOC2020 Unit Group | B70: Core | C70: Selected from official DfE datasets; 11 Unit Groups retained | D70: SOC code | E70: Q1, Q2, Q4
A71: Occupation | B71: Core | C71: Occupation description associated with each SOC2020 Unit Group | D71: Text | E71: Q1, Q2, Q4
A72: Year | B72: Core | C72: Annual period retained from source datasets | D72: Year | E72: Q1, Q2, Forecasting
A73: Original Employment | B73: Core | C73: Employment value from the original DfE projection dataset before Career Area allocation | D73: Number of jobs | E73: Q1, Q2
A74: Career Area | B74: Prepared | C74: SOC occupations mapped into the five Computer Science Career Areas using 06_Career_Area_Map | D74: Category | E74: Q1, Q2, Prescriptive Analysis
A75: Allocation Share | B75: Prepared | C75: 100% for standard SOCs; documented Adzuna proxy shares applied to mixed SOCs 2133 and 2139 | D75: Percentage | E75: Q1, Q2, Forecast aggregation
A76: Treatment | B76: Prepared | C76: Identifies whether the SOC is a Full/Standard Unit Group or Mixed Unit Group | D76: Category | E76: Methodological traceability
A77: Technology Trend | B77: Core | C77: WEF Future of Jobs 2025 — UK Economy Profile | D77: Text category | E77: Q3
A78: UK (%) | B78: Core | C78: WEF UK employer expectation for each technology trend | D78: Percentage | E78: Q3
A79: Global (%) | B79: Core | C79: WEF global employer expectation for each technology trend | D79: Percentage | E79: Q3
... A86: APS Employment Estimate | B86: Core / Prepared | C86: ONS Annual Population Survey employment estimates for the selected SOC2020 Unit Groups, 2021–2025 | D86: Number of jobs | E86: Short-term forecasting
A88: Derived Analytical Variables
A89: Variable | B89: Calculation / Definition | C89: Unit / Format | D89: Used For
A90: Allocated Employment | B90: Original Employment × Allocation Share | C90: Number of jobs | D90: Q1, Q2
A91: Career Area Employment | B91: Sum of Allocated Employment by Career Area, Year and Scenario | C91: Number of jobs | D91: Q1, Q2
A92: Absolute Growth | B92: Employment 2035 − Employment 2025 | C92: Number of jobs | D92: Q1
A93: Growth % | B93: (Employment 2035 − Employment 2025) ÷ Employment 2025 × 100 | C93: Percentage | D93: Q1, Q4
A94: Scenario Difference | B94: Alternative Scenario Employment − Baseline Employment | C94: Number of jobs | D94: Q2
A95: Scenario Uplift % | B95: (Alternative Scenario − Baseline) ÷ Baseline × 100 | C95: Percentage | D95: Q2, Prescriptive Analysis
A96: UK–Global Difference | B96: UK % − Global % | C96: Percentage points | D96: Q3
A97: Assessable Sub-Units | B97: Strong + Moderate + Limited + No Clear Evidence | C97: Count | D97: Q4
A98: Gap Share | B98: (Limited + No Clear Evidence) ÷ Assessable Sub-Units | C98: Percentage | D98: Q4
A99: Z Growth % | B99: Standardised Growth % value | C99: Z-score | D99: Q4 Cluster Analysis
A100: Z Gap Share | B100: Standardised Gap Share value | C100: Z-score | D100: Q4 Cluster Analysis
... A112: Forecast–DfE Difference % | B112: (Final Forecast − DfE Baseline) ÷ DfE Baseline × 100 | C112: Percentage | D112: Q2 external benchmark comparison
A114: Preparation Rules & Limitations
A115: Official employment and projection data are available at SOC2020 Unit Group level; equivalent employment data are not available at Extended SOC Sub-Unit level. The documented mixed-SOC methodology addresses this limitation for Career Area aggregation.
A116: Forecasting Note: ONS APS employment estimates for 2021–2025 were used to generate an exploratory short-term 2026 forecast. A 2-Year Moving Average and Simple Exponential Smoothing (α = 0.2, 0.5 and 0.8) were evaluated using MSE over 2023–2025. The selected model was compared with the DfE Baseline 2026 as an external benchmark. Due to the short five-year series, the forecasting exercise is exploratory and is not extended to 2035.
A117: WEF evidence is prepared separately as Extracted / Structured Data from the original report and is not treated as raw government employment data.
A119: Legal & Ethical Considerations
A120: This analysis uses publicly available, aggregated secondary data from official and recognised sources. No personal, identifiable or individual-level data were collected or processed, and no human participants were involved; therefore, consent and anonymisation were not applicable. Original source attribution and links have been retained to support transparency and responsible academic use. Adzuna vacancy-search results were used only in aggregate form as methodological proxy evidence, without collecting applicant or individual-level information. Potential classification and proxy limitations are explicitly acknowledged, and the findings are interpreted at occupational or Career Area level rather than being used to make claims about individual people.

Sheet 06_Career_Area_Map
A1: This table provides the operational SOC-to-Career-Area mapping used to aggregate the official employment projections into the five Computer Science Career Areas. The classification, mixed-SOC methodology and Adzuna-derived allocation calculations are documented in the Career Map & Curriculum Alignment Supporting Workbook, saved on: https://docs.google.com/spreadsheets/d/16bBDBk5eAcaZsfU9kJ7sDSBoUj7RSggH/edit?usp=sharing
A2: Career Area | B2: SOC Unit Group / Sub-Unit | C2: Occupation | D2: Share / Treatment
A3: 1. Software Development & Testing | B3: 2134 | C3: Programmers and software development professionals | D3: Full Unit Group
B4: 2136 | C4: IT quality and testing professionals | D4: Full Unit Group
B5: 2139/01 | C5: DevOps engineers | D5: 46.1% of validated 2139 results
A6: 2. Data, Analytics & Databases | B6: 3544 | C6: Data analysts | D6: Full Unit Group
B7: 3133 | C7: Database administrators and web content technicians | D7: Full Unit Group
B8: 2133/02 + 2133/03 | C8: Data architects + Data engineers | D8: 64.5% of validated 2133 results
A9: 3. Cybersecurity | B9: 2135 | C9: Cyber security professionals | D9: Full Unit Group
A10: 4. Web, Applications & UX/UI | B10: 2141 | C10: Web design professionals | D10: Full Unit Group
B11: 2139/03 | C11: Webmasters / Website managers | D11: 29.0% of validated 2139 results
A12: 5. IT Infrastructure, Networks & Support | B12: 2137 | C12: IT network professionals | D12: Full Unit Group
B13: 3131 | C13: IT operations technicians | D13: Full Unit Group
B14: 3132 | C14: IT user support technicians | D14: Full Unit Group
B15: 2133/04 + 2133/06 | C15: Systems architects + Solution architects | D15: 29.9% of validated 2133 results
A16: Cross-functional / Mixed IT | B16: 2133/01 + 2133/05 | C16: Systems analysts + IT business analysts | D16: 5.6% of validated 2133 results
B17: 2139/02 | C17: IT consultants | D17: 24.9% of validated 2139 results
A18: Mixed SOC Note: SOC 2133 and 2139 span multiple Career Areas and are therefore proportionally allocated using the validated Adzuna vacancy-search shares documented in the supporting Career Map workbook. These shares are methodological proxies and are not official SOC employment weights.
A22: Application: Full Unit Groups are allocated at 100% to their mapped Career Area, while the documented proportional shares are applied to 2133 and 2139 consistently across all years and projection scenarios.

Sheet 07_Analysis_Base
A1: Analysis Base
A2: Consolidated analytical dataset combining the three official employment projection scenarios with the final Career Area mapping and mixed-SOC allocation rules
A3: Scenario Use: Baseline is the primary reference scenario for the main employment growth analysis. Technical Opportunities and Human-Centric are retained as alternative scenarios for comparative analysis of future employment trajectories.
A5: Scenario | B5: SOC Unit Group | C5: Year | D5: Occupation | E5: Career Area | F5: Allocation Share | G5: Original Employment | H5: Allocated Employment | I5: Treatment
A6: Baseline | B6: 2135 | C6: 2021 | D6: Cyber security professionals | E6: Cybersecurity | F6: 1 | G6: 34245.903 | H6: =G6*F6 -> 34245.903 | I6: Full Unit Group
A7: Baseline | B7: 2135 | C7: 2022 | D7: Cyber security professionals | E7: Cybersecurity | F7: 1 | G7: 34653.141 | H7: =G7*F7 -> 34653.141 | I7: Full Unit Group
A8: Baseline | B8: 2135 | C8: 2023 | D8: Cyber security professionals | E8: Cybersecurity | F8: 1 | G8: 35124.791 | H8: =G8*F8 -> 35124.791 | I8: Full Unit Group
A9: Baseline | B9: 2135 | C9: 2024 | D9: Cyber security professionals | E9: Cybersecurity | F9: 1 | G9: 35618.52 | H9: =G9*F9 -> 35618.52 | I9: Full Unit Group
A10: Baseline | B10: 2135 | C10: 2025 | D10: Cyber security professionals | E10: Cybersecurity | F10: 1 | G10: 36034.67 | H10: =G10*F10 -> 36034.67 | I10: Full Unit Group
A11: Baseline | B11: 2135 | C11: 2026 | D11: Cyber security professionals | E11: Cybersecurity | F11: 1 | G11: 36430.761 | H11: =G11*F11 -> 36430.761 | I11: Full Unit Group
A12: Baseline | B12: 2135 | C12: 2027 | D12: Cyber security professionals | E12: Cybersecurity | F12: 1 | G12: 36813.326 | H12: =G12*F12 -> 36813.326 | I12: Full Unit Group
A13: Baseline | B13: 2135 | C13: 2028 | D13: Cyber security professionals | E13: Cybersecurity | F13: 1 | G13: 37199.286 | H13: =G13*F13 -> 37199.286 | I13: Full Unit Group
A14: Baseline | B14: 2135 | C14: 2029 | D14: Cyber security professionals | E14: Cybersecurity | F14: 1 | G14: 37586.872 | H14: =G14*F14 -> 37586.872 | I14: Full Unit Group
A15: Baseline | B15: 2135 | C15: 2030 | D15: Cyber security professionals | E15: Cybersecurity | F15: 1 | G15: 37991.733 | H15: =G15*F15 -> 37991.733 | I15: Full Unit Group
A16: Baseline | B16: 2135 | C16: 2031 | D16: Cyber security professionals | E16: Cybersecurity | F16: 1 | G16: 38394.72 | H16: =G16*F16 -> 38394.72 | I16: Full Unit Group
A17: Baseline | B17: 2135 | C17: 2032 | D17: Cyber security professionals | E17: Cybersecurity | F17: 1 | G17: 38800.818 | H17: =G17*F17 -> 38800.818 | I17: Full Unit Group
... A680: Human-Centric | B680: 2139 | C680: 2035 | D680: Information technology professionals n.e.c. | E680: Cross-functional / Mixed IT | F680: 0.249 | G680: 191404.64 | H680: =G680*F680 -> 47659.757 | I680: Mixed SOC Allocation
A684: Career Area Annual Aggregation
A685: Aggregated from Allocated Employment by Scenario, Year and Career Area. Cross-functional / Mixed IT is retained for reconciliation but is not treated as one of the five primary Career Areas.
A687: Scenario | B687: Year | C687: Career Area | D687: Total Allocated Employment
A688: Baseline | B688: 2021 | C688: Software Development & Testing | D688: =SUMIFS($H$6:$H$680,$A$6:$A$680,A688,$C$6:$C$680,B688,$E$6:$E$680,C688) -> 568646.59
A689: Baseline | B689: 2021 | C689: Data, Analytics & Databases | D689: =SUMIFS($H$6:$H$680,$A$6:$A$680,A689,$C$6:$C$680,B689,$E$6:$E$680,C689) -> 284910.57
A690: Baseline | B690: 2021 | C690: Cybersecurity | D690: =SUMIFS($H$6:$H$680,$A$6:$A$680,A690,$C$6:$C$680,B690,$E$6:$E$680,C690) -> 34245.903
A691: Baseline | B691: 2021 | C691: Web, Applications & UX/UI | D691: =SUMIFS($H$6:$H$680,$A$6:$A$680,A691,$C$6:$C$680,B691,$E$6:$E$680,C691) -> 72790.875
A692: Baseline | B692: 2021 | C692: IT Infrastructure, Networks & Support | D692: =SUMIFS($H$6:$H$680,$A$6:$A$680,A692,$C$6:$C$680,B692,$E$6:$E$680,C692) -> 288932.74
A693: Baseline | B693: 2021 | C693: Cross-functional / Mixed IT | D693: =SUMIFS($H$6:$H$680,$A$6:$A$680,A693,$C$6:$C$680,B693,$E$6:$E$680,C693) -> 42727.154
A694: Baseline | B694: 2022 | C694: Software Development & Testing | D694: =SUMIFS($H$6:$H$680,$A$6:$A$680,A694,$C$6:$C$680,B694,$E$6:$E$680,C694) -> 575408.7
A695: Baseline | B695: 2022 | C695: Data, Analytics & Databases | D695: =SUMIFS($H$6:$H$680,$A$6:$A$680,A695,$C$6:$C$680,B695,$E$6:$E$680,C695) -> 287261.57
A696: Baseline | B696: 2022 | C696: Cybersecurity | D696: =SUMIFS($H$6:$H$680,$A$6:$A$680,A696,$C$6:$C$680,B696,$E$6:$E$680,C696) -> 34653.141
A697: Baseline | B697: 2022 | C697: Web, Applications & UX/UI | D697: =SUMIFS($H$6:$H$680,$A$6:$A$680,A697,$C$6:$C$680,B697,$E$6:$E$680,C697) -> 73656.474
A698: Baseline | B698: 2022 | C698: IT Infrastructure, Networks & Support | D698: =SUMIFS($H$6:$H$680,$A$6:$A$680,A698,$C$6:$C$680,B698,$E$6:$E$680,C698) -> 291526.59
A699: Baseline | B699: 2022 | C699: Cross-functional / Mixed IT | D699: =SUMIFS($H$6:$H$680,$A$6:$A$680,A699,$C$6:$C$680,B699,$E$6:$E$680,C699) -> 43235.247
... A957: Human-Centric | B957: 2035 | C957: Cross-functional / Mixed IT | D957: =SUMIFS($H$6:$H$680,$A$6:$A$680,A957,$C$6:$C$680,B957,$E$6:$E$680,C957) -> 58514.809

Sheet 08_WEF_Technology
A1: WEF Technology Trends — Extracted / Structured Data from the United Kingdom Economy Profile, Future of Jobs Report 2025
A2: ID | B2: Technology Trend driving business transformation | C2: Category | D2: UK (%) | E2: Global (%) | F2: Difference (UK - Global) | G2: Net Effect (Million Jobs) | H2: Primary Related Area | I2: Use in Analysis | J2: Notes
A3: 1 | B3: AI and information processing technologies (Big Data, Virtual Reality, Augmented Reality, etc.) | C3: Technology Driver | D3: 92 | E3: 86 | F3: =D3-E3 -> 6 | G3: 1.8 | H3: Data, Analytics & Databases | I3: Yes | J3: Main driving technology.
A4: 2 | B4: Robots and autonomous systems | C4: Technology Driver | D4: 62 | E4: 58 | F4: =D4-E4 -> 4 | G4: -4.8 | H4: Software Development & Testing | I4: Yes | J4: Automation and applied AI.
A5: 3 | B5: Energy generation, storage and distribution | C5: Technology Driver | D5: 40 | E5: 41 | F5: =D5-E5 -> -1 | G5: 1 | H5: Outside Scope | I5: No | J5: Not directly related to the five areas.
A6: 4 | B6: Semiconductors and computing technologies | C6: Technology Driver | D6: 33 | E6: 20 | F6: =D6-E6 -> 13 | G6: 0.6 | H6: IT Infrastructure, Networks & Support | I6: Yes | J6: Infrastructure, hardware, and cloud computing.
A7: 5 | B7: New materials and composites | C7: Technology Driver | D7: 32 | E7: 30 | F7: =D7-E7 -> 2 | G7: 0.9 | H7: Outside Scope | I7: No | J7: Focus on materials engineering.
A8: 6 | B8: Sensing, laser and optical technologies | C8: Technology Driver | D8: 24 | E8: 18 | F8: =D8-E8 -> 6 | G8: 0.1 | H8: Outside Scope | I8: No | J8: Limited relevance to the project.
A9: 7 | B9: Quantum and encryption | C9: Technology Driver | D9: 23 | E9: 12 | F9: =D9-E9 -> 11 | G9: 0.3 | H9: Cybersecurity | I9: Yes | J9: Strong connection to information security.
A10: 8 | B10: Biotechnology and gene technologies | C10: Technology Driver | D10: 15 | E10: 11 | F10: =D10-E10 -> 4 | G10: 0.2 | H10: Outside Scope | I10: No | J10: Not related to the project's focus.
A11: 9 | B11: Satellites and space technologies | C11: Technology Driver | D11: 10 | E11: 9 | F11: =D11-E11 -> 1 | G11: 0.1 | H11: Outside Scope | I11: No | J11: Low relevance to the five areas.
A12: The UK (%) and Global (%) values were extracted from the "Technology Trends" section of the WEF Economy Profile – United Kingdom.
A13: Source: World Economic Forum, Future of Jobs Report 2025, United Kingdom Economy Profile. https://www.weforum.org/publications/the-future-of-jobs-report-2025/
A14: The Net Effect (Million Jobs) values were extracted from Figure 2.6 – "Expected impact of macrotrends and technology trends on jobs, 2025–2030" of the WEF Future of Jobs Report 2025.
A15: Net Effect (Million Jobs): The overall change in employment after subtracting jobs lost from jobs created, measured in millions of jobs, is global WEF contextual evidence and is not used in the UK–Global regression or as a direct measure of Computer Science employment.

Sheet 09_WEF_Jobs_Outlook
A1: WEF Jobs Outlook — Extracted / Structured Data from the United Kingdom Economy Profile, Future of Jobs Report 2025
A2: ID | B2: Occupation | C2: UK Net Growth (%) | D2: Global Net Growth (%) | E2: Structural Churn (%) | F2: Primary Related Area | G2: Use in Analysis | H2: Notes
A3: 1 | B3: Big Data Specialists | C3: 319 | D3: 113 | E3: 320 | F3: Data, Analytics & Databases | G3: Yes | H3: Highest net growth in the United Kingdom.
A4: 2 | B4: AI and Machine Learning Specialists | C4: 151 | D4: 82 | E4: 151 | F4: Data, Analytics & Databases | G4: Yes | H4: AI is one of the main drivers of these careers.
A5: 3 | B5: Data Analysts and Scientists | C5: 29 | D5: 41 | E5: 29 | F5: Data, Analytics & Databases | G5: Yes | H5: Directly related to data analytics.
A6: 4 | B6: Business Development Professionals | C6: 14 | D6: 19 | E6: 15 | F6: Outside Scope | G6: No | H6: Outside the five Computer Science areas.
A7: 5 | B7: General and Operations Managers | C7: -4 | D7: 4 | E7: 9 | F7: Outside Scope | G7: No | H7: Management role; does not represent a technical specialization.
A8: 6 | B8: Data Entry Clerks | C8: -26 | D8: -26 | E8: 26 | F8: Outside Scope | G8: No | H8: Declining occupation; does not represent Data Analytics.
A9: Source: World Economic Forum, Future of Jobs Report 2025, United Kingdom Economy Profile. https://www.weforum.org/publications/the-future-of-jobs-report-2025/
A10: Source Note: World Economic Forum, Future of Jobs Report 2025 — United Kingdom Economy Profile, “Jobs outlook – Key roles for business transformation”.
A11: Analytical Note: WEF Jobs Outlook values are survey-based percentage indicators of expected occupational change and are used as complementary future-trend evidence. They are not employment counts and are not directly combined with the official DfE employment projections.
A12: Net Growth (%): The projected net change in employment for the occupation, expressed as a percentage. Positive values indicate growth, while negative values indicate decline.
A13: Structural Churn (%): The combined scale of job growth and job displacement associated with the occupation, indicating the expected degree of employment transformation.

Sheet 10_WEF_AI_Strategy
A1: WEF AI Strategy — Extracted / Structured Data from the United Kingdom Economy Profile, Future of Jobs Report 2025
A2: ID | B2: AI Strategy | C2: Category | D2: UK (%) | E2: Global (%) | F2: Difference (UK - Global) | G2: Primary Related Area | H2: Use in Analysis | I2: Notes
A3: 1 | B3: Reskilling and upskilling the existing workforce to better work alongside AI | C3: Workforce Development | D3: 90 | E3: 77 | F3: =D3-E3 -> 13 | G3: All Areas | H3: Yes | I3: Primary strategy adopted by organizations in the United Kingdom.
A4: 2 | B4: Hiring new people with skills to design AI tools and enhancements appropriate for the organization | C4: AI Talent Acquisition | D4: 74 | E4: 69 | F4: =D4-E4 -> 5 | G4: Data, Analytics & Databases | H4: Yes | I4: Demonstrates strong demand for AI-related skills.
A5: 3 | B5: Hiring new people with skills to better work alongside AI | C5: AI Workforce Integration | D5: 66 | E5: 62 | F5: =D5-E5 -> 4 | G5: All Areas | H5: Yes | I5: Reinforces the need for skills to work with AI.
A6: Source: World Economic Forum, Future of Jobs Report 2025, United Kingdom Economy Profile. https://www.weforum.org/publications/the-future-of-jobs-report-2025/
A7: Source Note: Data extracted from the AI Strategy section of the World Economic Forum, Future of Jobs Report 2025 — United Kingdom Economy Profile.

Sheet 11_WEF_Skills_Outlook
A1: WEF Skills Outlook — Extracted / Structured Data from the United Kingdom Economy Profile, Future of Jobs Report 2025
A2: Core Skills of 2025
A3: ID | B3: Skill | C3: Category | D3: UK (%) | E3: Global position vs UK | F3: Primary Related Area | G3: Use in Analysis | H3: Notes
A4: 1 | B4: Analytical thinking | C4: Core Skill (2025) | D4: 80 | E4: Below UK | F4: All Areas | G4: Yes | H4: Cross-cutting skill across all Computer Science areas.
A5: 2 | B5: Resilience, flexibility and agility | C5: Core Skill (2025) | D5: 73 | E5: Below UK | F5: All Areas | G5: Yes | H5: Important for adapting to technological change.
A6: 3 | B6: Leadership and social influence | C6: Core Skill (2025) | D6: 65 | E6: Below UK | F6: All Areas | G6: Partial | H6: Complementary skill.
A7: 4 | B7: Creative thinking | C7: Core Skill (2025) | D7: 62 | E7: Below UK | F7: Web, Applications & UX/UI | G7: Yes | H7: Particularly relevant to UX/UI, but valuable across all areas.
A8: 5 | B8: Motivation and self-awareness | C8: Core Skill (2025) | D8: 56 | E8: Below UK | F8: All Areas | G8: Partial | H8: Behavioral skill.
A10: Skills of Increasing Use by 2030
A11: ID | B11: Skill | C11: Category | D11: UK (%) | E11: Global position vs UK | F11: Primary Related Area | G11: Use in Analysis | H11: Notes
A12: 6 | B12: AI and big data | C12: Increasing Skill (2030) | D12: 92 | E12: Below UK | F12: Data, Analytics & Databases | G12: Yes | H12: Technical skill with the highest expected growth.
A13: 7 | B13: Networks and cybersecurity | C13: Increasing Skill (2030) | D13: 71 | E13: Slightly above UK | F13: Cybersecurity | G13: Yes | H13: Directly related to information security.
A14: 8 | B14: Technological literacy | C14: Increasing Skill (2030) | D14: 71 | E14: Approximately aligned with UK | F14: All Areas | G14: Yes | H14: Cross-cutting skill; the exact Global percentage is not numerically reported, although the Global benchmark is shown graphically.
A15: 9 | B15: Resilience, flexibility and agility | C15: Increasing Skill (2030) | D15: 69 | E15: Slightly below UK | F15: All Areas | G15: Partial | H15: Important behavioral skill.
A16: 10 | B16: Curiosity and lifelong learning | C16: Increasing Skill (2030) | D16: 68 | E16: Below UK | F16: All Areas | G16: Yes | H16: Essential for keeping pace with technological advancement.
A17: Source: World Economic Forum, Future of Jobs Report 2025, United Kingdom Economy Profile. https://www.weforum.org/publications/the-future-of-jobs-report-2025/
A18: Source Note: Data extracted from the Skill Outlook section of the World Economic Forum, Future of Jobs Report 2025 — United Kingdom Economy Profile.
A19: Global Comparison Note: Exact Global percentages are not numerically reported in the source. Global benchmarks are displayed graphically using markers; therefore, the comparison is recorded qualitatively as above, below or approximately aligned with the UK value rather than estimating exact percentages.

Sheet 12_WEF_Fastest_Growing
A1: WEF Fastest-Growing Jobs — Extracted / Structured Data from the Future of Jobs Report 2025
A2: Rank | B2: Occupation | C2: Primary Related Area | D2: In Scope
A3: 1 | B3: Big Data Specialists | C3: Data, Analytics & Databases | D3: Yes
A4: 2 | B4: FinTech Engineers | C4: Software Development & Testing | D4: Yes
A5: 3 | B5: AI and Machine Learning Specialists | C5: Data, Analytics & Databases | D5: Yes
A6: 4 | B6: Software and Applications Developers | C6: Software Development & Testing | D6: Yes
A7: 5 | B7: Security Management Specialists | C7: Cybersecurity | D7: Yes
A8: 6 | B8: Data Warehousing Specialists | C8: Data, Analytics & Databases | D8: Yes
A9: 7 | B9: Autonomous and Electric Vehicle Specialists | C9: Outside Scope | D9: No
A10: 8 | B10: UI and UX Designers | C10: Web, Applications & UX/UI | D10: Yes
A11: 9 | B11: Light Truck or Delivery Services Drivers | C11: Outside Scope | D11: No
A12: 10 | B12: Internet of Things Specialists | C12: IT Infrastructure, Networks & Support | D12: Yes
A13: 11 | B13: Data Analysts and Scientists | C13: Data, Analytics & Databases | D13: Yes
A14: 12 | B14: Environmental Engineers | C14: Outside Scope | D14: No
... A17: 15 | B17: Renewable Energy Engineers | C17: Outside Scope | D17: No
A18: Source: World Economic Forum, Future of Jobs Report 2025, Figure 2.2, “Fastest-growing and fastest-declining jobs, 2025–2030”. https://www.weforum.org/publications/the-future-of-jobs-report-2025/
A19: Source Note: Data extracted from Figure 2.2, “Fastest-growing and fastest-declining jobs, 2025–2030”, World Economic Forum, Future of Jobs Report 2025.
A20: Scope Note: Figure 2.2 presents global fastest-growing occupations based on the WEF Future of Jobs Survey 2024. It is used as complementary global evidence of occupational growth trends and should not be interpreted as a UK-specific employment projection.

Sheet 13_Descriptive_Q1
A1: Field | B1: Content | H1: Between 2025 and 2035, all five Computer Science Career Areas are projected to increase employment under the Baseline scenario. Software Development & Testing shows the largest absolute job creation (+66,470 jobs) and one of the highest proportional growth rates (11.1%). Cybersecurity and Web, Applications & UX/UI also show approximately 11.1% growth, but their smaller employment bases result in lower absolute job creation. IT Infrastructure, Networks & Support and Data, Analytics & Databases show lower proportional growth of 8.3% and 7.4%, respectively, while still adding more jobs in absolute terms than some faster-growing smaller areas.
A2: Analytics Type | B2: Descriptive
A3: Research Question | B3: Q1. How do employment growth and job creation differ across the five Career Areas?
A4: Purpose | B4: Compare employment scale, absolute job creation and percentage growth across the five Career Areas.
A5: Method(s) | B5: Descriptive Analysis; Absolute Growth; Growth %
A6: Dataset(s) | B6: 07_Analysis_Base — Baseline scenario
A7: Unit of Analysis | B7: Career Area
A8: Comparison Period | B8: 2025–2035
A10: Reconciliation Note: Cross-functional / Mixed IT is retained in the Analysis Base for reconciliation of mixed SOC allocations but is excluded from the five-Career-Area comparison presented in Q1.
A11: Methodological Note: Employment totals use the Career Area allocations prepared in 07_Analysis_Base. Mixed SOC Unit Groups 2133 and 2139 are proportionally allocated using the documented Adzuna methodological proxy; these shares are not official SOC employment weights.
B16: Area Computer Science | C16: 2025 Employment | D16: 2035 Employment | E16: Growth % | F16: Absolute Growth | H16: Which of the five CS Career Areas are projected to show the strongest employment growth between 2025 and 2035?
B17: Software Development & Testing | C17: 598348.73 | D17: 664818.79 | E17: =(D17-C17)/C17 -> 0.11108918 | F17: =D17-C17 -> 66470.067
B18: Cybersecurity | C18: 36034.67 | D18: 40037.732 | E18: =(D18-C18)/C18 -> 0.11108918 | F18: =D18-C18 -> 4003.0618
B19: Web, Applications & UX/UI | C19: 76592.963 | D19: 85101.612 | E19: =(D19-C19)/C19 -> 0.11108918 | F19: =D19-C19 -> 8508.6492
B20: IT Infrastructure, Networks & Support | C20: 300551.2 | D20: 325423.34 | E20: =(D20-C20)/C20 -> 0.082755087 | F20: =D20-C20 -> 24872.141
B21: Data, Analytics & Databases | C21: 295489.76 | D21: 317390.55 | E21: =(D21-C21)/C21 -> 0.074116912 | F21: =D21-C21 -> 21900.789
H38: Source: Author’s calculations based on Department for Education employment projections, Baseline scenario.
H39: Software Development & Testing, Cybersecurity, and Web, Applications & UX/UI show the strongest projected employment growth, each increasing by approximately 11.1% between 2025 and 2035. IT Infrastructure, Networks & Support is also expected to grow at 8.28%, while Data, Analytics & Databases shows the lowest projected growth among the five Career Areas, at 7.41%.
B46: Area Computer Science | C46: 2025 Employment | D46: 2035 Employment | E46: Growth % | F46: Absolute Growth | H46: Which of the five CS Career Areas are projected to create the largest number of additional jobs between 2025 and 2035?
B47: Software Development & Testing | C47: 598348.73 | D47: 664818.79 | E47: =(D47-C47)/C47 -> 0.11108918 | F47: =D47-C47 -> 66470.067
B48: IT Infrastructure, Networks & Support | C48: 300551.2 | D48: 325423.34 | E48: =(D48-C48)/C48 -> 0.082755087 | F48: =D48-C48 -> 24872.141
B49: Data, Analytics & Databases | C49: 295489.76 | D49: 317390.55 | E49: =(D49-C49)/C49 -> 0.074116912 | F49: =D49-C49 -> 21900.789
B50: Web, Applications & UX/UI | C50: 76592.963 | D50: 85101.612 | E50: =(D50-C50)/C50 -> 0.11108918 | F50: =D50-C50 -> 8508.6492
B51: Cybersecurity | C51: 36034.67 | D51: 40037.732 | E51: =(D51-C51)/C51 -> 0.11108918 | F51: =D51-C51 -> 4003.0618
H66: Source: Author’s calculations based on Department for Education employment projections, Baseline scenario.
H67: Software Development & Testing is projected to create the largest number of additional jobs between 2025 and 2035, adding approximately 66,470 positions. IT Infrastructure, Networks & Support follows with around 24,872 additional jobs, while Data, Analytics & Databases is projected to add approximately 21,901. Although Web, Applications & UX/UI and Cybersecurity show strong proportional growth, their smaller employment bases result in lower absolute job creation of approximately 8,509 and 4,003 jobs, respectively.

Sheet 14_Predictive_Q2
A1: Section 1 — Analytical Framework
A2: Field | B2: Content
A3: Analytics Type | B3: Predictive-oriented
A4: Research Question | B4: Q2. How do employment projections change over time and across future scenarios?
A5: Purpose | B5: Examine long-term employment projections across the five Career Areas and alternative future scenarios, and complement these projections with an exploratory short-term forecast based on recent Annual Population Survey (APS) employment estimates.
A6: Method(s) | B6: Time Series Analysis; 2-Year Moving Average; Simple Exponential Smoothing; MSE Model Comparison; Scenario Comparison
A7: Dataset(s) | B7: 07_Analysis_Base — DfE Baseline, Technical Opportunities and Human-Centric projections; 14A — ONS Annual Population Survey employment estimates, 2021–2025
A8: Unit of Analysis | B8: Career Area by Year and Scenario; Career Area for short-term forecast comparison
A9: Period | B9: DfE projections: 2021–2035; APS estimates: 2021–2025; exploratory forecast: 2026
A10: Methodological Note: This analysis combines externally produced DfE employment projections with an exploratory short-term forecast generated from ONS APS employment estimates for 2021–2025. A 2-year Moving Average and Simple Exponential Smoothing (α = 0.2, 0.5 and 0.8) were evaluated using Mean Squared Error (MSE) over the common validation period 2023–2025. The best-performing method for each Career Area was used to generate a 2026 forecast. Due to the short five-year time series, the forecast is exploratory and is not extended to 2035. Mixed SOC Unit Groups 2133 and 2139 use the proportional allocations already applied in 07_Analysis_Base. The Q3 regression was used to examine the Global–UK relationship rather than to forecast employment and was therefore not included in the MSE model comparison.
A11: Reconciliation Note: Cross-functional / Mixed IT is retained in the Analysis Base for reconciliation but excluded from the five-Career-Area comparison.
A12: Model Selection Result: Simple Exponential Smoothing (SES) with α = 0.8 produced the lowest MSE for Software Development & Testing, Data, Analytics & Databases, Cybersecurity, and IT Infrastructure, Networks & Support. SES with α = 0.2 produced the lowest MSE for Web, Applications & UX/UI. The 2-Year Moving Average did not produce the lowest MSE for any Career Area.
A14: Section 2 — Career Area Time-Series Data
B16: Career Area | C16: Year | D16: Baseline | E16: Technical Opportunities | F16: Human-Centric
B17: Software Development & Testing | C17: 2021 | D17: =SUMIFS('07_Analysis_Base'!$D$688:$D$957,'07_Analysis_Base'!$A$688:$A$957,D$16,'07_Analysis_Base'!$B$688:$B$957,$C17,'07_Analysis_Base'!$C$688:$C$957,$B17) -> 568646.59 | E17: =SUMIFS('07_Analysis_Base'!$D$688:$D$957,'07_Analysis_Base'!$A$688:$A$957,E$16,'07_Analysis_Base'!$B$688:$B$957,$C17,'07_Analysis_Base'!$C$688:$C$957,$B17) -> 569832.96 | F17: =SUMIFS('07_Analysis_Base'!$D$688:$D$957,'07_Analysis_Base'!$A$688:$A$957,F$16,'07_Analysis_Base'!$B$688:$B$957,$C17,'07_Analysis_Base'!$C$688:$C$957,$B17) -> 569544.52
B18: Software Development & Testing | C18: 2022 | D18: =SUMIFS('07_Analysis_Base'!$D$688:$D$957,'07_Analysis_Base'!$A$688:$A$957,D$16,'07_Analysis_Base'!$B$688:$B$957,$C18,'07_Analysis_Base'!$C$688:$C$957,$B18) -> 575408.7 | E18: =SUMIFS('07_Analysis_Base'!$D$688:$D$957,'07_Analysis_Base'!$A$688:$A$957,E$16,'07_Analysis_Base'!$B$688:$B$957,$C18,'07_Analysis_Base'!$C$688:$C$957,$B18) -> 585874.68 | F18: =SUMIFS('07_Analysis_Base'!$D$688:$D$957,'07_Analysis_Base'!$A$688:$A$957,F$16,'07_Analysis_Base'!$B$688:$B$957,$C18,'07_Analysis_Base'!$C$688:$C$957,$B18) -> 586330.79
B19: Software Development & Testing | C19: 2023 | D19: =SUMIFS('07_Analysis_Base'!$D$688:$D$957,'07_Analysis_Base'!$A$688:$A$957,D$16,'07_Analysis_Base'!$B$688:$B$957,$C19,'07_Analysis_Base'!$C$688:$C$957,$B19) -> 583240.36 | E19: =SUMIFS('07_Analysis_Base'!$D$688:$D$957,'07_Analysis_Base'!$A$688:$A$957,E$16,'07_Analysis_Base'!$B$688:$B$957,$C19,'07_Analysis_Base'!$C$688:$C$957,$B19) -> 601912.68 | F19: =SUMIFS('07_Analysis_Base'!$D$688:$D$957,'07_Analysis_Base'!$A$688:$A$957,F$16,'07_Analysis_Base'!$B$688:$B$957,$C19,'07_Analysis_Base'!$C$688:$C$957,$B19) -> 603246.99
B20: Software Development & Testing | C20: 2024 | D20: =SUMIFS('07_Analysis_Base'!$D$688:$D$957,'07_Analysis_Base'!$A$688:$A$957,D$16,'07_Analysis_Base'!$B$688:$B$957,$C20,'07_Analysis_Base'!$C$688:$C$957,$B20) -> 591438.63 | E20: =SUMIFS('07_Analysis_Base'!$D$688:$D$957,'07_Analysis_Base'!$A$688:$A$957,E$16,'07_Analysis_Base'!$B$688:$B$957,$C20,'07_Analysis_Base'!$C$688:$C$957,$B20) -> 617583.71 | F20: =SUMIFS('07_Analysis_Base'!$D$688:$D$957,'07_Analysis_Base'!$A$688:$A$957,F$16,'07_Analysis_Base'!$B$688:$B$957,$C20,'07_Analysis_Base'!$C$688:$C$957,$B20) -> 619829.47
B21: Software Development & Testing | C21: 2025 | D21: =SUMIFS('07_Analysis_Base'!$D$688:$D$957,'07_Analysis_Base'!$A$688:$A$957,D$16,'07_Analysis_Base'!$B$688:$B$957,$C21,'07_Analysis_Base'!$C$688:$C$957,$B21) -> 598348.73 | E21: =SUMIFS('07_Analysis_Base'!$D$688:$D$957,'07_Analysis_Base'!$A$688:$A$957,E$16,'07_Analysis_Base'!$B$688:$B$957,$C21,'07_Analysis_Base'!$C$688:$C$957,$B21) -> 631535.48 | F21: =SUMIFS('07_Analysis_Base'!$D$688:$D$957,'07_Analysis_Base'!$A$688:$A$957,F$16,'07_Analysis_Base'!$B$688:$B$957,$C21,'07_Analysis_Base'!$C$688:$C$957,$B21) -> 634596.58
B22: Software Development & Testing | C22: 2026 | D22: =SUMIFS('07_Analysis_Base'!$D$688:$D$957,'07_Analysis_Base'!$A$688:$A$957,D$16,'07_Analysis_Base'!$B$688:$B$957,$C22,'07_Analysis_Base'!$C$688:$C$957,$B22) -> 604925.74 | E22: =SUMIFS('07_Analysis_Base'!$D$688:$D$957,'07_Analysis_Base'!$A$688:$A$957,E$16,'07_Analysis_Base'!$B$688:$B$957,$C22,'07_Analysis_Base'!$C$688:$C$957,$B22) -> 645201.93 | F22: =SUMIFS('07_Analysis_Base'!$D$688:$D$957,'07_Analysis_Base'!$A$688:$A$957,F$16,'07_Analysis_Base'!$B$688:$B$957,$C22,'07_Analysis_Base'!$C$688:$C$957,$B22) -> 649071.85
B23: Software Development & Testing | C23: 2027 | D23: =SUMIFS('07_Analysis_Base'!$D$688:$D$957,'07_Analysis_Base'!$A$688:$A$957,D$16,'07_Analysis_Base'!$B$688:$B$957,$C23,'07_Analysis_Base'!$C$688:$C$957,$B23) -> 611278.15 | E23: =SUMIFS('07_Analysis_Base'!$D$688:$D$957,'07_Analysis_Base'!$A$688:$A$957,E$16,'07_Analysis_Base'!$B$688:$B$957,$C23,'07_Analysis_Base'!$C$688:$C$957,$B23) -> 658631.01 | F23: =SUMIFS('07_Analysis_Base'!$D$688:$D$957,'07_Analysis_Base'!$A$688:$A$957,F$16,'07_Analysis_Base'!$B$688:$B$957,$C23,'07_Analysis_Base'!$C$688:$C$957,$B23) -> 663314.51
B24: Software Development & Testing | C24: 2028 | D24: =SUMIFS('07_Analysis_Base'!$D$688:$D$957,'07_Analysis_Base'!$A$688:$A$957,D$16,'07_Analysis_Base'!$B$688:$B$957,$C24,'07_Analysis_Base'!$C$688:$C$957,$B24) -> 617686.94 | E24: =SUMIFS('07_Analysis_Base'!$D$688:$D$957,'07_Analysis_Base'!$A$688:$A$957,E$16,'07_Analysis_Base'!$B$688:$B$957,$C24,'07_Analysis_Base'!$C$688:$C$957,$B24) -> 672108.32 | F24: =SUMIFS('07_Analysis_Base'!$D$688:$D$957,'07_Analysis_Base'!$A$688:$A$957,F$16,'07_Analysis_Base'!$B$688:$B$957,$C24,'07_Analysis_Base'!$C$688:$C$957,$B24) -> 677615.26
B25: Software Development & Testing | C25: 2029 | D25: =SUMIFS('07_Analysis_Base'!$D$688:$D$957,'07_Analysis_Base'!$A$688:$A$957,D$16,'07_Analysis_Base'!$B$688:$B$957,$C25,'07_Analysis_Base'!$C$688:$C$957,$B25) -> 624122.74 | E25: =SUMIFS('07_Analysis_Base'!$D$688:$D$957,'07_Analysis_Base'!$A$688:$A$957,E$16,'07_Analysis_Base'!$B$688:$B$957,$C25,'07_Analysis_Base'!$C$688:$C$957,$B25) -> 685581 | F25: =SUMIFS('07_Analysis_Base'!$D$688:$D$957,'07_Analysis_Base'!$A$688:$A$957,F$16,'07_Analysis_Base'!$B$688:$B$957,$C25,'07_Analysis_Base'!$C$688:$C$957,$B25) -> 691918.61
B26: Software Development & Testing | C26: 2030 | D26: =SUMIFS('07_Analysis_Base'!$D$688:$D$957,'07_Analysis_Base'!$A$688:$A$957,D$16,'07_Analysis_Base'!$B$688:$B$957,$C26,'07_Analysis_Base'!$C$688:$C$957,$B26) -> 630845.37 | E26: =SUMIFS('07_Analysis_Base'!$D$688:$D$957,'07_Analysis_Base'!$A$688:$A$957,E$16,'07_Analysis_Base'!$B$688:$B$957,$C26,'07_Analysis_Base'!$C$688:$C$957,$B26) -> 699356.31 | F26: =SUMIFS('07_Analysis_Base'!$D$688:$D$957,'07_Analysis_Base'!$A$688:$A$957,F$16,'07_Analysis_Base'!$B$688:$B$957,$C26,'07_Analysis_Base'!$C$688:$C$957,$B26) -> 706534.76
B27: Software Development & Testing | C27: 2031 | D27: =SUMIFS('07_Analysis_Base'!$D$688:$D$957,'07_Analysis_Base'!$A$688:$A$957,D$16,'07_Analysis_Base'!$B$688:$B$957,$C27,'07_Analysis_Base'!$C$688:$C$957,$B27) -> 637536.89 | E27: =SUMIFS('07_Analysis_Base'!$D$688:$D$957,'07_Analysis_Base'!$A$688:$A$957,E$16,'07_Analysis_Base'!$B$688:$B$957,$C27,'07_Analysis_Base'!$C$688:$C$957,$B27) -> 712938.12 | F27: =SUMIFS('07_Analysis_Base'!$D$688:$D$957,'07_Analysis_Base'!$A$688:$A$957,F$16,'07_Analysis_Base'!$B$688:$B$957,$C27,'07_Analysis_Base'!$C$688:$C$957,$B27) -> 720963.95
B28: Software Development & Testing | C28: 2032 | D28: =SUMIFS('07_Analysis_Base'!$D$688:$D$957,'07_Analysis_Base'!$A$688:$A$957,D$16,'07_Analysis_Base'!$B$688:$B$957,$C28,'07_Analysis_Base'!$C$688:$C$957,$B28) -> 644280.08 | E28: =SUMIFS('07_Analysis_Base'!$D$688:$D$957,'07_Analysis_Base'!$A$688:$A$957,E$16,'07_Analysis_Base'!$B$688:$B$957,$C28,'07_Analysis_Base'!$C$688:$C$957,$B28) -> 726513.29 | F28: =SUMIFS('07_Analysis_Base'!$D$688:$D$957,'07_Analysis_Base'!$A$688:$A$957,F$16,'07_Analysis_Base'!$B$688:$B$957,$C28,'07_Analysis_Base'!$C$688:$C$957,$B28) -> 735397.61
... B91: IT Infrastructure, Networks & Support | C91: 2035 | D91: =SUMIFS('07_Analysis_Base'!$D$688:$D$957,'07_Analysis_Base'!$A$688:$A$957,D$16,'07_Analysis_Base'!$B$688:$B$957,$C91,'07_Analysis_Base'!$C$688:$C$957,$B91) -> 325423.34 | E91: =SUMIFS('07_Analysis_Base'!$D$688:$D$957,'07_Analysis_Base'!$A$688:$A$957,E$16,'07_Analysis_Base'!$B$688:$B$957,$C91,'07_Analysis_Base'!$C$688:$C$957,$B91) -> 424066.86 | F91: =SUMIFS('07_Analysis_Base'!$D$688:$D$957,'07_Analysis_Base'!$A$688:$A$957,F$16,'07_Analysis_Base'!$B$688:$B$957,$C91,'07_Analysis_Base'!$C$688:$C$957,$B91) -> 407126.18
A93: Section 3 — Employment Trajectory
A94: Chart A — Baseline Employment Trajectories, 2021–2035
A96: Year | B96: Software Development & Testing | C96: Data, Analytics & Databases | D96: Cybersecurity | E96: Web, Applications & UX/UI | F96: IT Infrastructure, Networks & Support
A97: =C17 -> 2021 | B97: =D17 -> 568646.59 | C97: =D32 -> 284910.57 | D97: =D47 -> 34245.903 | E97: =D62 -> 72790.875 | F97: =D77 -> 288932.74
A98: =C18 -> 2022 | B98: =D18 -> 575408.7 | C98: =D33 -> 287261.57 | D98: =D48 -> 34653.141 | E98: =D63 -> 73656.474 | F98: =D78 -> 291526.59
A99: =C19 -> 2023 | B99: =D19 -> 583240.36 | C99: =D34 -> 290091.06 | D99: =D49 -> 35124.791 | E99: =D64 -> 74658.983 | F99: =D79 -> 294624.33
A100: =C20 -> 2024 | B100: =D20 -> 591438.63 | C100: =D35 -> 293106.39 | D100: =D50 -> 35618.52 | E100: =D65 -> 75708.421 | F100: =D80 -> 297908.17
A101: =C21 -> 2025 | B101: =D21 -> 598348.73 | C101: =D36 -> 295489.76 | D101: =D51 -> 36034.67 | E101: =D66 -> 76592.963 | F101: =D81 -> 300551.2
A102: =C22 -> 2026 | B102: =D22 -> 604925.74 | C102: =D37 -> 297686.55 | D102: =D52 -> 36430.761 | E102: =D67 -> 77434.869 | F102: =D82 -> 303017.38
A103: =C23 -> 2027 | B103: =D23 -> 611278.15 | C103: =D38 -> 299769.56 | D103: =D53 -> 36813.326 | E103: =D68 -> 78248.023 | F103: =D83 -> 305369.98
A104: =C24 -> 2028 | B104: =D24 -> 617686.94 | C104: =D39 -> 301867.24 | D104: =D54 -> 37199.286 | E104: =D69 -> 79068.395 | F104: =D84 -> 307746.91
A105: =C25 -> 2029 | B105: =D25 -> 624122.74 | C105: =D40 -> 303970.32 | D105: =D55 -> 37586.872 | E105: =D70 -> 79892.224 | F105: =D85 -> 310135.19
A106: =C26 -> 2030 | B106: =D26 -> 630845.37 | C106: =D41 -> 306197.94 | D106: =D56 -> 37991.733 | E106: =D71 -> 80752.769 | F106: =D86 -> 312659.81
A107: =C27 -> 2031 | B107: =D27 -> 637536.89 | C107: =D42 -> 308403.84 | D107: =D57 -> 38394.72 | E107: =D72 -> 81609.332 | F107: =D87 -> 315167.01
A108: =C28 -> 2032 | B108: =D28 -> 644280.08 | C108: =D43 -> 310625.36 | D108: =D58 -> 38800.818 | E108: =D73 -> 82472.508 | F108: =D88 -> 317696.46
... A111: =C31 -> 2035 | B111: =D31 -> 664818.79 | C111: =D46 -> 317390.55 | D111: =D61 -> 40037.732 | E111: =D76 -> 85101.612 | F111: =D91 -> 325423.34
A113: How do employment projections change over time?
A115: Source: Author’s analysis based on Department for Education employment projections, Baseline scenario.
A116: Under the Baseline scenario, all five Computer Science Career Areas show a gradual increase in projected employment between 2021 and 2035. Software Development & Testing remains the largest Career Area throughout the period, while Data, Analytics & Databases and IT Infrastructure, Networks & Support maintain substantially higher employment levels than Web, Applications & UX/UI and Cybersecurity. Although the areas differ considerably in employment scale, the Baseline trajectories show a consistently positive direction across all five Career Areas.
A118: Section 4 — Scenario Comparison
A119: Charts B — Scenario trajectories
A121: Career Area | B121: Baseline 2035 | C121: Technical Opportunities 2035 | D121: Human-Centric 2035 | E121: Highest Scenario | F121: Lowest Scenario | G121: Scenario Range
A122: Software Development & Testing | B122: =SUMIFS($D$17:$D$91,$B$17:$B$91,$A122,$C$17:$C$91,2035) -> 664818.79 | C122: =SUMIFS($E$17:$E$91,$B$17:$B$91,$A122,$C$17:$C$91,2035) -> 767246.73 | D122: =SUMIFS($F$17:$F$91,$B$17:$B$91,$A122,$C$17:$C$91,2035) -> 778761.13 | E122: =INDEX($B$121:$D$121,1,MATCH(MAX(B122:D122),B122:D122,0)) -> Human-Centric 2035 | F122: =INDEX($B$121:$D$121,1,MATCH(MIN(B122:D122),B122:D122,0)) -> Baseline 2035 | G122: =MAX(B122:D122)-MIN(B122:D122) -> 113942.34
A123: Data, Analytics & Databases | B123: =SUMIFS($D$17:$D$91,$B$17:$B$91,$A123,$C$17:$C$91,2035) -> 317390.55 | C123: =SUMIFS($E$17:$E$91,$B$17:$B$91,$A123,$C$17:$C$91,2035) -> 354173.44 | D123: =SUMIFS($F$17:$F$91,$B$17:$B$91,$A123,$C$17:$C$91,2035) -> 349719.95 | E123: =INDEX($B$121:$D$121,1,MATCH(MAX(B123:D123),B123:D123,0)) -> Technical Opportunities 2035 | F123: =INDEX($B$121:$D$121,1,MATCH(MIN(B123:D123),B123:D123,0)) -> Baseline 2035 | G123: =MAX(B123:D123)-MIN(B123:D123) -> 36782.891
A124: Cybersecurity | B124: =SUMIFS($D$17:$D$91,$B$17:$B$91,$A124,$C$17:$C$91,2035) -> 40037.732 | C124: =SUMIFS($E$17:$E$91,$B$17:$B$91,$A124,$C$17:$C$91,2035) -> 46206.303 | D124: =SUMIFS($F$17:$F$91,$B$17:$B$91,$A124,$C$17:$C$91,2035) -> 46899.742 | E124: =INDEX($B$121:$D$121,1,MATCH(MAX(B124:D124),B124:D124,0)) -> Human-Centric 2035 | F124: =INDEX($B$121:$D$121,1,MATCH(MIN(B124:D124),B124:D124,0)) -> Baseline 2035 | G124: =MAX(B124:D124)-MIN(B124:D124) -> 6862.0096
A125: Web, Applications & UX/UI | B125: =SUMIFS($D$17:$D$91,$B$17:$B$91,$A125,$C$17:$C$91,2035) -> 85101.612 | C125: =SUMIFS($E$17:$E$91,$B$17:$B$91,$A125,$C$17:$C$91,2035) -> 98213.129 | D125: =SUMIFS($F$17:$F$91,$B$17:$B$91,$A125,$C$17:$C$91,2035) -> 99687.056 | E125: =INDEX($B$121:$D$121,1,MATCH(MAX(B125:D125),B125:D125,0)) -> Human-Centric 2035 | F125: =INDEX($B$121:$D$121,1,MATCH(MIN(B125:D125),B125:D125,0)) -> Baseline 2035 | G125: =MAX(B125:D125)-MIN(B125:D125) -> 14585.444
A126: IT Infrastructure, Networks & Support | B126: =SUMIFS($D$17:$D$91,$B$17:$B$91,$A126,$C$17:$C$91,2035) -> 325423.34 | C126: =SUMIFS($E$17:$E$91,$B$17:$B$91,$A126,$C$17:$C$91,2035) -> 424066.86 | D126: =SUMIFS($F$17:$F$91,$B$17:$B$91,$A126,$C$17:$C$91,2035) -> 407126.18 | E126: =INDEX($B$121:$D$121,1,MATCH(MAX(B126:D126),B126:D126,0)) -> Technical Opportunities 2035 | F126: =INDEX($B$121:$D$121,1,MATCH(MIN(B126:D126),B126:D126,0)) -> Baseline 2035 | G126: =MAX(B126:D126)-MIN(B126:D126) -> 98643.52
A128: By 2035, all five Career Areas show higher projected employment under the Technical Opportunities and Human-Centric scenarios than under the Baseline scenario. Human-Centric produces the highest projected employment for Software Development & Testing, Cybersecurity, and Web, Applications & UX/UI, while Technical Opportunities produces the highest projections for Data, Analytics & Databases and IT Infrastructure, Networks & Support. Scenario sensitivity varies considerably across Career Areas, with IT Infrastructure, Networks & Support showing particularly strong divergence between the alternative futures.
A130: How do projected employment levels differ across future scenarios in 2035?
A149: Source: Author’s analysis based on Department for Education Baseline, Technical Opportunities and Human-Centric employment projection scenarios.
A150: By 2035, projected employment is higher under both alternative scenarios than under the Baseline across all five Career Areas. Human-Centric produces the highest projected employment for Software Development & Testing, Cybersecurity, and Web, Applications & UX/UI, while Technical Opportunities produces the highest projections for Data, Analytics & Databases and IT Infrastructure, Networks & Support. The largest absolute differences between scenarios are observed in Software Development & Testing and IT Infrastructure, Networks & Support.

Sheet 14A_Forecasting_Methods
A2: January-December 2021 | B2: Weighted 2022
A3: SOC20M Occupation in Main Job SOC2020 Unit Level | B3: 1 01 Crop, animal production, hunting | C3: 2 02 Forestry and logging | D3: 3 03 Fishing and aquaculture | E3: 5 05 Mining of coal and lignite | F3: 6 06 Extraction crude petroleum and gas | G3: 7 07 Mining of metal ores | H3: 8 08 Other mining and quarrying | I3: 9 09 Mining support service activities | J3: 10 10 Manufacture of food products | K3: 11 11 Manufacture of beverages | L3: 12 12 Manufacture of tobacco products | M3: 13 13 Manufacture of textiles | N3: 14 14 Manufacture of wearing apparel | O3: 15 15 Manufacture of leather and related | P3: 16 16 Manufacture wood and wood products | Q3: 17 17 Manufacture paper & paper products | R3: 18 18 Printing and recorded media | S3: 19 19 Manufacture of coke & refined petrol | T3: 20 20 Manufacture of chemicals | U3: 21 21 Manufacture of pharmaceuticals | V3: 22 22 Manufacture rubber plastic products | W3: 23 23 Manuf non-metallic mineral products | X3: 24 24 Manufacture of basic metals | Y3: 25 25 Manuf fab metal prods, ex machinery | Z3: 26 26 Manuf computr, electronic & optical | AA3: 27 27 Manufacture of electrical equipment | AB3: 28 28 Manuf of machinery n.e.c. | AC3: 29 29 Manuf vehicles and trailers | AD3: 30 30 Manufacture of other transport | AE3: 31 31 Manufacture of furniture | AF3: 32 32 Other manufacturing | AG3: 33 33 Repair and installation of machinery | AH3: 35 35 Electricity, gas and air cond supply | AI3: 36 36 Water collectn, treatment & supply | AJ3: 37 37 Sewerage | AK3: 38 38 Waste collectn, treatment, disposal | AL3: 39 39 Remediation & other waste managmnt | AM3: 41 41 Construction of buildings | AN3: 42 42 Civil engineering | AO3: 43 43 Specialised construction activities | AP3: 45 45 Wholesale retail trade repair vehcls | AQ3: 46 46 Wholesale trade, except vehicles | AR3: 47 47 Retail trade, except vehicles | AS3: 49 49 Land transport inc via pipelines | AT3: 50 50 Water transport | AU3: 51 51 Air transport | AV3: 52 52 Warehousing & support for transport | AW3: 53 53 Postal and courier activities | AX3: 55 55 Accommodation | AY3: 56 56 Food and beverage service activities | AZ3: 58 58 Publishing activities | BA3: 59 59 Film, video, television sound record | BB3: 60 60 Programming and broadcasting | BC3: 61 61 Telecommunications | BD3: 62 62 Computer programming and consultancy | BE3: 63 63 Information service activities | BF3: 64 64 Financial ex insurance and pension | BG3: 65 65 Insurance, reinsurance and pension | BH3: 66 66 Auxiliary to financial and insurance | BI3: 68 68 Real estate activities | BJ3: 69 69 Legal and accounting activities | BK3: 70 70 Head offices; management consultancy | BL3: 71 71 Architerctural and engineering | BM3: 72 72 Scientific research and development | BN3: 73 73 Advertising and market research | BO3: 74 74 Other prof, scientific and technical | BP3: 75 75 Vetinary activities | BQ3: 77 77 Rental and leasing activities | BR3: 78 78 Employment activities | BS3: 79 79 Travel, tour operator, reservation | BT3: 80 80 Security & investigation activities | BU3: 81 81 Services to buildings and landscape | BV3: 82 82 Office admin, support and other | BW3: 84 84 Public admin, defence, social sec | BX3: 85 85 Education | BY3: 86 86 Human health activities | BZ3: 87 87 Residential care activities | CA3: 88 88 Social work without accommodation | CB3: 90 90 Creative, arts and entertainment | CC3: 91 91 Libraries, archives, museums | CD3: 92 92 Gambling and betting activities | CE3: 93 93 Sports, amusement, recreation | CF3: 94 94 Activities membership organisations | CG3: 95 95 Repair of computers and other goods | CH3: 96 96 Other personal service activities | CI3: 97 97 Domestic personnel | CJ3: 98 98 Undifferentiated goods | CK3: 99 99 Extraterritorial organisations | CL3: Total 2021 | CS3: Total 2021 | CT3: Total By Career Area
A4: 2133 IT business analysts, architects and systems designers | B4: - | C4: - | D4: - | E4: - | F4: - | G4: - | H4: - | I4: 1342 | J4: - | K4: - | L4: - | M4: - | N4: - | O4: - | P4: - | Q4: - | R4: * | S4: - | T4: 1314 | U4: 733 | V4: * | W4: - | X4: * | Y4: * | Z4: 2805 | AA4: * | AB4: * | AC4: 1082 | AD4: * | AE4: - | AF4: * | AG4: 1389 | AH4: 2908 | AI4: * | AJ4: - | AK4: - | AL4: - | AM4: * | AN4: 2619 | AO4: * | AP4: * | AQ4: 932 | AR4: 1207 | AS4: * | AT4: - | AU4: - | AV4: 3849 | AW4: - | AX4: - | AY4: * | AZ4: 1018 | BA4: - | BB4: * | BC4: 3416 | BD4: 44670 | BE4: * | BF4: 11253 | BG4: 4053 | BH4: 9512 | BI4: - | BJ4: * | BK4: 3351 | BL4: 5555 | BM4: 1407 | BN4: 2167 | BO4: 2347 | BP4: - | BQ4: 1090 | BR4: - | BS4: - | BT4: * | BU4: * | BV4: * | BW4: 10766 | BX4: 4174 | BY4: 1857 | BZ4: - | CA4: 2417 | CB4: - | CC4: * | CD4: * | CE4: - | CF4: 1722 | CG4: 2330 | CH4: * | CI4: - | CJ4: - | CK4: * | CL4: 144673 | CN4: 1. Software Development & Testing | CO4: 2134 | CP4: Programmers and software development professionals | CQ4: Full Unit Group | CS4: =CL5 -> 452528 | CT4: =SUM(CS4:CS6) -> 544841.15
A5: 2134 Programmers and software development professionals | B5: - | C5: - | D5: - | E5: - | F5: - | G5: - | H5: - | I5: 1609 | J5: * | K5: - | L5: - | M5: * | N5: * | O5: - | P5: * | Q5: * | R5: 1435 | S5: - | T5: * | U5: 1670 | V5: * | W5: - | X5: * | Y5: 1093 | Z5: 9821 | AA5: * | AB5: 959 | AC5: 3581 | AD5: 2931 | AE5: * | AF5: 2212 | AG5: 2119 | AH5: 1272 | AI5: * | AJ5: * | AK5: - | AL5: - | AM5: 3039 | AN5: 2424 | AO5: 1656 | AP5: 2246 | AQ5: 2640 | AR5: 11017 | AS5: * | AT5: * | AU5: * | AV5: 1319 | AW5: * | AX5: * | AY5: * | AZ5: 13229 | BA5: 1508 | BB5: * | BC5: 3956 | BD5: 235133 | BE5: 1704 | BF5: 17262 | BG5: 2987 | BH5: 13994 | BI5: 2323 | BJ5: 1601 | BK5: 6457 | BL5: 9849 | BM5: 8426 | BN5: 2758 | BO5: 2034 | BP5: - | BQ5: 1636 | BR5: * | BS5: * | BT5: * | BU5: 1525 | BV5: 3954 | BW5: 26300 | BX5: 12178 | BY5: 5082 | BZ5: * | CA5: 2411 | CB5: - | CC5: 3152 | CD5: 2321 | CE5: * | CF5: 2762 | CG5: * | CH5: * | CI5: - | CJ5: - | CK5: * | CL5: 452528 | CO5: 2136 | CP5: IT quality and testing professionals | CQ5: Full Unit Group | CS5: =CL7 -> 27308
A6: 2135 Cyber security professionals | B6: - | C6: - | D6: - | E6: - | F6: - | G6: - | H6: - | I6: * | J6: - | K6: - | L6: - | M6: - | N6: - | O6: - | P6: - | Q6: - | R6: - | S6: - | T6: - | U6: - | V6: - | W6: - | X6: - | Y6: * | Z6: - | AA6: - | AB6: - | AC6: - | AD6: - | AE6: - | AF6: - | AG6: - | AH6: - | AI6: * | AJ6: - | AK6: * | AL6: * | AM6: - | AN6: - | AO6: - | AP6: - | AQ6: - | AR6: * | AS6: - | AT6: - | AU6: - | AV6: * | AW6: - | AX6: - | AY6: * | AZ6: * | BA6: - | BB6: - | BC6: 1900 | BD6: 7175 | BE6: - | BF6: 3980 | BG6: 447 | BH6: * | BI6: - | BJ6: * | BK6: 1245 | BL6: * | BM6: - | BN6: * | BO6: * | BP6: - | BQ6: - | BR6: - | BS6: - | BT6: 1604 | BU6: * | BV6: - | BW6: 2152 | BX6: * | BY6: 842 | BZ6: - | CA6: - | CB6: - | CC6: * | CD6: - | CE6: - | CF6: - | CG6: - | CH6: - | CI6: - | CJ6: - | CK6: - | CL6: 28494 | CO6: 2139/01 | CP6: DevOps engineers | CQ6: validated 2139 results | CR6: 0.461 | CS6: =CL9*CR6 -> 65005.149
A7: 2136 IT quality and testing professionals | B7: - | C7: - | D7: - | E7: - | F7: - | G7: - | H7: - | I7: - | J7: - | K7: - | L7: - | M7: - | N7: - | O7: - | P7: - | Q7: - | R7: - | S7: - | T7: - | U7: - | V7: - | W7: - | X7: - | Y7: - | Z7: * | AA7: - | AB7: - | AC7: * | AD7: - | AE7: - | AF7: - | AG7: - | AH7: * | AI7: - | AJ7: - | AK7: - | AL7: - | AM7: - | AN7: - | AO7: - | AP7: - | AQ7: - | AR7: * | AS7: - | AT7: * | AU7: - | AV7: - | AW7: - | AX7: - | AY7: - | AZ7: * | BA7: - | BB7: * | BC7: - | BD7: 15073 | BE7: - | BF7: * | BG7: 1847 | BH7: 681 | BI7: - | BJ7: - | BK7: * | BL7: 694 | BM7: - | BN7: - | BO7: - | BP7: - | BQ7: * | BR7: - | BS7: - | BT7: * | BU7: * | BV7: - | BW7: 765 | BX7: * | BY7: - | BZ7: - | CA7: - | CB7: - | CC7: - | CD7: * | CE7: - | CF7: - | CG7: * | CH7: - | CI7: - | CJ7: - | CK7: - | CL7: 27308 | CN7: 2. Data, Analytics & Databases | CO7: 3544 | CP7: Data analysts | CQ7: Full Unit Group | CS7: =CL14 -> 121377 | CT7: =SUM(CS7:CS9) -> 283779.09
A8: 2137 IT network professionals | B8: - | C8: - | D8: - | E8: - | F8: - | G8: - | H8: - | I8: - | J8: * | K8: - | L8: - | M8: - | N8: - | O8: - | P8: * | Q8: - | R8: - | S8: - | T8: - | U8: - | V8: - | W8: - | X8: - | Y8: - | Z8: 1358 | AA8: - | AB8: * | AC8: * | AD8: * | AE8: - | AF8: - | AG8: * | AH8: * | AI8: * | AJ8: - | AK8: - | AL8: - | AM8: - | AN8: * | AO8: 3481 | AP8: * | AQ8: * | AR8: 1158 | AS8: * | AT8: - | AU8: - | AV8: * | AW8: - | AX8: - | AY8: - | AZ8: - | BA8: - | BB8: * | BC8: 4741 | BD8: 6329 | BE8: - | BF8: * | BG8: - | BH8: * | BI8: * | BJ8: * | BK8: - | BL8: 900 | BM8: - | BN8: - | BO8: - | BP8: - | BQ8: - | BR8: - | BS8: - | BT8: * | BU8: - | BV8: * | BW8: 2619 | BX8: * | BY8: * | BZ8: - | CA8: - | CB8: - | CC8: - | CD8: - | CE8: - | CF8: - | CG8: - | CH8: - | CI8: - | CJ8: - | CK8: - | CL8: 31052 | CO8: 3133 | CP8: Database administrators and web content technicians | CQ8: Full Unit Group | CS8: =CL13 -> 69088
A9: 2139 Information technology professionals n.e.c. | B9: - | C9: - | D9: - | E9: - | F9: - | G9: - | H9: * | I9: - | J9: - | K9: - | L9: - | M9: - | N9: - | O9: - | P9: - | Q9: - | R9: * | S9: - | T9: * | U9: 2084 | V9: - | W9: * | X9: - | Y9: - | Z9: 1886 | AA9: - | AB9: - | AC9: - | AD9: * | AE9: - | AF9: * | AG9: 365 | AH9: * | AI9: - | AJ9: - | AK9: * | AL9: - | AM9: * | AN9: * | AO9: 1519 | AP9: * | AQ9: 1416 | AR9: 1498 | AS9: * | AT9: - | AU9: - | AV9: - | AW9: - | AX9: - | AY9: - | AZ9: 855 | BA9: - | BB9: * | BC9: 3640 | BD9: 70457 | BE9: - | BF9: 3313 | BG9: * | BH9: 3757 | BI9: 989 | BJ9: 2258 | BK9: 13518 | BL9: 3648 | BM9: - | BN9: * | BO9: * | BP9: - | BQ9: - | BR9: - | BS9: 1766 | BT9: - | BU9: - | BV9: 1550 | BW9: 7477 | BX9: 1316 | BY9: 1708 | BZ9: - | CA9: * | CB9: - | CC9: 929 | CD9: - | CE9: - | CF9: * | CG9: * | CH9: - | CI9: - | CJ9: - | CK9: * | CL9: 141009 | CO9: 2133/02 + 2133/03 | CP9: Data architects + Data engineers | CQ9: validated 2133 results | CR9: 0.645 | CS9: =CR9*CL4 -> 93314.085
A10: 2141 Web design professionals | B10: - | C10: - | D10: - | E10: - | F10: - | G10: - | H10: - | I10: - | J10: - | K10: - | L10: - | M10: - | N10: - | O10: - | P10: - | Q10: - | R10: - | S10: - | T10: * | U10: - | V10: - | W10: - | X10: - | Y10: - | Z10: - | AA10: - | AB10: - | AC10: - | AD10: - | AE10: - | AF10: - | AG10: - | AH10: - | AI10: - | AJ10: - | AK10: - | AL10: - | AM10: - | AN10: - | AO10: - | AP10: - | AQ10: * | AR10: * | AS10: - | AT10: - | AU10: - | AV10: - | AW10: - | AX10: - | AY10: - | AZ10: - | BA10: * | BB10: * | BC10: * | BD10: 18046 | BE10: * | BF10: - | BG10: - | BH10: * | BI10: - | BJ10: - | BK10: 1325 | BL10: - | BM10: * | BN10: 2318 | BO10: 2261 | BP10: - | BQ10: - | BR10: - | BS10: * | BT10: - | BU10: - | BV10: - | BW10: 1744 | BX10: 2111 | BY10: - | BZ10: - | CA10: - | CB10: - | CC10: * | CD10: * | CE10: - | CF10: * | CG10: - | CH10: - | CI10: - | CJ10: - | CK10: - | CL10: 34673 | CN10: 3. Cybersecurity | CO10: 2135 | CP10: Cyber security professionals | CQ10: Full Unit Group | CS10: =CL6 -> 28494 | CT10: =CS10 -> 28494
A11: 3131 IT operations technicians | B11: - | C11: - | D11: * | E11: - | F11: - | G11: - | H11: - | I11: * | J11: * | K11: - | L11: - | M11: - | N11: - | O11: - | P11: * | Q11: * | R11: - | S11: - | T11: - | U11: - | V11: * | W11: - | X11: - | Y11: 720 | Z11: 1696 | AA11: * | AB11: * | AC11: * | AD11: 1575 | AE11: - | AF11: * | AG11: - | AH11: * | AI11: 1304 | AJ11: - | AK11: - | AL11: - | AM11: 2576 | AN11: * | AO11: 1155 | AP11: * | AQ11: 2596 | AR11: 3117 | AS11: 2068 | AT11: - | AU11: - | AV11: * | AW11: * | AX11: - | AY11: - | AZ11: 4598 | BA11: 930 | BB11: * | BC11: 1983 | BD11: 23727 | BE11: * | BF11: 3583 | BG11: 1835 | BH11: 2229 | BI11: * | BJ11: * | BK11: 2502 | BL11: 1145 | BM11: 2191 | BN11: 616 | BO11: * | BP11: - | BQ11: * | BR11: * | BS11: - | BT11: 946 | BU11: * | BV11: * | BW11: 12167 | BX11: 13537 | BY11: 5258 | BZ11: * | CA11: 1277 | CB11: - | CC11: 520 | CD11: - | CE11: * | CF11: 1542 | CG11: 3008 | CH11: - | CI11: - | CJ11: - | CK11: * | CL11: 112101 | CN11: 4. Web, Applications & UX/UI | CO11: 2141 | CP11: Web design professionals | CQ11: Full Unit Group | CS11: =CL10 -> 34673 | CT11: =SUM(CS11:CS12) -> 75565.61
A12: 3132 IT user support technicians | B12: - | C12: * | D12: - | E12: - | F12: - | G12: - | H12: - | I12: - | J12: 1390 | K12: - | L12: - | M12: * | N12: - | O12: - | P12: * | Q12: - | R12: * | S12: - | T12: - | U12: * | V12: * | W12: * | X12: - | Y12: - | Z12: 1811 | AA12: * | AB12: * | AC12: 1125 | AD12: - | AE12: - | AF12: - | AG12: * | AH12: * | AI12: 1088 | AJ12: - | AK12: - | AL12: - | AM12: * | AN12: - | AO12: 1358 | AP12: * | AQ12: * | AR12: 4721 | AS12: * | AT12: - | AU12: - | AV12: 1824 | AW12: - | AX12: - | AY12: - | AZ12: * | BA12: - | BB12: * | BC12: 3182 | BD12: 25897 | BE12: * | BF12: 4092 | BG12: 1642 | BH12: 4488 | BI12: * | BJ12: * | BK12: 2174 | BL12: 714 | BM12: - | BN12: - | BO12: - | BP12: - | BQ12: * | BR12: * | BS12: - | BT12: * | BU12: * | BV12: * | BW12: 9089 | BX12: 9751 | BY12: 3017 | BZ12: * | CA12: 3362 | CB12: - | CC12: 1523 | CD12: - | CE12: 1037 | CF12: 1094 | CG12: 1478 | CH12: - | CI12: - | CJ12: - | CK12: * | CL12: 98501 | CO12: 2139/03 | CP12: Webmasters / Website managers | CQ12: validated 2139 results | CR12: 0.29 | CS12: =CR12*CL9 -> 40892.61
A13: 3133 Database administrators and web content technicians | B13: - | C13: - | D13: - | E13: - | F13: - | G13: - | H13: - | I13: - | J13: - | K13: * | L13: - | M13: * | N13: * | O13: - | P13: - | Q13: * | R13: - | S13: - | T13: * | U13: * | V13: * | W13: - | X13: - | Y13: * | Z13: 1029 | AA13: - | AB13: - | AC13: * | AD13: - | AE13: - | AF13: - | AG13: - | AH13: - | AI13: * | AJ13: - | AK13: - | AL13: - | AM13: - | AN13: - | AO13: - | AP13: * | AQ13: * | AR13: 1880 | AS13: * | AT13: - | AU13: - | AV13: 1088 | AW13: - | AX13: - | AY13: * | AZ13: 2519 | BA13: 1948 | BB13: * | BC13: 1796 | BD13: 8315 | BE13: 2861 | BF13: 2534 | BG13: * | BH13: 1788 | BI13: * | BJ13: 2077 | BK13: 2230 | BL13: * | BM13: * | BN13: 4282 | BO13: 2680 | BP13: - | BQ13: * | BR13: * | BS13: * | BT13: - | BU13: * | BV13: * | BW13: 3895 | BX13: 6378 | BY13: 1752 | BZ13: * | CA13: 2909 | CB13: * | CC13: 1323 | CD13: * | CE13: * | CF13: * | CG13: - | CH13: * | CI13: - | CJ13: - | CK13: * | CL13: 69088 | CN13: 5. IT Infrastructure, Networks & Support | CO13: 2137 | CP13: IT network professionals | CQ13: Full Unit Group | CS13: =CL8 -> 31052 | CT13: =SUM(CS13:CS16) -> 284911.23
A14: 3544 Data analysts | B14: - | C14: - | D14: - | E14: - | F14: - | G14: - | H14: - | I14: 1362 | J14: - | K14: * | L14: - | M14: - | N14: - | O14: - | P14: - | Q14: - | R14: * | S14: * | T14: * | U14: - | V14: * | W14: - | X14: - | Y14: 1471 | Z14: * | AA14: - | AB14: * | AC14: * | AD14: * | AE14: * | AF14: * | AG14: * | AH14: 5034 | AI14: * | AJ14: * | AK14: - | AL14: - | AM14: * | AN14: 1881 | AO14: - | AP14: * | AQ14: 1425 | AR14: 2204 | AS14: 1112 | AT14: - | AU14: - | AV14: * | AW14: - | AX14: - | AY14: - | AZ14: 3645 | BA14: * | BB14: - | BC14: 881 | BD14: 9237 | BE14: * | BF14: 8930 | BG14: 4203 | BH14: 11045 | BI14: 1086 | BJ14: * | BK14: 4615 | BL14: 2414 | BM14: 2444 | BN14: 3081 | BO14: 1431 | BP14: - | BQ14: 1050 | BR14: * | BS14: * | BT14: - | BU14: * | BV14: 2235 | BW14: 22690 | BX14: 4531 | BY14: 3326 | BZ14: * | CA14: 2943 | CB14: - | CC14: * | CD14: * | CE14: * | CF14: * | CG14: - | CH14: - | CI14: - | CJ14: - | CK14: * | CL14: 121377 | CO14: 3131 | CP14: IT operations technicians | CQ14: Full Unit Group | CS14: =CL11 -> 112101
CO15: 3132 | CP15: IT user support technicians | CQ15: Full Unit Group | CS15: =CL12 -> 98501
CO16: 2133/04 + 2133/06 | CP16: Systems architects + Solution architects | CQ16: validated 2133 results | CR16: 0.299 | CS16: =CR16*CL4 -> 43257.227
A18: January-December 2022 | B18: Weighted 2022 | CL18: Total 2022 | CS18: Total 2022 | CT18: Total By Career Area
A19: 2133 IT business analysts, architects and systems designers | B19: - | C19: - | D19: - | E19: - | F19: * | G19: - | H19: - | I19: * | J19: * | K19: * | L19: - | M19: - | N19: * | O19: - | P19: - | Q19: - | R19: - | S19: * | T19: * | U19: * | V19: * | W19: - | X19: - | Y19: 3217 | Z19: 501 | AA19: - | AB19: * | AC19: 1182 | AD19: 1085 | AE19: - | AF19: * | AG19: * | AH19: 1353 | AI19: * | AJ19: - | AK19: * | AL19: - | AM19: * | AN19: 1771 | AO19: * | AP19: - | AQ19: 2177 | AR19: 2487 | AS19: 1138 | AT19: * | AU19: * | AV19: 1345 | AW19: - | AX19: - | AY19: * | AZ19: 1065 | BA19: - | BB19: * | BC19: 5935 | BD19: 47438 | BE19: - | BF19: 14069 | BG19: 12071 | BH19: 5461 | BI19: 1323 | BJ19: * | BK19: 4841 | BL19: 7801 | BM19: 2415 | BN19: * | BO19: 1916 | BP19: - | BQ19: * | BR19: - | BS19: - | BT19: * | BU19: * | BV19: * | BW19: 12597 | BX19: 1632 | BY19: 1642 | BZ19: - | CA19: 731 | CB19: - | CC19: 1076 | CD19: * | CE19: * | CF19: 2317 | CG19: 2249 | CH19: - | CI19: - | CJ19: - | CK19: 1045 | CL19: 160530 | CN19: 1. Software Development & Testing | CO19: 2134 | CP19: Programmers and software development professionals | CQ19: Full Unit Group | CS19: =CL20 -> 512971 | CT19: =SUM(CS19:CS21) -> 609898.92
A20: 2134 Programmers and software development professionals | B20: - | C20: - | D20: - | E20: - | F20: - | G20: - | H20: - | I20: 3461 | J20: * | K20: - | L20: - | M20: * | N20: - | O20: - | P20: * | Q20: - | R20: 1824 | S20: - | T20: * | U20: 710 | V20: * | W20: - | X20: - | Y20: 1140 | Z20: 11870 | AA20: 1560 | AB20: 1905 | AC20: 3460 | AD20: 2123 | AE20: - | AF20: * | AG20: * | AH20: * | AI20: * | AJ20: - | AK20: * | AL20: - | AM20: 1249 | AN20: 3314 | AO20: 759 | AP20: 1293 | AQ20: 4469 | AR20: 13275 | AS20: * | AT20: * | AU20: - | AV20: 2065 | AW20: 1504 | AX20: - | AY20: 4121 | AZ20: 12170 | BA20: 1269 | BB20: * | BC20: 6716 | BD20: 270512 | BE20: 4780 | BF20: 21460 | BG20: 6975 | BH20: 16971 | BI20: 1216 | BJ20: 3790 | BK20: 6737 | BL20: 12901 | BM20: 4838 | BN20: 2718 | BO20: 1697 | BP20: - | BQ20: 811 | BR20: * | BS20: 624 | BT20: * | BU20: 1497 | BV20: 6479 | BW20: 28683 | BX20: 11301 | BY20: 3951 | BZ20: * | CA20: 1967 | CB20: - | CC20: 6276 | CD20: 3097 | CE20: 1552 | CF20: 1049 | CG20: - | CH20: * | CI20: - | CJ20: - | CK20: - | CL20: 512971 | CO20: 2136 | CP20: IT quality and testing professionals | CQ20: Full Unit Group | CS20: =CL22 -> 34556
A21: 2135 Cyber security professionals | B21: - | C21: - | D21: - | E21: - | F21: - | G21: - | H21: - | I21: - | J21: * | K21: - | L21: - | M21: - | N21: - | O21: - | P21: - | Q21: - | R21: - | S21: - | T21: - | U21: - | V21: - | W21: - | X21: - | Y21: - | Z21: * | AA21: - | AB21: - | AC21: - | AD21: * | AE21: - | AF21: - | AG21: - | AH21: - | AI21: - | AJ21: - | AK21: - | AL21: - | AM21: - | AN21: - | AO21: - | AP21: - | AQ21: * | AR21: * | AS21: - | AT21: - | AU21: - | AV21: - | AW21: - | AX21: - | AY21: - | AZ21: - | BA21: - | BB21: - | BC21: 5165 | BD21: 10384 | BE21: - | BF21: 1610 | BG21: 1515 | BH21: 1372 | BI21: - | BJ21: - | BK21: 1801 | BL21: - | BM21: * | BN21: * | BO21: * | BP21: - | BQ21: - | BR21: - | BS21: - | BT21: 6069 | BU21: - | BV21: * | BW21: 5390 | BX21: * | BY21: * | BZ21: - | CA21: * | CB21: - | CC21: * | CD21: - | CE21: - | CF21: - | CG21: - | CH21: - | CI21: - | CJ21: - | CK21: - | CL21: 41349 | CO21: 2139/01 | CP21: DevOps engineers | CQ21: validated 2139 results | CR21: 0.461 | CS21: =CR21*CL24 -> 62371.917
A22: 2136 IT quality and testing professionals | B22: - | C22: - | D22: - | E22: - | F22: - | G22: - | H22: - | I22: - | J22: - | K22: - | L22: - | M22: - | N22: - | O22: - | P22: - | Q22: - | R22: - | S22: - | T22: - | U22: - | V22: * | W22: - | X22: - | Y22: - | Z22: 781 | AA22: - | AB22: - | AC22: - | AD22: * | AE22: - | AF22: - | AG22: - | AH22: * | AI22: * | AJ22: - | AK22: - | AL22: - | AM22: - | AN22: - | AO22: - | AP22: - | AQ22: 757 | AR22: 2442 | AS22: - | AT22: - | AU22: - | AV22: * | AW22: - | AX22: * | AY22: - | AZ22: * | BA22: - | BB22: * | BC22: 772 | BD22: 19707 | BE22: - | BF22: 2440 | BG22: * | BH22: - | BI22: - | BJ22: - | BK22: - | BL22: * | BM22: - | BN22: - | BO22: - | BP22: - | BQ22: - | BR22: - | BS22: - | BT22: - | BU22: - | BV22: - | BW22: 1385 | BX22: - | BY22: - | BZ22: - | CA22: - | CB22: - | CC22: - | CD22: - | CE22: - | CF22: - | CG22: * | CH22: - | CI22: - | CJ22: - | CK22: - | CL22: 34556 | CN22: 2. Data, Analytics & Databases | CO22: 3544 | CP22: Data analysts | CQ22: Full Unit Group | CS22: =CL29 -> 126861 | CT22: =SUM(CS22:CS24) -> 296340.85
A23: 2137 IT network professionals | B23: - | C23: - | D23: - | E23: - | F23: - | G23: - | H23: - | I23: - | J23: * | K23: * | L23: - | M23: - | N23: - | O23: - | P23: - | Q23: - | R23: - | S23: - | T23: - | U23: - | V23: - | W23: - | X23: - | Y23: * | Z23: * | AA23: * | AB23: - | AC23: * | AD23: 1831 | AE23: - | AF23: * | AG23: - | AH23: * | AI23: - | AJ23: - | AK23: - | AL23: - | AM23: - | AN23: - | AO23: 1415 | AP23: - | AQ23: * | AR23: * | AS23: * | AT23: - | AU23: - | AV23: - | AW23: * | AX23: - | AY23: - | AZ23: * | BA23: - | BB23: - | BC23: 7973 | BD23: 9822 | BE23: * | BF23: * | BG23: * | BH23: - | BI23: - | BJ23: * | BK23: - | BL23: 1992 | BM23: * | BN23: * | BO23: - | BP23: - | BQ23: - | BR23: - | BS23: - | BT23: - | BU23: - | BV23: - | BW23: 4223 | BX23: 930 | BY23: 996 | BZ23: - | CA23: - | CB23: - | CC23: * | CD23: - | CE23: * | CF23: - | CG23: * | CH23: - | CI23: - | CJ23: - | CK23: - | CL23: 43118 | CO23: 3133 | CP23: Database administrators and web content technicians | CQ23: Full Unit Group | CS23: =CL28 -> 65938
A24: 2139 Information technology professionals n.e.c. | B24: - | C24: - | D24: - | E24: - | F24: - | G24: - | H24: - | I24: - | J24: - | K24: - | L24: - | M24: * | N24: - | O24: - | P24: - | Q24: - | R24: - | S24: * | T24: * | U24: * | V24: * | W24: - | X24: - | Y24: * | Z24: * | AA24: - | AB24: * | AC24: * | AD24: * | AE24: - | AF24: - | AG24: * | AH24: * | AI24: * | AJ24: - | AK24: - | AL24: - | AM24: * | AN24: * | AO24: * | AP24: 2125 | AQ24: 764 | AR24: 3440 | AS24: * | AT24: - | AU24: - | AV24: * | AW24: - | AX24: - | AY24: - | AZ24: 3149 | BA24: - | BB24: * | BC24: 5168 | BD24: 72133 | BE24: - | BF24: 1551 | BG24: * | BH24: 1705 | BI24: * | BJ24: * | BK24: 9602 | BL24: 2711 | BM24: 601 | BN24: 675 | BO24: * | BP24: - | BQ24: - | BR24: 2507 | BS24: - | BT24: - | BU24: - | BV24: * | BW24: 7170 | BX24: 2719 | BY24: 1676 | BZ24: - | CA24: 685 | CB24: - | CC24: 1107 | CD24: - | CE24: - | CF24: * | CG24: 1896 | CH24: - | CI24: - | CJ24: - | CK24: - | CL24: 135297 | CO24: 2133/02 + 2133/03 | CP24: Data architects + Data engineers | CQ24: validated 2133 results | CR24: 0.645 | CS24: =CR24*CL19 -> 103541.85
A25: 2141 Web design professionals | B25: - | C25: - | D25: - | E25: - | F25: - | G25: - | H25: - | I25: - | J25: - | K25: - | L25: - | M25: - | N25: - | O25: - | P25: - | Q25: - | R25: - | S25: - | T25: - | U25: - | V25: - | W25: - | X25: - | Y25: - | Z25: * | AA25: - | AB25: - | AC25: - | AD25: - | AE25: - | AF25: - | AG25: - | AH25: - | AI25: - | AJ25: - | AK25: - | AL25: - | AM25: - | AN25: - | AO25: - | AP25: * | AQ25: - | AR25: * | AS25: - | AT25: - | AU25: - | AV25: - | AW25: - | AX25: - | AY25: - | AZ25: * | BA25: * | BB25: - | BC25: - | BD25: 14732 | BE25: - | BF25: * | BG25: - | BH25: - | BI25: - | BJ25: * | BK25: * | BL25: - | BM25: * | BN25: * | BO25: * | BP25: * | BQ25: - | BR25: - | BS25: - | BT25: - | BU25: - | BV25: - | BW25: 3655 | BX25: * | BY25: 1747 | BZ25: - | CA25: * | CB25: - | CC25: * | CD25: - | CE25: * | CF25: - | CG25: - | CH25: - | CI25: - | CJ25: - | CK25: - | CL25: 29936 | CN25: 3. Cybersecurity | CO25: 2135 | CP25: Cyber security professionals | CQ25: Full Unit Group | CS25: =CL21 -> 41349 | CT25: =CS25 -> 41349
A26: 3131 IT operations technicians | B26: - | C26: - | D26: - | E26: - | F26: - | G26: - | H26: - | I26: * | J26: 1368 | K26: * | L26: - | M26: - | N26: - | O26: - | P26: * | Q26: * | R26: * | S26: - | T26: - | U26: 2407 | V26: - | W26: - | X26: - | Y26: * | Z26: 1632 | AA26: * | AB26: * | AC26: - | AD26: * | AE26: * | AF26: 1495 | AG26: - | AH26: * | AI26: 922 | AJ26: - | AK26: - | AL26: - | AM26: * | AN26: * | AO26: 1169 | AP26: * | AQ26: 2901 | AR26: 4263 | AS26: 1521 | AT26: * | AU26: - | AV26: 1792 | AW26: * | AX26: - | AY26: * | AZ26: 2737 | BA26: * | BB26: * | BC26: 993 | BD26: 22455 | BE26: * | BF26: 1912 | BG26: 953 | BH26: 3995 | BI26: * | BJ26: * | BK26: 2465 | BL26: 2118 | BM26: 593 | BN26: - | BO26: 1569 | BP26: - | BQ26: - | BR26: - | BS26: - | BT26: * | BU26: 1468 | BV26: 927 | BW26: 15127 | BX26: 11398 | BY26: 3273 | BZ26: * | CA26: * | CB26: - | CC26: * | CD26: * | CE26: * | CF26: * | CG26: 2045 | CH26: - | CI26: - | CJ26: - | CK26: * | CL26: 113150 | CN26: 4. Web, Applications & UX/UI | CO26: 2141 | CP26: Web design professionals | CQ26: Full Unit Group | CS26: =CL25 -> 29936 | CT26: =SUM(CS26:CS27) -> 69172.13
A27: 3132 IT user support technicians | B27: - | C27: - | D27: - | E27: - | F27: - | G27: - | H27: - | I27: * | J27: * | K27: * | L27: - | M27: * | N27: - | O27: - | P27: - | Q27: - | R27: * | S27: - | T27: * | U27: * | V27: - | W27: - | X27: - | Y27: * | Z27: 2523 | AA27: - | AB27: * | AC27: * | AD27: * | AE27: * | AF27: - | AG27: * | AH27: * | AI27: * | AJ27: - | AK27: - | AL27: - | AM27: 666 | AN27: * | AO27: * | AP27: * | AQ27: * | AR27: 2428 | AS27: - | AT27: * | AU27: - | AV27: 1167 | AW27: * | AX27: - | AY27: * | AZ27: 897 | BA27: - | BB27: * | BC27: 1723 | BD27: 35653 | BE27: * | BF27: 6838 | BG27: * | BH27: 3750 | BI27: * | BJ27: * | BK27: 2898 | BL27: 2561 | BM27: * | BN27: - | BO27: - | BP27: - | BQ27: - | BR27: * | BS27: - | BT27: - | BU27: 1209 | BV27: 1011 | BW27: 9496 | BX27: 8505 | BY27: 2614 | BZ27: - | CA27: - | CB27: - | CC27: 560 | CD27: - | CE27: * | CF27: 1258 | CG27: * | CH27: - | CI27: - | CJ27: - | CK27: * | CL27: 102443 | CO27: 2139/03 | CP27: Webmasters / Website managers | CQ27: validated 2139 results | CR27: 0.29 | CS27: =CR27*CL24 -> 39236.13
A28: 3133 Database administrators and web content technicians | B28: * | C28: * | D28: - | E28: - | F28: - | G28: - | H28: - | I28: - | J28: * | K28: * | L28: - | M28: - | N28: - | O28: - | P28: - | Q28: * | R28: - | S28: * | T28: - | U28: * | V28: - | W28: - | X28: * | Y28: - | Z28: * | AA28: * | AB28: * | AC28: - | AD28: - | AE28: * | AF28: * | AG28: - | AH28: * | AI28: * | AJ28: - | AK28: * | AL28: - | AM28: * | AN28: - | AO28: - | AP28: * | AQ28: * | AR28: 6234 | AS28: * | AT28: - | AU28: - | AV28: * | AW28: * | AX28: - | AY28: * | AZ28: 3156 | BA28: * | BB28: - | BC28: 1408 | BD28: 3646 | BE28: 1663 | BF28: 2785 | BG28: * | BH28: 3767 | BI28: * | BJ28: * | BK28: * | BL28: * | BM28: * | BN28: 1720 | BO28: * | BP28: - | BQ28: * | BR28: * | BS28: * | BT28: - | BU28: * | BV28: * | BW28: 5240 | BX28: 6446 | BY28: 1611 | BZ28: - | CA28: 3918 | CB28: - | CC28: - | CD28: * | CE28: - | CF28: * | CG28: - | CH28: * | CI28: - | CJ28: - | CK28: - | CL28: 65938 | CN28: 5. IT Infrastructure, Networks & Support | CO28: 2137 | CP28: IT network professionals | CQ28: Full Unit Group | CS28: =CL23 -> 43118 | CT28: =SUM(CS28:CS31) -> 306709.47
A29: 3544 Data analysts | B29: - | C29: - | D29: - | E29: - | F29: - | G29: - | H29: - | I29: - | J29: - | K29: - | L29: - | M29: - | N29: - | O29: - | P29: - | Q29: - | R29: - | S29: - | T29: * | U29: * | V29: * | W29: - | X29: - | Y29: * | Z29: * | AA29: * | AB29: - | AC29: * | AD29: * | AE29: - | AF29: * | AG29: * | AH29: 918 | AI29: 3728 | AJ29: - | AK29: - | AL29: * | AM29: * | AN29: * | AO29: - | AP29: * | AQ29: 2146 | AR29: 5458 | AS29: * | AT29: - | AU29: * | AV29: - | AW29: - | AX29: - | AY29: * | AZ29: 664 | BA29: * | BB29: * | BC29: * | BD29: 17197 | BE29: * | BF29: 7476 | BG29: 1794 | BH29: 10057 | BI29: - | BJ29: 809 | BK29: 6453 | BL29: 1293 | BM29: 2197 | BN29: 3341 | BO29: 2787 | BP29: - | BQ29: * | BR29: - | BS29: - | BT29: - | BU29: * | BV29: 1188 | BW29: 23448 | BX29: 5690 | BY29: 4876 | BZ29: * | CA29: 5146 | CB29: * | CC29: * | CD29: * | CE29: 1380 | CF29: * | CG29: - | CH29: * | CI29: - | CJ29: - | CK29: * | CL29: 126861 | CO29: 3131 | CP29: IT operations technicians | CQ29: Full Unit Group | CS29: =CL26 -> 113150
CO30: 3132 | CP30: IT user support technicians | CQ30: Full Unit Group | CS30: =CL27 -> 102443
CO31: 2133/04 + 2133/06 | CP31: Systems architects + Solution architects | CQ31: validated 2133 results | CR31: 0.299 | CS31: =CR31*CL19 -> 47998.47
A33: January-December 2023 | B33: Weighted 2022 | CL33: Total 2023 | CS33: Total 2023 | CT33: Total By Career Area
A34: 2133 IT business analysts, architects and systems designers | B34: - | C34: - | D34: - | E34: - | F34: - | G34: - | H34: - | I34: * | J34: * | K34: 1475 | L34: - | M34: - | N34: * | O34: - | P34: * | Q34: - | R34: * | S34: * | T34: * | U34: 1058 | V34: * | W34: * | X34: - | Y34: - | Z34: 8410 | AA34: - | AB34: * | AC34: - | AD34: 1370 | AE34: - | AF34: * | AG34: * | AH34: * | AI34: * | AJ34: - | AK34: - | AL34: - | AM34: 1934 | AN34: 1524 | AO34: * | AP34: * | AQ34: 2088 | AR34: 5863 | AS34: * | AT34: * | AU34: - | AV34: * | AW34: - | AX34: - | AY34: * | AZ34: * | BA34: * | BB34: 3567 | BC34: 3611 | BD34: 55640 | BE34: - | BF34: 16592 | BG34: 1449 | BH34: 6255 | BI34: - | BJ34: 1198 | BK34: 10089 | BL34: 15930 | BM34: * | BN34: * | BO34: 3658 | BP34: - | BQ34: - | BR34: * | BS34: * | BT34: - | BU34: * | BV34: * | BW34: 22418 | BX34: 6799 | BY34: 2107 | BZ34: * | CA34: - | CB34: - | CC34: 1194 | CD34: * | CE34: - | CF34: 2080 | CG34: * | CH34: - | CI34: - | CJ34: - | CK34: 1810 | CL34: 199600 | CN34: 1. Software Development & Testing | CO34: 2134 | CP34: Programmers and software development professionals | CQ34: Full Unit Group | CS34: =CL35 -> 582439 | CT34: =SUM(CS34:CS36) -> 697664.66
A35: 2134 Programmers and software development professionals | B35: - | C35: * | D35: - | E35: - | F35: - | G35: - | H35: - | I35: 2923 | J35: - | K35: - | L35: - | M35: - | N35: - | O35: * | P35: - | Q35: * | R35: 3411 | S35: * | T35: * | U35: 2598 | V35: * | W35: * | X35: - | Y35: 955 | Z35: 10616 | AA35: 748 | AB35: 4441 | AC35: 2232 | AD35: 3797 | AE35: 594 | AF35: * | AG35: * | AH35: 4400 | AI35: * | AJ35: - | AK35: * | AL35: * | AM35: * | AN35: 2574 | AO35: - | AP35: 1690 | AQ35: 4522 | AR35: 15833 | AS35: * | AT35: 2733 | AU35: * | AV35: 2697 | AW35: - | AX35: - | AY35: - | AZ35: 11312 | BA35: * | BB35: 3556 | BC35: 6657 | BD35: 270766 | BE35: 3615 | BF35: 25356 | BG35: 10028 | BH35: 28985 | BI35: - | BJ35: 3987 | BK35: 10787 | BL35: 9341 | BM35: 14420 | BN35: 9130 | BO35: 4293 | BP35: - | BQ35: 1844 | BR35: * | BS35: 3256 | BT35: 1405 | BU35: 1899 | BV35: * | BW35: 38182 | BX35: 17440 | BY35: 1617 | BZ35: * | CA35: 2242 | CB35: - | CC35: 1575 | CD35: 3269 | CE35: 7921 | CF35: * | CG35: 1669 | CH35: - | CI35: - | CJ35: - | CK35: * | CL35: 582439 | CO35: 2136 | CP35: IT quality and testing professionals | CQ35: Full Unit Group | CS35: =CL37 -> 36367
A36: 2135 Cyber security professionals | B36: - | C36: - | D36: - | E36: - | F36: - | G36: - | H36: - | I36: - | J36: * | K36: - | L36: - | M36: - | N36: - | O36: - | P36: - | Q36: - | R36: - | S36: - | T36: - | U36: * | V36: - | W36: * | X36: - | Y36: - | Z36: * | AA36: - | AB36: - | AC36: * | AD36: * | AE36: - | AF36: - | AG36: - | AH36: * | AI36: - | AJ36: - | AK36: - | AL36: - | AM36: * | AN36: - | AO36: * | AP36: - | AQ36: 2229 | AR36: * | AS36: * | AT36: - | AU36: - | AV36: * | AW36: * | AX36: - | AY36: - | AZ36: * | BA36: * | BB36: - | BC36: 11325 | BD36: 8220 | BE36: - | BF36: 4116 | BG36: 435 | BH36: 4765 | BI36: - | BJ36: * | BK36: 3668 | BL36: * | BM36: * | BN36: * | BO36: 3675 | BP36: - | BQ36: - | BR36: * | BS36: - | BT36: 5654 | BU36: * | BV36: - | BW36: 4097 | BX36: * | BY36: 1413 | BZ36: - | CA36: - | CB36: - | CC36: - | CD36: - | CE36: - | CF36: * | CG36: - | CH36: - | CI36: - | CJ36: - | CK36: - | CL36: 65151 | CO36: 2139/01 | CP36: DevOps engineers | CQ36: validated 2139 results | CR36: 0.461 | CS36: =CR36*CL39 -> 78858.66
A37: 2136 IT quality and testing professionals | B37: - | C37: - | D37: - | E37: - | F37: - | G37: - | H37: - | I37: - | J37: - | K37: - | L37: - | M37: - | N37: - | O37: - | P37: - | Q37: - | R37: - | S37: - | T37: - | U37: - | V37: - | W37: - | X37: - | Y37: - | Z37: * | AA37: - | AB37: - | AC37: - | AD37: * | AE37: - | AF37: - | AG37: * | AH37: - | AI37: - | AJ37: - | AK37: - | AL37: - | AM37: - | AN37: * | AO37: - | AP37: - | AQ37: * | AR37: * | AS37: - | AT37: - | AU37: - | AV37: - | AW37: * | AX37: - | AY37: - | AZ37: - | BA37: - | BB37: * | BC37: * | BD37: 17081 | BE37: * | BF37: 3442 | BG37: - | BH37: * | BI37: - | BJ37: * | BK37: * | BL37: - | BM37: - | BN37: - | BO37: * | BP37: - | BQ37: - | BR37: - | BS37: - | BT37: * | BU37: - | BV37: * | BW37: 2277 | BX37: - | BY37: * | BZ37: - | CA37: - | CB37: - | CC37: - | CD37: * | CE37: - | CF37: * | CG37: * | CH37: - | CI37: - | CJ37: - | CK37: - | CL37: 36367 | CN37: 2. Data, Analytics & Databases | CO37: 3544 | CP37: Data analysts | CQ37: Full Unit Group | CS37: =CL44 -> 110449 | CT37: =SUM(CS37:CS39) -> 300662
A38: 2137 IT network professionals | B38: - | C38: - | D38: - | E38: - | F38: - | G38: - | H38: - | I38: - | J38: - | K38: - | L38: * | M38: - | N38: - | O38: - | P38: - | Q38: - | R38: - | S38: - | T38: - | U38: - | V38: - | W38: - | X38: - | Y38: * | Z38: * | AA38: - | AB38: - | AC38: - | AD38: - | AE38: - | AF38: - | AG38: - | AH38: - | AI38: * | AJ38: - | AK38: - | AL38: - | AM38: - | AN38: * | AO38: 6470 | AP38: - | AQ38: - | AR38: * | AS38: * | AT38: - | AU38: - | AV38: - | AW38: * | AX38: - | AY38: - | AZ38: * | BA38: - | BB38: - | BC38: 6157 | BD38: 3349 | BE38: - | BF38: * | BG38: - | BH38: * | BI38: - | BJ38: * | BK38: - | BL38: 474 | BM38: - | BN38: - | BO38: * | BP38: - | BQ38: * | BR38: - | BS38: - | BT38: - | BU38: - | BV38: - | BW38: 4752 | BX38: * | BY38: - | BZ38: - | CA38: - | CB38: - | CC38: - | CD38: - | CE38: - | CF38: * | CG38: - | CH38: - | CI38: - | CJ38: - | CK38: - | CL38: 33211 | CO38: 3133 | CP38: Database administrators and web content technicians | CQ38: Full Unit Group | CS38: =CL43 -> 61471
A39: 2139 Information technology professionals n.e.c. | B39: - | C39: - | D39: - | E39: - | F39: - | G39: - | H39: - | I39: * | J39: - | K39: * | L39: - | M39: - | N39: - | O39: - | P39: - | Q39: - | R39: 1040 | S39: - | T39: * | U39: * | V39: - | W39: - | X39: - | Y39: * | Z39: 2544 | AA39: 1092 | AB39: * | AC39: * | AD39: - | AE39: - | AF39: * | AG39: * | AH39: * | AI39: - | AJ39: - | AK39: - | AL39: - | AM39: * | AN39: * | AO39: * | AP39: * | AQ39: 2465 | AR39: 1723 | AS39: - | AT39: * | AU39: - | AV39: - | AW39: - | AX39: - | AY39: - | AZ39: 1244 | BA39: * | BB39: * | BC39: 6499 | BD39: 89297 | BE39: * | BF39: 5312 | BG39: 2287 | BH39: 2837 | BI39: - | BJ39: * | BK39: 16093 | BL39: 4042 | BM39: * | BN39: - | BO39: 1535 | BP39: - | BQ39: * | BR39: - | BS39: - | BT39: * | BU39: - | BV39: * | BW39: 7491 | BX39: 3561 | BY39: 1569 | BZ39: - | CA39: - | CB39: - | CC39: * | CD39: - | CE39: * | CF39: * | CG39: - | CH39: * | CI39: - | CJ39: - | CK39: * | CL39: 171060 | CO39: 2133/02 + 2133/03 | CP39: Data architects + Data engineers | CQ39: validated 2133 results | CR39: 0.645 | CS39: =CR39*CL34 -> 128742
A40: 2141 Web design professionals | B40: - | C40: - | D40: - | E40: - | F40: - | G40: - | H40: - | I40: - | J40: - | K40: - | L40: - | M40: - | N40: - | O40: - | P40: - | Q40: - | R40: - | S40: - | T40: - | U40: - | V40: - | W40: - | X40: - | Y40: - | Z40: * | AA40: - | AB40: * | AC40: - | AD40: - | AE40: - | AF40: - | AG40: - | AH40: - | AI40: - | AJ40: - | AK40: - | AL40: - | AM40: - | AN40: - | AO40: - | AP40: - | AQ40: * | AR40: - | AS40: - | AT40: - | AU40: - | AV40: * | AW40: - | AX40: - | AY40: - | AZ40: * | BA40: - | BB40: - | BC40: * | BD40: 15073 | BE40: * | BF40: * | BG40: - | BH40: * | BI40: - | BJ40: - | BK40: * | BL40: * | BM40: - | BN40: * | BO40: - | BP40: - | BQ40: - | BR40: - | BS40: - | BT40: - | BU40: - | BV40: * | BW40: * | BX40: - | BY40: - | BZ40: - | CA40: * | CB40: * | CC40: * | CD40: * | CE40: * | CF40: - | CG40: - | CH40: * | CI40: - | CJ40: - | CK40: - | CL40: 30851 | CN40: 3. Cybersecurity | CO40: 2135 | CP40: Cyber security professionals | CQ40: Full Unit Group | CS40: =CL36 -> 65151 | CT40: =CS40 -> 65151
A41: 3131 IT operations technicians | B41: - | C41: - | D41: - | E41: - | F41: - | G41: - | H41: - | I41: 2365 | J41: - | K41: - | L41: - | M41: - | N41: - | O41: - | P41: - | Q41: - | R41: * | S41: - | T41: * | U41: * | V41: - | W41: - | X41: - | Y41: - | Z41: 1328 | AA41: - | AB41: * | AC41: * | AD41: * | AE41: - | AF41: - | AG41: - | AH41: * | AI41: 943 | AJ41: - | AK41: - | AL41: - | AM41: - | AN41: 964 | AO41: 1981 | AP41: * | AQ41: * | AR41: * | AS41: * | AT41: - | AU41: - | AV41: * | AW41: - | AX41: - | AY41: - | AZ41: * | BA41: - | BB41: - | BC41: 3122 | BD41: 24214 | BE41: * | BF41: 1011 | BG41: - | BH41: 3001 | BI41: * | BJ41: * | BK41: 2497 | BL41: 1635 | BM41: * | BN41: * | BO41: 1996 | BP41: - | BQ41: * | BR41: * | BS41: - | BT41: - | BU41: * | BV41: * | BW41: 14178 | BX41: 8652 | BY41: 7684 | BZ41: - | CA41: - | CB41: - | CC41: * | CD41: - | CE41: - | CF41: * | CG41: 4442 | CH41: - | CI41: - | CJ41: - | CK41: - | CL41: 96362 | CN41: 4. Web, Applications & UX/UI | CO41: 2141 | CP41: Web design professionals | CQ41: Full Unit Group | CS41: =CL40 -> 30851 | CT41: =SUM(CS41:CS42) -> 80458.4
A42: 3132 IT user support technicians | B42: - | C42: - | D42: - | E42: - | F42: - | G42: - | H42: - | I42: * | J42: - | K42: - | L42: - | M42: - | N42: - | O42: - | P42: - | Q42: - | R42: * | S42: - | T42: - | U42: - | V42: * | W42: - | X42: - | Y42: * | Z42: 4843 | AA42: * | AB42: 2414 | AC42: - | AD42: * | AE42: * | AF42: - | AG42: 1184 | AH42: * | AI42: - | AJ42: * | AK42: - | AL42: - | AM42: * | AN42: 1137 | AO42: * | AP42: * | AQ42: * | AR42: 4739 | AS42: * | AT42: - | AU42: - | AV42: * | AW42: - | AX42: - | AY42: - | AZ42: 3838 | BA42: - | BB42: * | BC42: 4514 | BD42: 35315 | BE42: * | BF42: 14203 | BG42: * | BH42: 2813 | BI42: 929 | BJ42: 2178 | BK42: 3688 | BL42: 2151 | BM42: * | BN42: * | BO42: - | BP42: - | BQ42: * | BR42: - | BS42: - | BT42: 1709 | BU42: 2134 | BV42: 1105 | BW42: 12372 | BX42: 5852 | BY42: 7880 | BZ42: * | CA42: 2290 | CB42: - | CC42: 1246 | CD42: - | CE42: 1004 | CF42: 1680 | CG42: 2389 | CH42: - | CI42: - | CJ42: - | CK42: * | CL42: 143956 | CO42: 2139/03 | CP42: Webmasters / Website managers | CQ42: validated 2139 results | CR42: 0.29 | CS42: =CR42*CL39 -> 49607.4
A43: 3133 Database administrators and web content technicians | B43: - | C43: - | D43: - | E43: - | F43: * | G43: - | H43: - | I43: - | J43: - | K43: 659 | L43: - | M43: - | N43: - | O43: - | P43: - | Q43: - | R43: * | S43: - | T43: - | U43: - | V43: - | W43: * | X43: - | Y43: - | Z43: * | AA43: * | AB43: - | AC43: - | AD43: - | AE43: - | AF43: - | AG43: - | AH43: - | AI43: - | AJ43: - | AK43: * | AL43: * | AM43: - | AN43: * | AO43: - | AP43: * | AQ43: - | AR43: 2011 | AS43: - | AT43: - | AU43: - | AV43: - | AW43: - | AX43: - | AY43: - | AZ43: 1551 | BA43: - | BB43: - | BC43: - | BD43: 8927 | BE43: 1714 | BF43: 2605 | BG43: 1236 | BH43: 1085 | BI43: * | BJ43: - | BK43: 3606 | BL43: * | BM43: * | BN43: 3230 | BO43: * | BP43: - | BQ43: - | BR43: * | BS43: - | BT43: * | BU43: - | BV43: - | BW43: 10797 | BX43: 4785 | BY43: 933 | BZ43: * | CA43: * | CB43: * | CC43: - | CD43: - | CE43: * | CF43: * | CG43: - | CH43: * | CI43: - | CJ43: - | CK43: - | CL43: 61471 | CN43: 5. IT Infrastructure, Networks & Support | CO43: 2137 | CP43: IT network professionals | CQ43: Full Unit Group | CS43: =CL38 -> 33211 | CT43: =SUM(CS43:CS46) -> 333209.4
A44: 3544 Data analysts | B44: - | C44: - | D44: - | E44: - | F44: - | G44: - | H44: - | I44: - | J44: - | K44: - | L44: - | M44: - | N44: - | O44: - | P44: - | Q44: - | R44: * | S44: - | T44: * | U44: * | V44: - | W44: - | X44: - | Y44: * | Z44: * | AA44: - | AB44: - | AC44: - | AD44: * | AE44: - | AF44: - | AG44: * | AH44: * | AI44: 4547 | AJ44: - | AK44: - | AL44: - | AM44: * | AN44: * | AO44: * | AP44: - | AQ44: * | AR44: 2784 | AS44: * | AT44: - | AU44: - | AV44: * | AW44: * | AX44: - | AY44: * | AZ44: * | BA44: - | BB44: - | BC44: * | BD44: 19724 | BE44: - | BF44: 4726 | BG44: 4022 | BH44: 3851 | BI44: - | BJ44: 1675 | BK44: 2886 | BL44: 3448 | BM44: * | BN44: 2463 | BO44: - | BP44: - | BQ44: * | BR44: - | BS44: * | BT44: - | BU44: * | BV44: * | BW44: 21092 | BX44: 5228 | BY44: 6388 | BZ44: * | CA44: 2014 | CB44: - | CC44: - | CD44: * | CE44: * | CF44: 1466 | CG44: - | CH44: - | CI44: - | CJ44: - | CK44: - | CL44: 110449 | CO44: 3131 | CP44: IT operations technicians | CQ44: Full Unit Group | CS44: =CL41 -> 96362
CO45: 3132 | CP45: IT user support technicians | CQ45: Full Unit Group | CS45: =CL42 -> 143956
CO46: 2133/04 + 2133/06 | CP46: Systems architects + Solution architects | CQ46: validated 2133 results | CR46: 0.299 | CS46: =CR46*CL34 -> 59680.4
A48: January-December 2024 | B48: Weighted 2022 | CL48: Total 2024 | CS48: Total 2024 | CT48: Total By Career Area
A49: 2133 IT business analysts, architects and systems designers | B49: - | C49: - | D49: - | E49: - | F49: - | G49: - | H49: - | I49: * | J49: 1871 | K49: - | L49: - | M49: - | N49: * | O49: - | P49: - | Q49: - | R49: * | S49: - | T49: * | U49: 2929 | V49: * | W49: - | X49: - | Y49: * | Z49: 2526 | AA49: * | AB49: 2035 | AC49: 2677 | AD49: 2094 | AE49: - | AF49: * | AG49: - | AH49: 1388 | AI49: * | AJ49: - | AK49: - | AL49: - | AM49: 1328 | AN49: 2485 | AO49: * | AP49: * | AQ49: 3288 | AR49: 3390 | AS49: * | AT49: - | AU49: 1616 | AV49: 1882 | AW49: - | AX49: - | AY49: - | AZ49: 5042 | BA49: * | BB49: * | BC49: 4118 | BD49: 59259 | BE49: 1215 | BF49: 11962 | BG49: 5317 | BH49: 10734 | BI49: * | BJ49: 1552 | BK49: 5614 | BL49: 10154 | BM49: 3533 | BN49: 2427 | BO49: * | BP49: - | BQ49: - | BR49: * | BS49: * | BT49: * | BU49: - | BV49: * | BW49: 24498 | BX49: 4668 | BY49: 5316 | BZ49: - | CA49: * | CB49: - | CC49: * | CD49: * | CE49: - | CF49: 1362 | CG49: 1723 | CH49: - | CI49: - | CJ49: - | CK49: * | CL49: 204940 | CN49: 1. Software Development & Testing | CO49: 2134 | CP49: Programmers and software development professionals | CQ49: Full Unit Group | CS49: =CL50 -> 557287 | CT49: =SUM(CS49:CS51) -> 655901.02
A50: 2134 Programmers and software development professionals | B50: - | C50: - | D50: * | E50: - | F50: - | G50: - | H50: - | I50: * | J50: * | K50: - | L50: - | M50: - | N50: - | O50: - | P50: - | Q50: - | R50: 1359 | S50: * | T50: * | U50: 3049 | V50: - | W50: - | X50: - | Y50: 2586 | Z50: 17017 | AA50: 4747 | AB50: 3959 | AC50: 2191 | AD50: 3282 | AE50: * | AF50: 1561 | AG50: 2105 | AH50: * | AI50: * | AJ50: - | AK50: * | AL50: - | AM50: 1802 | AN50: 2640 | AO50: 7396 | AP50: * | AQ50: 9120 | AR50: 10887 | AS50: 2684 | AT50: 579 | AU50: - | AV50: - | AW50: * | AX50: - | AY50: * | AZ50: 11386 | BA50: * | BB50: * | BC50: 5196 | BD50: 255324 | BE50: 1726 | BF50: 21499 | BG50: 16857 | BH50: 26494 | BI50: 3336 | BJ50: 6899 | BK50: 12690 | BL50: 13255 | BM50: 11672 | BN50: 5230 | BO50: 2200 | BP50: - | BQ50: 893 | BR50: 3016 | BS50: 1994 | BT50: * | BU50: * | BV50: 2490 | BW50: 30808 | BX50: 12876 | BY50: 3526 | BZ50: * | CA50: * | CB50: - | CC50: 3483 | CD50: 4826 | CE50: 4233 | CF50: 3250 | CG50: 955 | CH50: - | CI50: - | CJ50: - | CK50: 2475 | CL50: 557287 | CO50: 2136 | CP50: IT quality and testing professionals | CQ50: Full Unit Group | CS50: =CL52 -> 26911
A51: 2135 Cyber security professionals | B51: - | C51: - | D51: - | E51: - | F51: - | G51: - | H51: - | I51: - | J51: - | K51: - | L51: - | M51: - | N51: - | O51: - | P51: - | Q51: - | R51: - | S51: - | T51: - | U51: * | V51: * | W51: - | X51: - | Y51: - | Z51: 1236 | AA51: - | AB51: - | AC51: - | AD51: * | AE51: - | AF51: - | AG51: - | AH51: * | AI51: - | AJ51: - | AK51: - | AL51: - | AM51: - | AN51: - | AO51: - | AP51: - | AQ51: * | AR51: * | AS51: * | AT51: * | AU51: * | AV51: * | AW51: - | AX51: * | AY51: - | AZ51: * | BA51: - | BB51: * | BC51: 4797 | BD51: 19477 | BE51: * | BF51: 5179 | BG51: 2100 | BH51: 4793 | BI51: * | BJ51: * | BK51: - | BL51: * | BM51: - | BN51: * | BO51: 2056 | BP51: - | BQ51: - | BR51: - | BS51: * | BT51: 5976 | BU51: 1699 | BV51: - | BW51: 9586 | BX51: 2351 | BY51: 1736 | BZ51: - | CA51: * | CB51: - | CC51: * | CD51: - | CE51: - | CF51: - | CG51: - | CH51: - | CI51: - | CJ51: - | CK51: - | CL51: 72567 | CO51: 2139/01 | CP51: DevOps engineers | CQ51: validated 2139 results | CR51: 0.461 | CS51: =CR51*CL54 -> 71703.018
A52: 2136 IT quality and testing professionals | B52: - | C52: - | D52: - | E52: - | F52: - | G52: - | H52: - | I52: - | J52: - | K52: - | L52: - | M52: - | N52: * | O52: - | P52: - | Q52: - | R52: - | S52: - | T52: - | U52: - | V52: - | W52: - | X52: - | Y52: - | Z52: 2700 | AA52: - | AB52: - | AC52: - | AD52: - | AE52: - | AF52: - | AG52: * | AH52: - | AI52: - | AJ52: - | AK52: - | AL52: - | AM52: - | AN52: - | AO52: - | AP52: * | AQ52: * | AR52: * | AS52: * | AT52: - | AU52: - | AV52: - | AW52: * | AX52: - | AY52: - | AZ52: * | BA52: - | BB52: - | BC52: - | BD52: 8429 | BE52: - | BF52: 1653 | BG52: * | BH52: - | BI52: - | BJ52: 1514 | BK52: * | BL52: * | BM52: - | BN52: - | BO52: * | BP52: - | BQ52: - | BR52: - | BS52: - | BT52: - | BU52: - | BV52: * | BW52: 2039 | BX52: * | BY52: * | BZ52: - | CA52: - | CB52: - | CC52: - | CD52: - | CE52: - | CF52: - | CG52: - | CH52: - | CI52: - | CJ52: - | CK52: - | CL52: 26911 | CN52: 2. Data, Analytics & Databases | CO52: 3544 | CP52: Data analysts | CQ52: Full Unit Group | CS52: =CL59 -> 127180 | CT52: =SUM(CS52:CS54) -> 326068.3
A53: 2137 IT network professionals | B53: - | C53: - | D53: - | E53: - | F53: - | G53: - | H53: - | I53: * | J53: - | K53: - | L53: - | M53: - | N53: - | O53: - | P53: - | Q53: - | R53: - | S53: - | T53: - | U53: - | V53: - | W53: - | X53: - | Y53: - | Z53: - | AA53: - | AB53: - | AC53: - | AD53: - | AE53: - | AF53: - | AG53: * | AH53: - | AI53: - | AJ53: * | AK53: - | AL53: - | AM53: * | AN53: * | AO53: 2934 | AP53: - | AQ53: - | AR53: - | AS53: * | AT53: - | AU53: - | AV53: * | AW53: * | AX53: - | AY53: - | AZ53: * | BA53: - | BB53: - | BC53: 6672 | BD53: 9673 | BE53: - | BF53: * | BG53: - | BH53: - | BI53: - | BJ53: - | BK53: - | BL53: 1156 | BM53: - | BN53: - | BO53: - | BP53: - | BQ53: - | BR53: - | BS53: - | BT53: - | BU53: * | BV53: - | BW53: 3458 | BX53: * | BY53: - | BZ53: - | CA53: - | CB53: - | CC53: - | CD53: - | CE53: - | CF53: - | CG53: * | CH53: - | CI53: - | CJ53: - | CK53: - | CL53: 33609 | CO53: 3133 | CP53: Database administrators and web content technicians | CQ53: Full Unit Group | CS53: =CL58 -> 66702
A54: 2139 Information technology professionals n.e.c. | B54: - | C54: - | D54: - | E54: - | F54: - | G54: - | H54: - | I54: - | J54: - | K54: - | L54: - | M54: - | N54: - | O54: - | P54: - | Q54: - | R54: - | S54: - | T54: * | U54: - | V54: * | W54: - | X54: - | Y54: - | Z54: * | AA54: - | AB54: - | AC54: - | AD54: - | AE54: * | AF54: * | AG54: - | AH54: * | AI54: - | AJ54: - | AK54: - | AL54: - | AM54: * | AN54: * | AO54: * | AP54: - | AQ54: 1746 | AR54: 3581 | AS54: - | AT54: * | AU54: - | AV54: * | AW54: - | AX54: - | AY54: - | AZ54: 964 | BA54: * | BB54: 1633 | BC54: 2801 | BD54: 84152 | BE54: 2364 | BF54: 7076 | BG54: * | BH54: 1562 | BI54: * | BJ54: 3072 | BK54: 14105 | BL54: 3105 | BM54: * | BN54: 3432 | BO54: * | BP54: - | BQ54: - | BR54: * | BS54: - | BT54: * | BU54: * | BV54: * | BW54: 6519 | BX54: 1689 | BY54: * | BZ54: - | CA54: 1902 | CB54: - | CC54: 1003 | CD54: * | CE54: - | CF54: * | CG54: * | CH54: - | CI54: - | CJ54: - | CK54: - | CL54: 155538 | CO54: 2133/02 + 2133/03 | CP54: Data architects + Data engineers | CQ54: validated 2133 results | CR54: 0.645 | CS54: =CR54*CL49 -> 132186.3
A55: 2141 Web design professionals | B55: - | C55: - | D55: - | E55: - | F55: - | G55: - | H55: - | I55: - | J55: - | K55: - | L55: - | M55: - | N55: - | O55: - | P55: - | Q55: - | R55: * | S55: - | T55: - | U55: - | V55: - | W55: - | X55: - | Y55: - | Z55: - | AA55: - | AB55: * | AC55: - | AD55: - | AE55: - | AF55: - | AG55: - | AH55: - | AI55: - | AJ55: - | AK55: - | AL55: - | AM55: - | AN55: - | AO55: * | AP55: * | AQ55: * | AR55: - | AS55: - | AT55: - | AU55: - | AV55: - | AW55: - | AX55: - | AY55: * | AZ55: 2161 | BA55: - | BB55: - | BC55: - | BD55: 21840 | BE55: * | BF55: 1319 | BG55: * | BH55: * | BI55: - | BJ55: * | BK55: 1466 | BL55: 2950 | BM55: * | BN55: 1780 | BO55: * | BP55: - | BQ55: - | BR55: - | BS55: - | BT55: - | BU55: - | BV55: - | BW55: 2432 | BX55: - | BY55: * | BZ55: - | CA55: - | CB55: - | CC55: 982 | CD55: - | CE55: * | CF55: * | CG55: - | CH55: * | CI55: - | CJ55: - | CK55: - | CL55: 44743 | CN55: 3. Cybersecurity | CO55: 2135 | CP55: Cyber security professionals | CQ55: Full Unit Group | CS55: =CL51 -> 72567 | CT55: =CS55 -> 72567
A56: 3131 IT operations technicians | B56: - | C56: - | D56: - | E56: - | F56: - | G56: - | H56: * | I56: - | J56: 1623 | K56: * | L56: - | M56: - | N56: - | O56: - | P56: - | Q56: - | R56: * | S56: * | T56: * | U56: - | V56: - | W56: - | X56: - | Y56: - | Z56: * | AA56: * | AB56: * | AC56: 1484 | AD56: * | AE56: - | AF56: * | AG56: * | AH56: * | AI56: * | AJ56: - | AK56: * | AL56: - | AM56: - | AN56: 1065 | AO56: * | AP56: - | AQ56: 1133 | AR56: 3090 | AS56: * | AT56: - | AU56: - | AV56: * | AW56: * | AX56: - | AY56: - | AZ56: - | BA56: - | BB56: - | BC56: 2517 | BD56: 19766 | BE56: * | BF56: 2692 | BG56: - | BH56: * | BI56: * | BJ56: 1288 | BK56: 2636 | BL56: 1577 | BM56: - | BN56: * | BO56: * | BP56: - | BQ56: * | BR56: 1924 | BS56: - | BT56: * | BU56: - | BV56: - | BW56: 10161 | BX56: 6805 | BY56: 4909 | BZ56: * | CA56: 757 | CB56: - | CC56: * | CD56: - | CE56: - | CF56: * | CG56: 1786 | CH56: - | CI56: - | CJ56: - | CK56: - | CL56: 85931 | CN56: 4. Web, Applications & UX/UI | CO56: 2141 | CP56: Web design professionals | CQ56: Full Unit Group | CS56: =CL55 -> 44743 | CT56: =SUM(CS56:CS57) -> 89849.02
A57: 3132 IT user support technicians | B57: - | C57: - | D57: - | E57: - | F57: - | G57: - | H57: - | I57: 3199 | J57: * | K57: - | L57: - | M57: - | N57: - | O57: - | P57: - | Q57: * | R57: * | S57: - | T57: * | U57: * | V57: * | W57: - | X57: * | Y57: * | Z57: 1319 | AA57: * | AB57: - | AC57: * | AD57: 2180 | AE57: - | AF57: * | AG57: * | AH57: * | AI57: * | AJ57: - | AK57: - | AL57: * | AM57: 1119 | AN57: * | AO57: * | AP57: - | AQ57: 1672 | AR57: 2990 | AS57: * | AT57: - | AU57: * | AV57: * | AW57: - | AX57: - | AY57: - | AZ57: 2202 | BA57: - | BB57: - | BC57: 1926 | BD57: 27925 | BE57: * | BF57: 6136 | BG57: 1146 | BH57: 4728 | BI57: * | BJ57: 1979 | BK57: 1826 | BL57: * | BM57: - | BN57: * | BO57: 2448 | BP57: * | BQ57: * | BR57: - | BS57: - | BT57: 3023 | BU57: * | BV57: 2518 | BW57: 15463 | BX57: 12116 | BY57: 3170 | BZ57: - | CA57: 3139 | CB57: - | CC57: * | CD57: - | CE57: * | CF57: * | CG57: * | CH57: - | CI57: - | CJ57: - | CK57: - | CL57: 125555 | CO57: 2139/03 | CP57: Webmasters / Website managers | CQ57: validated 2139 results | CR57: 0.29 | CS57: =CR57*CL54 -> 45106.02
A58: 3133 Database administrators and web content technicians | B58: - | C58: - | D58: - | E58: - | F58: - | G58: - | H58: - | I58: - | J58: * | K58: - | L58: - | M58: - | N58: - | O58: - | P58: - | Q58: - | R58: - | S58: - | T58: - | U58: * | V58: - | W58: - | X58: - | Y58: - | Z58: - | AA58: - | AB58: * | AC58: * | AD58: * | AE58: * | AF58: - | AG58: - | AH58: - | AI58: * | AJ58: - | AK58: - | AL58: * | AM58: - | AN58: - | AO58: - | AP58: - | AQ58: 1476 | AR58: 2366 | AS58: * | AT58: - | AU58: - | AV58: - | AW58: - | AX58: - | AY58: - | AZ58: 2708 | BA58: 2140 | BB58: * | BC58: * | BD58: 6508 | BE58: 1616 | BF58: 2279 | BG58: 2234 | BH58: 3077 | BI58: - | BJ58: - | BK58: 2520 | BL58: * | BM58: - | BN58: 2705 | BO58: 1036 | BP58: - | BQ58: - | BR58: - | BS58: - | BT58: - | BU58: - | BV58: - | BW58: 6105 | BX58: 9925 | BY58: 2645 | BZ58: - | CA58: 4656 | CB58: * | CC58: * | CD58: * | CE58: - | CF58: * | CG58: - | CH58: - | CI58: - | CJ58: - | CK58: * | CL58: 66702 | CN58: 5. IT Infrastructure, Networks & Support | CO58: 2137 | CP58: IT network professionals | CQ58: Full Unit Group | CS58: =CL53 -> 33609 | CT58: =SUM(CS58:CS61) -> 306372.06
A59: 3544 Data analysts | B59: * | C59: - | D59: - | E59: - | F59: - | G59: - | H59: - | I59: * | J59: * | K59: - | L59: - | M59: - | N59: - | O59: - | P59: - | Q59: - | R59: - | S59: * | T59: 1539 | U59: 3623 | V59: - | W59: * | X59: - | Y59: 1745 | Z59: - | AA59: - | AB59: - | AC59: - | AD59: - | AE59: - | AF59: * | AG59: * | AH59: 4389 | AI59: 1941 | AJ59: - | AK59: - | AL59: - | AM59: - | AN59: * | AO59: * | AP59: * | AQ59: 1984 | AR59: 2758 | AS59: 2270 | AT59: * | AU59: * | AV59: * | AW59: - | AX59: - | AY59: - | AZ59: 1030 | BA59: - | BB59: * | BC59: 2176 | BD59: 7497 | BE59: 534 | BF59: 7666 | BG59: 7555 | BH59: 6348 | BI59: 3029 | BJ59: 2112 | BK59: 6507 | BL59: 1958 | BM59: 1879 | BN59: 4537 | BO59: 4917 | BP59: - | BQ59: - | BR59: * | BS59: * | BT59: - | BU59: - | BV59: * | BW59: 22465 | BX59: 4557 | BY59: 3015 | BZ59: * | CA59: 4024 | CB59: - | CC59: - | CD59: * | CE59: * | CF59: * | CG59: - | CH59: - | CI59: - | CJ59: - | CK59: 1843 | CL59: 127180 | CO59: 3131 | CP59: IT operations technicians | CQ59: Full Unit Group | CS59: =CL56 -> 85931
CO60: 3132 | CP60: IT user support technicians | CQ60: Full Unit Group | CS60: =CL57 -> 125555
CO61: 2133/04 + 2133/06 | CP61: Systems architects + Solution architects | CQ61: validated 2133 results | CR61: 0.299 | CS61: =CR61*CL49 -> 61277.06
A63: January-December 2025 | B63: Weighted 2022 | CL63: Total 2025 | CS63: Total 2025 | CT63: Total By Career Area
A64: 2133 IT business analysts, architects and systems designers | B64: - | C64: - | D64: - | E64: - | F64: - | G64: - | H64: - | I64: 1672 | J64: 1011 | K64: - | L64: - | M64: * | N64: - | O64: - | P64: - | Q64: - | R64: * | S64: - | T64: * | U64: 1615 | V64: * | W64: * | X64: * | Y64: - | Z64: * | AA64: - | AB64: 1277 | AC64: 1361 | AD64: * | AE64: - | AF64: * | AG64: * | AH64: 1590 | AI64: * | AJ64: - | AK64: - | AL64: * | AM64: * | AN64: 2234 | AO64: 1174 | AP64: - | AQ64: 1060 | AR64: 3880 | AS64: * | AT64: - | AU64: * | AV64: 3457 | AW64: * | AX64: * | AY64: * | AZ64: 1889 | BA64: - | BB64: * | BC64: 5212 | BD64: 66487 | BE64: 1042 | BF64: 12763 | BG64: 5680 | BH64: 9802 | BI64: 1371 | BJ64: 2674 | BK64: 6775 | BL64: 9105 | BM64: * | BN64: 2858 | BO64: * | BP64: - | BQ64: * | BR64: - | BS64: * | BT64: 1706 | BU64: * | BV64: * | BW64: 25968 | BX64: 5208 | BY64: 3197 | BZ64: * | CA64: 1665 | CB64: - | CC64: * | CD64: 1103 | CE64: - | CF64: 2386 | CG64: * | CH64: - | CI64: - | CJ64: - | CK64: * | CL64: 203043 | CN64: 1. Software Development & Testing | CO64: 2134 | CP64: Programmers and software development professionals | CQ64: Full Unit Group | CS64: =CL65 -> 543590 | CT64: =SUM(CS64:CS66) -> 641426.62
A65: 2134 Programmers and software development professionals | B65: * | C65: - | D65: * | E65: - | F65: - | G65: - | H65: - | I65: 1385 | J65: * | K65: - | L65: - | M65: - | N65: - | O65: * | P65: * | Q65: - | R65: 4308 | S65: - | T65: * | U65: 2963 | V65: * | W65: - | X65: - | Y65: * | Z65: 10296 | AA65: 4168 | AB65: 6961 | AC65: 1161 | AD65: 5742 | AE65: - | AF65: * | AG65: 2597 | AH65: 2325 | AI65: * | AJ65: - | AK65: * | AL65: * | AM65: * | AN65: 1245 | AO65: 4817 | AP65: 1053 | AQ65: 8108 | AR65: 15359 | AS65: 1567 | AT65: * | AU65: * | AV65: 2530 | AW65: 2143 | AX65: * | AY65: * | AZ65: 11263 | BA65: 3314 | BB65: 3361 | BC65: 8239 | BD65: 241516 | BE65: 1646 | BF65: 26404 | BG65: 7053 | BH65: 26730 | BI65: 4246 | BJ65: 5163 | BK65: 8132 | BL65: 9258 | BM65: 12210 | BN65: 1517 | BO65: 4426 | BP65: - | BQ65: 2484 | BR65: * | BS65: 3104 | BT65: 1296 | BU65: - | BV65: 1007 | BW65: 29696 | BX65: 15449 | BY65: 6010 | BZ65: * | CA65: 1500 | CB65: * | CC65: 3436 | CD65: 6519 | CE65: 2489 | CF65: 1551 | CG65: * | CH65: * | CI65: - | CJ65: - | CK65: 4897 | CL65: 543590 | CO65: 2136 | CP65: IT quality and testing professionals | CQ65: Full Unit Group | CS65: =CL67 -> 35999
A66: 2135 Cyber security professionals | B66: - | C66: - | D66: * | E66: - | F66: - | G66: - | H66: - | I66: * | J66: - | K66: - | L66: - | M66: - | N66: - | O66: - | P66: - | Q66: - | R66: - | S66: - | T66: - | U66: * | V66: * | W66: - | X66: - | Y66: * | Z66: * | AA66: - | AB66: - | AC66: - | AD66: * | AE66: - | AF66: - | AG66: * | AH66: 619 | AI66: - | AJ66: - | AK66: - | AL66: - | AM66: - | AN66: * | AO66: * | AP66: * | AQ66: * | AR66: * | AS66: - | AT66: * | AU66: - | AV66: - | AW66: - | AX66: - | AY66: * | AZ66: - | BA66: - | BB66: - | BC66: 5654 | BD66: 20930 | BE66: * | BF66: 4781 | BG66: 1610 | BH66: 4510 | BI66: - | BJ66: * | BK66: 2969 | BL66: * | BM66: * | BN66: * | BO66: 1708 | BP66: - | BQ66: - | BR66: - | BS66: - | BT66: 8929 | BU66: * | BV66: - | BW66: 13414 | BX66: 2622 | BY66: 1814 | BZ66: - | CA66: * | CB66: - | CC66: 717 | CD66: * | CE66: * | CF66: - | CG66: - | CH66: - | CI66: - | CJ66: - | CK66: * | CL66: 83476 | CO66: 2139/01 | CP66: DevOps engineers | CQ66: validated 2139 results | CR66: 0.461 | CS66: =CR66*CL69 -> 61837.618
A67: 2136 IT quality and testing professionals | B67: - | C67: - | D67: - | E67: - | F67: - | G67: - | H67: - | I67: - | J67: - | K67: - | L67: - | M67: - | N67: - | O67: - | P67: - | Q67: - | R67: - | S67: - | T67: - | U67: - | V67: - | W67: - | X67: - | Y67: - | Z67: 1304 | AA67: - | AB67: - | AC67: - | AD67: * | AE67: - | AF67: - | AG67: * | AH67: - | AI67: - | AJ67: - | AK67: - | AL67: - | AM67: - | AN67: * | AO67: - | AP67: * | AQ67: * | AR67: * | AS67: - | AT67: - | AU67: - | AV67: * | AW67: - | AX67: - | AY67: - | AZ67: 937 | BA67: - | BB67: - | BC67: * | BD67: 15351 | BE67: * | BF67: 2356 | BG67: 1921 | BH67: 1287 | BI67: * | BJ67: * | BK67: - | BL67: * | BM67: * | BN67: * | BO67: * | BP67: - | BQ67: - | BR67: - | BS67: * | BT67: - | BU67: - | BV67: * | BW67: 2029 | BX67: * | BY67: - | BZ67: - | CA67: - | CB67: - | CC67: - | CD67: * | CE67: * | CF67: - | CG67: - | CH67: - | CI67: - | CJ67: - | CK67: - | CL67: 35999 | CN67: 2. Data, Analytics & Databases | CO67: 3544 | CP67: Data analysts | CQ67: Full Unit Group | CS67: =CL74 -> 132127 | CT67: =SUM(CS67:CS69) -> 316599.73
A68: 2137 IT network professionals | B68: - | C68: - | D68: - | E68: - | F68: - | G68: - | H68: - | I68: - | J68: - | K68: - | L68: - | M68: - | N68: - | O68: - | P68: - | Q68: - | R68: - | S68: - | T68: - | U68: - | V68: - | W68: - | X68: - | Y68: - | Z68: - | AA68: * | AB68: - | AC68: - | AD68: - | AE68: - | AF68: - | AG68: * | AH68: 1048 | AI68: * | AJ68: - | AK68: - | AL68: - | AM68: - | AN68: * | AO68: 2868 | AP68: - | AQ68: - | AR68: * | AS68: * | AT68: - | AU68: - | AV68: * | AW68: * | AX68: - | AY68: - | AZ68: * | BA68: - | BB68: - | BC68: 7351 | BD68: 6725 | BE68: - | BF68: - | BG68: * | BH68: * | BI68: - | BJ68: - | BK68: - | BL68: * | BM68: - | BN68: - | BO68: - | BP68: - | BQ68: - | BR68: - | BS68: * | BT68: - | BU68: - | BV68: - | BW68: 1128 | BX68: * | BY68: * | BZ68: - | CA68: - | CB68: - | CC68: * | CD68: - | CE68: * | CF68: - | CG68: * | CH68: - | CI68: - | CJ68: - | CK68: * | CL68: 30483 | CO68: 3133 | CP68: Database administrators and web content technicians | CQ68: Full Unit Group | CS68: =CL73 -> 53510
A69: 2139 Information technology professionals n.e.c. | B69: - | C69: - | D69: - | E69: - | F69: - | G69: - | H69: - | I69: * | J69: - | K69: - | L69: - | M69: - | N69: - | O69: - | P69: - | Q69: - | R69: * | S69: * | T69: - | U69: - | V69: * | W69: - | X69: - | Y69: * | Z69: 551 | AA69: - | AB69: * | AC69: - | AD69: * | AE69: - | AF69: - | AG69: 1259 | AH69: * | AI69: - | AJ69: - | AK69: - | AL69: - | AM69: * | AN69: 2045 | AO69: * | AP69: - | AQ69: 2211 | AR69: 2815 | AS69: * | AT69: * | AU69: - | AV69: - | AW69: * | AX69: - | AY69: - | AZ69: 2203 | BA69: - | BB69: * | BC69: 3189 | BD69: 70987 | BE69: 2075 | BF69: 3072 | BG69: 1476 | BH69: 1479 | BI69: * | BJ69: 3342 | BK69: 8390 | BL69: 3454 | BM69: * | BN69: * | BO69: - | BP69: - | BQ69: - | BR69: - | BS69: * | BT69: 1092 | BU69: * | BV69: - | BW69: 3052 | BX69: 3655 | BY69: * | BZ69: * | CA69: * | CB69: - | CC69: 1478 | CD69: * | CE69: * | CF69: 1267 | CG69: * | CH69: * | CI69: - | CJ69: - | CK69: * | CL69: 134138 | CO69: 2133/02 + 2133/03 | CP69: Data architects + Data engineers | CQ69: validated 2133 results | CR69: 0.645 | CS69: =CR69*CL64 -> 130962.74
A70: 2141 Web design professionals | B70: - | C70: - | D70: - | E70: - | F70: - | G70: - | H70: - | I70: - | J70: - | K70: - | L70: - | M70: - | N70: - | O70: - | P70: - | Q70: - | R70: * | S70: - | T70: - | U70: - | V70: - | W70: - | X70: - | Y70: - | Z70: - | AA70: - | AB70: * | AC70: - | AD70: - | AE70: - | AF70: - | AG70: - | AH70: - | AI70: - | AJ70: - | AK70: - | AL70: - | AM70: - | AN70: - | AO70: * | AP70: - | AQ70: * | AR70: 1923 | AS70: - | AT70: - | AU70: - | AV70: - | AW70: - | AX70: - | AY70: - | AZ70: * | BA70: - | BB70: - | BC70: * | BD70: 14742 | BE70: * | BF70: * | BG70: * | BH70: - | BI70: - | BJ70: - | BK70: * | BL70: 1812 | BM70: * | BN70: * | BO70: * | BP70: - | BQ70: - | BR70: - | BS70: - | BT70: - | BU70: * | BV70: * | BW70: * | BX70: - | BY70: - | BZ70: - | CA70: - | CB70: - | CC70: * | CD70: * | CE70: * | CF70: * | CG70: - | CH70: * | CI70: - | CJ70: - | CK70: - | CL70: 31060 | CN70: 3. Cybersecurity | CO70: 2135 | CP70: Cyber security professionals | CQ70: Full Unit Group | CS70: =CL66 -> 83476 | CT70: =CS70 -> 83476
A71: 3131 IT operations technicians | B71: - | C71: - | D71: - | E71: - | F71: - | G71: - | H71: - | I71: * | J71: * | K71: - | L71: - | M71: - | N71: - | O71: - | P71: - | Q71: - | R71: * | S71: - | T71: - | U71: * | V71: - | W71: * | X71: - | Y71: - | Z71: 1535 | AA71: - | AB71: * | AC71: * | AD71: - | AE71: - | AF71: * | AG71: * | AH71: - | AI71: * | AJ71: - | AK71: - | AL71: - | AM71: 1384 | AN71: * | AO71: * | AP71: * | AQ71: 2493 | AR71: 3997 | AS71: * | AT71: - | AU71: - | AV71: 1590 | AW71: - | AX71: * | AY71: * | AZ71: 1289 | BA71: - | BB71: - | BC71: 1553 | BD71: 18141 | BE71: 3306 | BF71: * | BG71: 1799 | BH71: * | BI71: * | BJ71: 1467 | BK71: 3298 | BL71: 3423 | BM71: * | BN71: * | BO71: - | BP71: - | BQ71: * | BR71: - | BS71: * | BT71: * | BU71: - | BV71: - | BW71: 9194 | BX71: 6012 | BY71: 3477 | BZ71: - | CA71: 1057 | CB71: - | CC71: * | CD71: - | CE71: * | CF71: * | CG71: 1222 | CH71: * | CI71: - | CJ71: - | CK71: * | CL71: 84966 | CN71: 4. Web, Applications & UX/UI | CO71: 2141 | CP71: Web design professionals | CQ71: Full Unit Group | CS71: =CL70 -> 31060 | CT71: =SUM(CS71:CS72) -> 69960.02
A72: 3132 IT user support technicians | B72: * | C72: - | D72: - | E72: - | F72: - | G72: - | H72: - | I72: * | J72: * | K72: - | L72: - | M72: * | N72: - | O72: - | P72: - | Q72: * | R72: * | S72: - | T72: * | U72: * | V72: - | W72: * | X72: - | Y72: * | Z72: 1417 | AA72: - | AB72: - | AC72: * | AD72: - | AE72: * | AF72: * | AG72: * | AH72: * | AI72: * | AJ72: - | AK72: - | AL72: - | AM72: 1873 | AN72: * | AO72: * | AP72: * | AQ72: 2103 | AR72: 3496 | AS72: * | AT72: * | AU72: - | AV72: 1823 | AW72: * | AX72: * | AY72: - | AZ72: * | BA72: - | BB72: - | BC72: 3645 | BD72: 40111 | BE72: * | BF72: 3181 | BG72: * | BH72: 3501 | BI72: * | BJ72: 1135 | BK72: 2081 | BL72: 2496 | BM72: 2259 | BN72: * | BO72: - | BP72: - | BQ72: - | BR72: - | BS72: * | BT72: * | BU72: * | BV72: * | BW72: 14070 | BX72: 8604 | BY72: 4964 | BZ72: - | CA72: * | CB72: - | CC72: 2957 | CD72: * | CE72: * | CF72: 1710 | CG72: - | CH72: * | CI72: - | CJ72: - | CK72: - | CL72: 123533 | CO72: 2139/03 | CP72: Webmasters / Website managers | CQ72: validated 2139 results | CR72: 0.29 | CS72: =CR72*CL69 -> 38900.02
A73: 3133 Database administrators and web content technicians | B73: - | C73: - | D73: - | E73: - | F73: - | G73: - | H73: - | I73: * | J73: * | K73: - | L73: - | M73: - | N73: - | O73: - | P73: - | Q73: - | R73: * | S73: - | T73: - | U73: * | V73: - | W73: * | X73: - | Y73: - | Z73: * | AA73: - | AB73: - | AC73: - | AD73: - | AE73: - | AF73: - | AG73: * | AH73: * | AI73: * | AJ73: - | AK73: - | AL73: - | AM73: - | AN73: 1334 | AO73: * | AP73: - | AQ73: * | AR73: 3286 | AS73: - | AT73: - | AU73: - | AV73: - | AW73: - | AX73: - | AY73: - | AZ73: 4041 | BA73: * | BB73: * | BC73: * | BD73: 3672 | BE73: 1664 | BF73: 2069 | BG73: * | BH73: * | BI73: - | BJ73: * | BK73: 1300 | BL73: 1468 | BM73: * | BN73: 5126 | BO73: 926 | BP73: - | BQ73: - | BR73: - | BS73: - | BT73: - | BU73: - | BV73: - | BW73: 6694 | BX73: 5727 | BY73: 1471 | BZ73: * | CA73: * | CB73: * | CC73: * | CD73: - | CE73: * | CF73: * | CG73: * | CH73: * | CI73: - | CJ73: - | CK73: - | CL73: 53510 | CN73: 5. IT Infrastructure, Networks & Support | CO73: 2137 | CP73: IT network professionals | CQ73: Full Unit Group | CS73: =CL68 -> 30483 | CT73: =SUM(CS73:CS76) -> 299691.86
A74: 3544 Data analysts | B74: - | C74: - | D74: - | E74: - | F74: * | G74: - | H74: - | I74: - | J74: * | K74: * | L74: * | M74: - | N74: - | O74: - | P74: - | Q74: - | R74: * | S74: * | T74: * | U74: * | V74: * | W74: - | X74: * | Y74: - | Z74: - | AA74: * | AB74: * | AC74: * | AD74: - | AE74: * | AF74: 1087 | AG74: * | AH74: 2716 | AI74: 1784 | AJ74: * | AK74: - | AL74: * | AM74: * | AN74: 1746 | AO74: - | AP74: * | AQ74: 908 | AR74: 2151 | AS74: 1181 | AT74: * | AU74: - | AV74: 1758 | AW74: * | AX74: * | AY74: * | AZ74: * | BA74: - | BB74: 1033 | BC74: 2972 | BD74: 8793 | BE74: * | BF74: 6133 | BG74: 5784 | BH74: 5660 | BI74: * | BJ74: 2985 | BK74: 4723 | BL74: 1459 | BM74: 2417 | BN74: 2196 | BO74: 3381 | BP74: - | BQ74: - | BR74: - | BS74: * | BT74: * | BU74: * | BV74: 1257 | BW74: 31047 | BX74: 6867 | BY74: 5226 | BZ74: * | CA74: 3411 | CB74: - | CC74: * | CD74: * | CE74: * | CF74: 1546 | CG74: - | CH74: * | CI74: - | CJ74: - | CK74: - | CL74: 132127 | CO74: 3131 | CP74: IT operations technicians | CQ74: Full Unit Group | CS74: =CL71 -> 84966
CO75: 3132 | CP75: IT user support technicians | CQ75: Full Unit Group | CS75: =CL72 -> 123533
CO76: 2133/04 + 2133/06 | CP76: Systems architects + Solution architects | CQ76: validated 2133 results | CR76: 0.299 | CS76: =CR76*CL64 -> 60709.857
CN78: Forecasting_Input_Long
CN79: Year | CO79: Career Area | CP79: Employment | CR79: Sum of Employment | CS79: Column Labels
CN80: 2021 | CO80: Software Development & Testing | CP80: =CT4 -> 544841.15 | CR80: Row Labels | CS80: Cybersecurity | CT80: Data, Analytics & Databases | CU80: IT Infrastructure, Networks & Support | CV80: Software Development & Testing | CW80: Web, Applications & UX/UI | CX80: Grand Total
CN81: 2021 | CO81: Data, Analytics & Databases | CP81: =CT7 -> 283779.09 | CR81: 2021 | CS81: 28494 | CT81: 283779.09 | CU81: 284911.23 | CV81: 544841.15 | CW81: 75565.61 | CX81: 1217591.1
CN82: 2021 | CO82: Cybersecurity | CP82: =CT10 -> 28494 | CR82: 2022 | CS82: 41349 | CT82: 296340.85 | CU82: 306709.47 | CV82: 609898.92 | CW82: 69172.13 | CX82: 1323470.4
CN83: 2021 | CO83: Web, Applications & UX/UI | CP83: =CT11 -> 75565.61 | CR83: 2023 | CS83: 65151 | CT83: 300662 | CU83: 333209.4 | CV83: 697664.66 | CW83: 80458.4 | CX83: 1477145.5
CN84: 2021 | CO84: IT Infrastructure, Networks & Support | CP84: =CT13 -> 284911.23 | CR84: 2024 | CS84: 72567 | CT84: 326068.3 | CU84: 306372.06 | CV84: 655901.02 | CW84: 89849.02 | CX84: 1450757.4
CN85: 2022 | CO85: Software Development & Testing | CP85: =CT19 -> 609898.92 | CR85: 2025 | CS85: 83476 | CT85: 316599.73 | CU85: 299691.86 | CV85: 641426.62 | CW85: 69960.02 | CX85: 1411154.2
CN86: 2022 | CO86: Data, Analytics & Databases | CP86: =CT22 -> 296340.85 | CR86: Grand Total | CS86: 291037 | CT86: 1523450 | CU86: 1530894 | CV86: 3149732.4 | CW86: 385005.18 | CX86: 6880118.5
CN87: 2022 | CO87: Cybersecurity | CP87: =CT25 -> 41349
CN88: 2022 | CO88: Web, Applications & UX/UI | CP88: =CT26 -> 69172.13
CN89: 2022 | CO89: IT Infrastructure, Networks & Support | CP89: =CT28 -> 306709.47
CN90: 2023 | CO90: Software Development & Testing | CP90: =CT34 -> 697664.66
CN91: 2023 | CO91: Data, Analytics & Databases | CP91: =CT37 -> 300662
CN92: 2023 | CO92: Cybersecurity | CP92: =CT40 -> 65151
CN93: 2023 | CO93: Web, Applications & UX/UI | CP93: =CT41 -> 80458.4
CN94: 2023 | CO94: IT Infrastructure, Networks & Support | CP94: =CT43 -> 333209.4
CN95: 2024 | CO95: Software Development & Testing | CP95: =CT49 -> 655901.02
CN96: 2024 | CO96: Data, Analytics & Databases | CP96: =CT52 -> 326068.3
CN97: 2024 | CO97: Cybersecurity | CP97: =CT55 -> 72567
CN98: 2024 | CO98: Web, Applications & UX/UI | CP98: =CT56 -> 89849.02
CN99: 2024 | CO99: IT Infrastructure, Networks & Support | CP99: =CT58 -> 306372.06
CN100: 2025 | CO100: Software Development & Testing | CP100: =CT64 -> 641426.62
CN101: 2025 | CO101: Data, Analytics & Databases | CP101: =CT67 -> 316599.73
CN102: 2025 | CO102: Cybersecurity | CP102: =CT70 -> 83476
CN103: 2025 | CO103: Web, Applications & UX/UI | CP103: =CT71 -> 69960.02
CN104: 2025 | CO104: IT Infrastructure, Networks & Support | CP104: =CT73 -> 299691.86
CR108: Source: Author’s calculations based on Office for National Statistics Annual Population Survey employment estimates, 2021–2025.
CN110: Observed Employment, 2021–2025 | CU110: 2-Year Moving Average
...

Sheet 15_Diagnostic_Q3
A1: Field | B1: Content
A2: Analytics Type | B2: Diagnostic
A3: Research Question | B3: Q3. Which technology trends are linked to the future outlook of Computer Science careers, and how does the UK compare globally?
A4: Purpose | B4: Identify technology trends relevant to the five CS Career Areas and examine the relationship between UK and Global employer expectations.
A5: Method(s) | B5: Descriptive Comparison; Correlation; Simple Linear Regression
A6: Dataset(s) | B6: 08_WEF_Technology
A7: Unit of Analysis | B7: Technology Trend
A8: Observations | B8: 9 technology trends
A10: Technology Trend | B10: UK (%) | C10: Primary Related Area | D10: Use in Analysis
A11: AI and information processing technologies | B11: 92 | C11: Data, Analytics & Databases | D11: Yes
A12: Robots and autonomous systems | B12: 62 | C12: Software Development & Testing | D12: Yes
A13: Semiconductors and computing technologies | B13: 33 | C13: IT Infrastructure, Networks & Support | D13: Yes
A14: Quantum and encryption | B14: 23 | C14: Cybersecurity | D14: Yes
A15: Among the technology trends identified as directly relevant to the five Computer Science Career Areas, AI and information processing technologies show the strongest UK employer expectation at 92%, followed by robots and autonomous systems at 62%. Semiconductors and computing technologies and quantum and encryption show lower but still notable UK expectations of 33% and 23%, respectively. These trends provide complementary evidence of the technologies most closely associated with the future outlook of selected Computer Science career areas.
A17: Technology Trend | B17: UK (%) | C17: Global (%) | D17: Difference (UK - Global)
A18: AI and information processing technologies | B18: 92 | C18: 86 | D18: =B18-C18 -> 6
A19: Robots and autonomous systems | B19: 62 | C19: 58 | D19: =B19-C19 -> 4
A20: Energy generation, storage and distribution | B20: 40 | C20: 41 | D20: =B20-C20 -> -1
A21: Semiconductors and computing technologies | B21: 33 | C21: 20 | D21: =B21-C21 -> 13
A22: New materials and composites | B22: 32 | C22: 30 | D22: =B22-C22 -> 2
A23: Sensing, laser and optical technologies | B23: 24 | C23: 18 | D23: =B23-C23 -> 6
A24: Quantum and encryption | B24: 23 | C24: 12 | D24: =B24-C24 -> 11
A25: Biotechnology and gene technologies | B25: 15 | C25: 11 | D25: =B25-C25 -> 4
A26: Satellites and space technologies | B26: 10 | C26: 9 | D26: =B26-C26 -> 1
A27: UK employer expectations are higher than the Global benchmark for eight of the nine technology trends analysed. The largest positive differences are observed for semiconductors and computing technologies (+13 percentage points) and quantum and encryption (+11 percentage points). AI and information processing technologies also show a higher UK expectation, at 92% compared with 86% globally. Energy generation, storage and distribution is the only trend where the UK is slightly below the Global benchmark, by 1 percentage point.
A29: How do UK employer expectations for technology trends compare with Global expectations?
A48: Source: Author’s analysis based on World Economic Forum, Future of Jobs Report 2025, United Kingdom Economy Profile and global evidence.
A50: Is there a linear association between Global and UK employer expectations across the technology trends?
A52: CORRELATION
A53: =CORREL(C18:C26, B18:B26) -> 0.98458807 | B53: Technology trends with higher Global employer expectations also tend to have higher UK employer expectations.
A56: SIMPLE LINEAR REGRESSION
A57: =SLOPE(B18:B26,C18:C26) -> 0.97462557 | B57: SLOPE | C57: for each 1 percentage-point increase in Global expectation, UK expectation is associated with an increase of approximately 0.975 percentage points.
A58: =INTERCEPT(B18:B26,C18:C26) -> 5.9146346 | B58: INTERCEPT
A59: =RSQ(B18:B26,C18:C26) -> 0.96941367 | B59: RSQ | C59: 96.9% of the variation in UK employer expectations across these nine technology trends is statistically associated with variation in the Global expectations in this simple linear model.
C60: The model shows a very strong linear association between Global and UK employer expectations, with R² = 0.969.
A62: Simple Linear Regression — Global vs UK Technology Expectations
A63: Measure | B63: Result
A64: Independent Variable (X) | B64: Global (%)
A65: Dependent Variable (Y) | B65: UK (%)
A66: Observations | B66: 9
A67: Correlation (r) | B67: 0.985
A68: R² | B68: 0.969
A69: Slope | B69: 0.975
A70: Intercept | B70: 5.915
A72: Interpretation: A very strong positive linear association is observed between Global and UK employer expectations across the nine technology trends (r ≈ 0.985; R² ≈ 0.969). Trends receiving stronger Global expectations also tend to receive stronger UK expectations. The analysis is exploratory and does not imply that Global expectations cause UK expectations.
A73: Limitation: The regression is based on only nine technology-trend observations and should be interpreted as exploratory rather than as a predictive or causal model.
A75: Is there a relationship between Global and UK employer expectations across technology trends?
A95: Source: Author’s regression analysis based on World Economic Forum, Future of Jobs Report 2025, United Kingdom Economy Profile and global technology-trend evidence.
A96: The scatter plot shows a very strong positive linear association between Global and UK employer expectations across the nine technology trends (r ≈ 0.985; R² ≈ 0.969). Technology trends with higher Global expectations also tend to have higher UK expectations. The regression slope of approximately 0.975 indicates that a one percentage-point increase in Global expectation is associated with an increase of approximately 0.975 percentage points in UK expectation. However, the analysis is exploratory, based on only nine observations, and does not imply causation.
A97: Points above the trendline indicate UK expectations higher than predicted by the overall Global–UK relationship, while points below the trendline indicate UK expectations lower than predicted by that relationship. This does not necessarily mean that UK expectations are lower than Global expectations.

Sheet 16_Diagnostic_Q4
A1: Field | B1: Content
A2: Analytics Type | B2: Diagnostic
A3: Research Question | B3: Q4. Do high-growth occupations also show strong curriculum alignment, or important skills gaps?
A4: Purpose | B4: Examine whether SOC Unit Groups with stronger projected employment growth also show stronger curriculum alignment or important curriculum gaps.
A5: Method(s) | B5: Descriptive Comparison; Standardisation; Exploratory Cluster Analysis
A6: Dataset(s) | B6: Department for Education (DfE) Baseline Employment Projections + Career Map & Curriculum Alignment Supporting Workbook
A7: Unit of Analysis | B7: SOC2020 Unit Group
A8: Comparison Period | B8: 2025–2035
A9: Scenario | B9: Baseline
A11: Methodological Note: Q4 is analysed at SOC2020 Unit Group level so that employment growth and curriculum alignment are compared at the same analytical level. SOC 2133 and 2139 remain mixed methodological cases and their Overall Alignment is not proportionally divided across Career Areas.
A13: SOC Unit Group | B13: Unit Group | C13: Employment 2025 | D13: Employment 2035 | E13: Absolute Growth | F13: Growth % | G13: Strong | H13: Moderate | I13: Limited | J13: No Clear Evidence | K13: N/A | L13: Overall Alignment | M13: Treatment | N13: Assessable Sub-Units | O13: Gap Share | P13: Z Growth % | Q13: Z Gap Share | R13: Cluster | S13: Cluster Label
A14: 2133 | B14: IT business analysts, architects and systems designers | C14: 148934 | D14: 165479 | E14: =D14-C14 -> 16545 | F14: =(D14-C14)/C14 -> 0.11108948 | G14: 0 | H14: 3 | I14: 3 | J14: 0 | K14: 1 | L14: Moderate | M14: Mixed Unit Group | N14: =SUM(G14:J14) -> 6 | O14: =IF(N14=0,"",(I14+J14)/N14) -> 0.5 | P14: =(F14-AVERAGE($F$14:$F$24))/_xlfn.STDEV.S($F$14:$F$24) -> 0.68743273 | Q14: =(O14-AVERAGE($O$14:$O$24))/_xlfn.STDEV.S($O$14:$O$24) -> 0.25332902 | R14: 1 | S14: Higher Growth / Lower-to-Moderate Curriculum Gap
A15: 2134 | B15: Programmers and software development professionals | C15: 496267 | D15: 551397 | E15: =D15-C15 -> 55130 | F15: =(D15-C15)/C15 -> 0.11108939 | G15: 2 | H15: 0 | I15: 1 | J15: 0 | K15: 1 | L15: Strong | M15: Standard Unit Group | N15: =SUM(G15:J15) -> 3 | O15: =IF(N15=0,"",(I15+J15)/N15) -> 0.33333333 | P15: =(F15-AVERAGE($F$14:$F$24))/_xlfn.STDEV.S($F$14:$F$24) -> 0.68742928 | Q15: =(O15-AVERAGE($O$14:$O$24))/_xlfn.STDEV.S($O$14:$O$24) -> -0.17538163 | R15: 1 | S15: Higher Growth / Lower-to-Moderate Curriculum Gap
A16: 2135 | B16: Cyber security professionals | C16: 36035 | D16: 40038 | E16: =D16-C16 -> 4003 | F16: =(D16-C16)/C16 -> 0.11108644 | G16: 0 | H16: 0 | I16: 3 | J16: 1 | K16: 1 | L16: Limited | M16: Standard Unit Group | N16: =SUM(G16:J16) -> 4 | O16: =IF(N16=0,"",(I16+J16)/N16) -> 1 | P16: =(F16-AVERAGE($F$14:$F$24))/_xlfn.STDEV.S($F$14:$F$24) -> 0.68730557 | Q16: =(O16-AVERAGE($O$14:$O$24))/_xlfn.STDEV.S($O$14:$O$24) -> 1.5394609 | R16: 2 | S16: Higher Curriculum-Gap Concern / Mixed Growth
A17: 2136 | B17: IT quality and testing professionals | C17: 34286 | D17: 38094 | E17: =D17-C17 -> 3808 | F17: =(D17-C17)/C17 -> 0.11106574 | G17: 0 | H17: 1 | I17: 0 | J17: 0 | K17: 0 | L17: Moderate | M17: Standard Unit Group | N17: =SUM(G17:J17) -> 1 | O17: =IF(N17=0,"",(I17+J17)/N17) -> 0 | P17: =(F17-AVERAGE($F$14:$F$24))/_xlfn.STDEV.S($F$14:$F$24) -> 0.6864373 | Q17: =(O17-AVERAGE($O$14:$O$24))/_xlfn.STDEV.S($O$14:$O$24) -> -1.0328029 | R17: 1 | S17: Higher Growth / Lower-to-Moderate Curriculum Gap
A18: 2137 | B18: IT network professionals | C18: 34951 | D18: 38834 | E18: =D18-C18 -> 3883 | F18: =(D18-C18)/C18 -> 0.11109839 | G18: 0 | H18: 1 | I18: 0 | J18: 0 | K18: 0 | L18: Moderate | M18: Standard Unit Group | N18: =SUM(G18:J18) -> 1 | O18: =IF(N18=0,"",(I18+J18)/N18) -> 0 | P18: =(F18-AVERAGE($F$14:$F$24))/_xlfn.STDEV.S($F$14:$F$24) -> 0.6878068 | Q18: =(O18-AVERAGE($O$14:$O$24))/_xlfn.STDEV.S($O$14:$O$24) -> -1.0328029 | R18: 1 | S18: Higher Growth / Lower-to-Moderate Curriculum Gap
A19: 2139 | B19: Information technology professionals n.e.c. | C19: 147063 | D19: 163400 | E19: =D19-C19 -> 16337 | F19: =(D19-C19)/C19 -> 0.11108845 | G19: 0 | H19: 2 | I19: 1 | J19: 0 | K19: 1 | L19: Moderate | M19: Mixed Unit Group | N19: =SUM(G19:J19) -> 3 | O19: =IF(N19=0,"",(I19+J19)/N19) -> 0.33333333 | P19: =(F19-AVERAGE($F$14:$F$24))/_xlfn.STDEV.S($F$14:$F$24) -> 0.6873895 | Q19: =(O19-AVERAGE($O$14:$O$24))/_xlfn.STDEV.S($O$14:$O$24) -> -0.17538163 | R19: 1 | S19: Higher Growth / Lower-to-Moderate Curriculum Gap
A20: 2141 | B20: Web design professionals | C20: 33945 | D20: 37716 | E20: =D20-C20 -> 3771 | F20: =(D20-C20)/C20 -> 0.11109147 | G20: 3 | H20: 0 | I20: 0 | J20: 0 | K20: 1 | L20: Strong | M20: Standard Unit Group | N20: =SUM(G20:J20) -> 3 | O20: =IF(N20=0,"",(I20+J20)/N20) -> 0 | P20: =(F20-AVERAGE($F$14:$F$24))/_xlfn.STDEV.S($F$14:$F$24) -> 0.68751643 | Q20: =(O20-AVERAGE($O$14:$O$24))/_xlfn.STDEV.S($O$14:$O$24) -> -1.0328029 | R20: 1 | S20: Higher Growth / Lower-to-Moderate Curriculum Gap
A21: 3131 | B21: IT operations technicians | C21: 120098 | D21: 128813 | E21: =D21-C21 -> 8715 | F21: =(D21-C21)/C21 -> 0.072565738 | G21: 0 | H21: 1 | I21: 3 | J21: 0 | K21: 1 | L21: Limited | M21: Standard Unit Group | N21: =SUM(G21:J21) -> 4 | O21: =IF(N21=0,"",(I21+J21)/N21) -> 0.75 | P21: =(F21-AVERAGE($F$14:$F$24))/_xlfn.STDEV.S($F$14:$F$24) -> -0.92825377 | Q21: =(O21-AVERAGE($O$14:$O$24))/_xlfn.STDEV.S($O$14:$O$24) -> 0.89639498 | R21: 2 | S21: Higher Curriculum-Gap Concern / Mixed Growth
A22: 3132 | B22: IT user support technicians | C22: 100971 | D22: 108299 | E22: =D22-C22 -> 7328 | F22: =(D22-C22)/C22 -> 0.072575294 | G22: 0 | H22: 0 | I22: 1 | J22: 0 | K22: 0 | L22: Limited | M22: Standard Unit Group | N22: =SUM(G22:J22) -> 1 | O22: =IF(N22=0,"",(I22+J22)/N22) -> 1 | P22: =(F22-AVERAGE($F$14:$F$24))/_xlfn.STDEV.S($F$14:$F$24) -> -0.927853 | Q22: =(O22-AVERAGE($O$14:$O$24))/_xlfn.STDEV.S($O$14:$O$24) -> 1.5394609 | R22: 2 | S22: Higher Curriculum-Gap Concern / Mixed Growth
A23: 3133 | B23: Database administrators and web content technicians | C23: 75694 | D23: 81187 | E23: =D23-C23 -> 5493 | F23: =(D23-C23)/C23 -> 0.072568499 | G23: 0 | H23: 1 | I23: 1 | J23: 0 | K23: 1 | L23: Moderate | M23: Standard Unit Group | N23: =SUM(G23:J23) -> 2 | O23: =IF(N23=0,"",(I23+J23)/N23) -> 0.5 | P23: =(F23-AVERAGE($F$14:$F$24))/_xlfn.STDEV.S($F$14:$F$24) -> -0.92813796 | Q23: =(O23-AVERAGE($O$14:$O$24))/_xlfn.STDEV.S($O$14:$O$24) -> 0.25332902 | R23: 2 | S23: Higher Curriculum-Gap Concern / Mixed Growth
A24: 3544 | B24: Data analysts | C24: 123733 | D24: 129470 | E24: =D24-C24 -> 5737 | F24: =(D24-C24)/C24 -> 0.046365965 | G24: 1 | H24: 0 | I24: 0 | J24: 0 | K24: 0 | L24: Strong | M24: Standard Unit Group | N24: =SUM(G24:J24) -> 1 | O24: =IF(N24=0,"",(I24+J24)/N24) -> 0 | P24: =(F24-AVERAGE($F$14:$F$24))/_xlfn.STDEV.S($F$14:$F$24) -> -2.0270729 | Q24: =(O24-AVERAGE($O$14:$O$24))/_xlfn.STDEV.S($O$14:$O$24) -> -1.0328029 | R24: 3 | S24: Lower Growth / Low Curriculum Gap
A26: Why was k = 3 selected? | F26: What does each final cluster represent?
A27: Cluster Quality Comparison | F27: Final Cluster Profiles
A28: k | B28: Inertia | C28: Silhouette Score | D28: Cluster Sizes | F28: Cluster | G28: Centroid Z Growth % | H28: Centroid Z Gap Share | I28: Size | J28: Label | M28: Interpretation
A29: 2 | B29: 9.828 | C29: 0.477 | D29: 7, 4 | F29: 1 | G29: 0.687 | H29: -0.533 | I29: 6 | J29: Higher Growth / Lower-to-Moderate Curriculum Gap | M29: Above-average projected growth combined with generally below-average curriculum gaps.
A30: 3 | B30: 4.718 | C30: 0.504 | D30: 6, 4, 1 | F30: 2 | G30: -0.524 | H30: 1.057 | I30: 4 | J30: Higher Curriculum-Gap Concern / Mixed Growth | M30: Characterised mainly by above-average curriculum gaps, with mixed employment-growth levels.
A31: 4 | B31: 2.451 | C31: 0.484 | D31: 6, 1, 1, 3 | F31: 3 | G31: -2.027 | H31: -1.033 | I31: 1 | J31: Lower Growth / Low Curriculum Gap | M31: Substantially below-average projected growth combined with a low curriculum gap.
A33: k = 3 was selected after comparing k = 2, 3 and 4. It produced the highest Silhouette Score (0.504) while maintaining a more interpretable structure than k = 4. The clustering is treated as exploratory due to the small sample of 11 SOC Unit Groups. | F33: Cluster Interpretation Note: Cluster labels are interpretive descriptions based on the validated centroids and are not formal occupational categories.
A35: Chart Data — Growth % vs Gap Share
A36: SOC Unit Group | B36: Growth % | C36: Gap Share | D36: Cluster | E36: Cluster Label
A37: 2133 | B37: 0.111089 | C37: 0.5 | D37: 1 | E37: Higher Growth / Lower-to-Moderate Curriculum Gap
A38: 2134 | B38: 0.111089 | C38: 0.333 | D38: 1 | E38: Higher Growth / Lower-to-Moderate Curriculum Gap
A39: 2135 | B39: 0.111086 | C39: 1 | D39: 2 | E39: Higher Curriculum-Gap Concern / Mixed Growth
A40: 2136 | B40: 0.111066 | C40: 0 | D40: 1 | E40: Higher Growth / Lower-to-Moderate Curriculum Gap
A41: 2137 | B41: 0.111098 | C41: 0 | D41: 1 | E41: Higher Growth / Lower-to-Moderate Curriculum Gap
A42: 2139 | B42: 0.111088 | C42: 0.333 | D42: 1 | E42: Higher Growth / Lower-to-Moderate Curriculum Gap
A43: 2141 | B43: 0.111091 | C43: 0 | D43: 1 | E43: Higher Growth / Lower-to-Moderate Curriculum Gap
A44: 3131 | B44: 0.072566 | C44: 0.75 | D44: 2 | E44: Higher Curriculum-Gap Concern / Mixed Growth
A45: 3132 | B45: 0.072575 | C45: 1 | D45: 2 | E45: Higher Curriculum-Gap Concern / Mixed Growth
A46: 3133 | B46: 0.072568 | C46: 0.5 | D46: 2 | E46: Higher Curriculum-Gap Concern / Mixed Growth
A47: 3544 | B47: 0.046366 | C47: 0 | D47: 3 | E47: Lower Growth / Low Curriculum Gap
A49: Chart Series Helper
A50: SOC | B50: Cluster 1 X | C50: Cluster 1 Y | D50: Cluster 2 X | E50: Cluster 2 Y | F50: Cluster 3 X | G50: Cluster 3 Y
A51: 2133 | B51: =IF($D37=1,$B37,NA()) -> 0.111089 | C51: =IF($D37=1,$C37,NA()) -> 0.5 | D51: =IF($D37=2,$B37,NA()) -> #N/A | E51: =IF($D37=2,$C37,NA()) -> #N/A | F51: =IF($D37=3,$B37,NA()) -> #N/A | G51: =IF($D37=3,$C37,NA()) -> #N/A
A52: 2134 | B52: =IF($D38=1,$B38,NA()) -> 0.111089 | C52: =IF($D38=1,$C38,NA()) -> 0.333 | D52: =IF($D38=2,$B38,NA()) -> #N/A | E52: =IF($D38=2,$C38,NA()) -> #N/A | F52: =IF($D38=3,$B38,NA()) -> #N/A | G52: =IF($D38=3,$C38,NA()) -> #N/A
A53: 2135 | B53: =IF($D39=1,$B39,NA()) -> #N/A | C53: =IF($D39=1,$C39,NA()) -> #N/A | D53: =IF($D39=2,$B39,NA()) -> 0.111086 | E53: =IF($D39=2,$C39,NA()) -> 1 | F53: =IF($D39=3,$B39,NA()) -> #N/A | G53: =IF($D39=3,$C39,NA()) -> #N/A
A54: 2136 | B54: =IF($D40=1,$B40,NA()) -> 0.111066 | C54: =IF($D40=1,$C40,NA()) -> 0 | D54: =IF($D40=2,$B40,NA()) -> #N/A | E54: =IF($D40=2,$C40,NA()) -> #N/A | F54: =IF($D40=3,$B40,NA()) -> #N/A | G54: =IF($D40=3,$C40,NA()) -> #N/A
A55: 2137 | B55: =IF($D41=1,$B41,NA()) -> 0.111098 | C55: =IF($D41=1,$C41,NA()) -> 0 | D55: =IF($D41=2,$B41,NA()) -> #N/A | E55: =IF($D41=2,$C41,NA()) -> #N/A | F55: =IF($D41=3,$B41,NA()) -> #N/A | G55: =IF($D41=3,$C41,NA()) -> #N/A
A56: 2139 | B56: =IF($D42=1,$B42,NA()) -> 0.111088 | C56: =IF($D42=1,$C42,NA()) -> 0.333 | D56: =IF($D42=2,$B42,NA()) -> #N/A | E56: =IF($D42=2,$C42,NA()) -> #N/A | F56: =IF($D42=3,$B42,NA()) -> #N/A | G56: =IF($D42=3,$C42,NA()) -> #N/A
A57: 2141 | B57: =IF($D43=1,$B43,NA()) -> 0.111091 | C57: =IF($D43=1,$C43,NA()) -> 0 | D57: =IF($D43=2,$B43,NA()) -> #N/A | E57: =IF($D43=2,$C43,NA()) -> #N/A | F57: =IF($D43=3,$B43,NA()) -> #N/A | G57: =IF($D43=3,$C43,NA()) -> #N/A
A58: 3131 | B58: =IF($D44=1,$B44,NA()) -> #N/A | C58: =IF($D44=1,$C44,NA()) -> #N/A | D58: =IF($D44=2,$B44,NA()) -> 0.072566 | E58: =IF($D44=2,$C44,NA()) -> 0.75 | F58: =IF($D44=3,$B44,NA()) -> #N/A | G58: =IF($D44=3,$C44,NA()) -> #N/A
A59: 3132 | B59: =IF($D45=1,$B45,NA()) -> #N/A | C59: =IF($D45=1,$C45,NA()) -> #N/A | D59: =IF($D45=2,$B45,NA()) -> 0.072575 | E59: =IF($D45=2,$C45,NA()) -> 1 | F59: =IF($D45=3,$B45,NA()) -> #N/A | G59: =IF($D45=3,$C45,NA()) -> #N/A
A60: 3133 | B60: =IF($D46=1,$B46,NA()) -> #N/A | C60: =IF($D46=1,$C46,NA()) -> #N/A | D60: =IF($D46=2,$B46,NA()) -> 0.072568 | E60: =IF($D46=2,$C46,NA()) -> 0.5 | F60: =IF($D46=3,$B46,NA()) -> #N/A | G60: =IF($D46=3,$C46,NA()) -> #N/A
A61: 3544 | B61: =IF($D47=1,$B47,NA()) -> #N/A | C61: =IF($D47=1,$C47,NA()) -> #N/A | D61: =IF($D47=2,$B47,NA()) -> #N/A | E61: =IF($D47=2,$C47,NA()) -> #N/A | F61: =IF($D47=3,$B47,NA()) -> 0.046366 | G61: =IF($D47=3,$C47,NA()) -> 0
A64: How does occupational growth relate to curriculum alignment and skills gaps? | I64: Mean Growth X | J64: Mean Growth Y
I65: =$J$75 -> 0.094698364 | J65: 0
I66: =$J$75 -> 0.094698364 | J66: 1
E68: Software Development & Testing | F68: 2134
F69: 2136 | I69: Mean Gap X | J69: Mean Gap Y
F70: 2139/01 | I70: =0% -> 0 | J70: =$J$76 -> 0.40145455
E71: Data, Analytics & Databases | F71: 3544 | I71: =12% -> 0.12 | J71: =$J$76 -> 0.40145455
F72: 3133
F73: 2133/02 + 2133/03
E74: Cybersecurity | F74: 2135 | I74: Reference | J74: Value
E75: Web, Applications & UX/UI | F75: 2141 | I75: Mean Growth % | J75: =AVERAGE(B37:B47) -> 0.094698364
F76: 2139/03 | I76: Mean Gap Share | J76: =AVERAGE(C37:C47) -> 0.40145455
E77: IT Infrastructure, Networks & Support | F77: 2137
F78: 3131
F79: 3132
A84: Source: Author’s analysis based on Department for Education employment projections and Career Map curriculum-alignment evidence.
A85: Cluster 1 | B85: Higher Growth / Lower-to-Moderate Curriculum Gap
A86: Cluster 2 | B86: Higher Curriculum-Gap Concern / Mixed Growth
A87: Cluster 3 | B87: Lower Growth / Low Curriculum Gap
A88: Interpretation: Projected employment growth does not consistently correspond to lower curriculum gaps across SOC Unit Groups. Some high-growth occupations show relatively low or moderate gaps, while SOC 2135 combines high projected growth with a very high gap share. Conversely, SOC 3544 shows lower projected growth but a low curriculum gap. The exploratory cluster analysis reinforces this pattern, suggesting that future growth potential and curriculum preparedness should be considered together when evaluating career opportunities.

Sheet 16A_Cluster_Python
A1: Section | B1: Conteúdo
A2: Purpose | B2: Purpose: This worksheet documents the reproducible Python workflow used for the exploratory k-Means cluster analysis in 16_Diagnostic_Q4. The analysis uses standardised Growth % and Gap Share values for 11 SOC2020 Unit Groups, compares k = 2, 3 and 4, and generates the final k = 3 cluster assignments and centroids.
A3: Python Code | B3: Presented below
A4: Key Outputs | B4: k comparison + assignments + centroids + sizes
A5: Method Note | B5: Inputs, k selection and exploratory nature of the analysis
B8: import pandas as pd | D8: Input Validation - Prepared Clustering Input
B9: from sklearn.cluster import KMeans | D9: SOC Unit Group | E9: Z Growth % | F9: Z Gap Share
B10: from sklearn.metrics import silhouette_score | D10: 2133 | E10: 0.687433 | F10: 0.253329
D11: 2134 | E11: 0.687429 | F11: -0.175382
B12: # -------------------------------------------------- | D12: 2135 | E12: 0.687306 | F12: 1.539461
B13: # 1. File path | D13: 2136 | E13: 0.686437 | F13: -1.032803
B14: # -------------------------------------------------- | D14: 2137 | E14: 0.687807 | F14: -1.032803
D15: 2139 | E15: 0.68739 | F15: -0.175382
B16: file_path = r "1_Main_dataset_in_construction.xlsx" # Update the file path if the workbook is stored in a different directory. | D16: 2141 | E16: 0.687516 | F16: -1.032803
D17: 3131 | E17: -0.928254 | F17: 0.896395
B18: # -------------------------------------------------- | D18: 3132 | E18: -0.927853 | F18: 1.539461
B19: # 2. Read the Q4 analysis sheet | D19: 3133 | E19: -0.928138 | F19: 0.253329
B20: # Excel row 13 is used as the header | D20: 3544 | E20: -2.027073 | F20: -1.032803
B21: # --------------------------------------------------
B23: df = pd.read_excel( | D23: Validation Check | E23: Result
B24: file_path, | D24: Number of SOC Unit Groups | E24: 11
B25: sheet_name="16_Diagnostic_Q4", | D25: Missing SOC Unit Group | E25: 0
B26: header=12 | D26: Missing Z Growth % | E26: 0
B27: ) | D27: Missing Z Gap Share | E27: 0
D28: Unique SOC Unit Groups | E28: 11
B29: # -------------------------------------------------- | D29: SOC Unit Group Data Type | E29: object
B30: # 3. Prepare clustering input | D30: Z Growth % Data Type | E30: float64
B31: # SOC Unit Group is used only as an identifier | D31: Z Gap Share Data Type | E31: float64
B32: # --------------------------------------------------
D33: Cluster Quality Comparison
B34: cluster_input = df[ | D34: k | E34: Inertia | F34: Silhouette Score | G34: Cluster Sizes
B35: [ | D35: 2 | E35: 9.827994 | F35: 0.477135 | G35: 7, 4
B36: "SOC Unit Group", | D36: 3 | E36: 4.717829 | F36: 0.503694 | G36: 6, 4, 1
B37: "Z Growth %", | D37: 4 | E37: 2.450572 | F37: 0.483631 | G37: 6, 1, 1, 3
B38: "Z Gap Share"
B39: ]
B40: ].dropna().copy() | D40: Final k-Means Cluster Assignments - k = 3
D41: SOC Unit Group | E41: Z Growth % | F41: Z Gap Share | G41: Cluster
B42: # -------------------------------------------------- | D42: 2133 | E42: 0.687433 | F42: 0.253329 | G42: 1
B43: # 4. Validate clustering input | D43: 2134 | E43: 0.687429 | F43: -0.175382 | G43: 1
B44: # -------------------------------------------------- | D44: 2135 | E44: 0.687306 | F44: 1.539461 | G44: 2
D45: 2136 | E45: 0.686437 | F45: -1.032803 | G45: 1
B46: print("\n--- Input Validation ---") | D46: 2137 | E46: 0.687807 | F46: -1.032803 | G46: 1
D47: 2139 | E47: 0.68739 | F47: -0.175382 | G47: 1
B48: print("\nPrepared clustering input:") | D48: 2141 | E48: 0.687516 | F48: -1.032803 | G48: 1
B49: print(cluster_input.to_string(index=False)) | D49: 3131 | E49: -0.928254 | F49: 0.896395 | G49: 2
D50: 3132 | E50: -0.927853 | F50: 1.539461 | G50: 2
B51: print("\nNumber of SOC Unit Groups:") | D51: 3133 | E51: -0.928138 | F51: 0.253329 | G51: 2
B52: print(len(cluster_input)) | D52: 3544 | E52: -2.027073 | F52: -1.032803 | G52: 3
B54: print("\nMissing values:")
B55: print(cluster_input.isna().sum()) | D55: Final Cluster Centroids and Sizes
D56: Cluster | E56: Z Growth % Centroid | F56: Z Gap Share Centroid | G56: Cluster Size
B57: print("\nData types:") | D57: 1 | E57: 0.687335 | F57: -0.53264 | G57: 6
B58: print(cluster_input.dtypes) | D58: 2 | E58: -0.524235 | F58: 1.057161 | G58: 4
D59: 3 | E59: -2.027073 | F59: -1.032803 | G59: 1
B60: print("\nUnique SOC Unit Groups:")
B61: print(cluster_input["SOC Unit Group"].nunique())
B63: # -------------------------------------------------- | D63: Exploratory k-Means Clustering Process
B64: # 5. Select variables used by k-Means | D64: 1. Prepare the data
B65: # -------------------------------------------------- | D65: Growth % and Gap Share were calculated for 11 SOC2020 Unit Groups in the 16_Diagnostic_Q4 worksheet.
B67: X = cluster_input[ | D67: 2. Standardise the variables
B68: [ | D68: Growth % and Gap Share were converted into Z-scores so that both variables contributed equally to the clustering.
B69: "Z Growth %",
B70: "Z Gap Share" | D70: 3. Import and validate the data
B71: ] | D71: Python imported the SOC Unit Group, Z Growth % and Z Gap Share columns. The data were checked for missing values, duplicates and correct data types.
B72: ]
D73: 4. Test different numbers of clusters
B74: # -------------------------------------------------- | D74: k-means was tested with k=2k=2, k=3k=3 and k=4k=4, using random_state=42 and n_init=10 to support reproducibility and stable results.
B75: # 6. Compare alternative numbers of clusters
B76: # k = 2, 3 and 4 | D76: 5. Evaluate cluster quality
B77: # -------------------------------------------------- | D77: Inertia, Silhouette Score and cluster sizes were calculated for each value of kk. A higher Silhouette Score indicates better separation between clusters.
B79: results = [] | D79: 6. Select the final model
D80: k=3k=3 was selected because it produced the highest Silhouette Score, 0.504, and provided an interpretable cluster structure.
B81: for k in [2, 3, 4]:
D82: 7. Generate the final outputs
B83: model = KMeans( | D83: The final model assigned each SOC Unit Group to a cluster and calculated the cluster centroids and sizes.
B84: n_clusters=k, | D84: 8. Interpret the clusters
B85: random_state=42, | D85: The clusters were interpreted according to their combinations of projected employment growth and curriculum gap. The analysis is exploratory because it is based on only 11 SOC Unit Groups.
B86: n_init=10
B87: )
B89: labels = model.fit_predict(X)
B91: inertia = model.inertia_
B92: silhouette = silhouette_score(X, labels)
B94: cluster_sizes = (
B95: pd.Series(labels)
B96: .value_counts()
B97: .sort_index()
B98: .tolist()
B99: )
B101: results.append({
... B163: print(cluster_sizes)

Sheet 17_Prescriptive_Analysis
A1: Field | B1: Definition
A2: Analytics Type | B2: Prescriptive
A3: Decision Question | B3: What do these findings imply for students choosing a Computer Science career with stronger future potential?
A4: Purpose | B4: Integrate Q1–Q4 findings to support comparison of the five Computer Science Career Areas based on future-growth evidence.
A5: Decision Unit | B5: Career Area
A6: Career Areas Compared | B6: Software Development & Testing
B7: Data, Analytics & Databases
B8: Cybersecurity
B9: Web, Applications & UX/UI
B10: IT Infrastructure, Networks & Support
A11: Evidence Base | B11: Q1 Descriptive; Q2 Predictive-oriented; Q3 Diagnostic; Q4 Diagnostic; complementary WEF evidence
A12: Method | B12: Structured Decision Analysis / Evidence Synthesis
A13: Primary Perspective | B13: Future Growth & Industry Trends
A14: Output | B14: Decision-support profile for each Career Area
A15: Use in Final Project | B15: Input to the group Career Comparison Dashboard and Decision Matrix
A16: Cross-Source Reconciliation Method: Evidence is interpreted according to what each source and measure represents. Only comparable measures are compared directly. Different sources can be used together as complementary evidence, but they are not treated as equivalent. Relevant limitations and proxies are stated, and interpretations are only made when supported by validated evidence.
A18: Integrated Q1–Q4 Evidence by Career Area
A19: Career Area | B19: Baseline Employment 2035 | C19: Absolute Growth | D19: Growth % | E19: Best 2035 Scenario | F19: Best Scenario Employment | G19: Scenario Uplift vs Baseline | H19: Technology / WEF Signal | I19: Curriculum / Gap Signal | J19: Consolidated Evidence
A20: Software Development & Testing | B20: =_xlfn.XLOOKUP($A20,'13_Descriptive_Q1'!$B$17:$B$21,'13_Descriptive_Q1'!$D$17:$D$21) -> 664818.79 | C20: =_xlfn.XLOOKUP($A20,'13_Descriptive_Q1'!$B$17:$B$21,'13_Descriptive_Q1'!$F$17:$F$21) -> 66470.067 | D20: =_xlfn.XLOOKUP($A20,'13_Descriptive_Q1'!$B$17:$B$21,'13_Descriptive_Q1'!$E$17:$E$21) -> 0.11108918 | E20: =SUBSTITUTE(_xlfn.XLOOKUP($A20,'14_Predictive_Q2'!$A$122:$A$126,'14_Predictive_Q2'!$E$122:$E$126)," 2035","") -> Human-Centric | F20: =MAX(_xlfn.XLOOKUP($A20,'14_Predictive_Q2'!$A$122:$A$126,'14_Predictive_Q2'!$B$122:$D$126)) -> 778761.13 | G20: =(F20-B20)/B20 -> 0.17138857 | H20: Strong - Robots/autonomous systems; DevOps-related evidence | I20: Mainly higher-growth SOCs with low-to-moderate gaps | J20: Strong broad growth and largest job creation, with favourable curriculum profile across most relevant SOCs.
A21: Data, Analytics & Databases | B21: =_xlfn.XLOOKUP($A21,'13_Descriptive_Q1'!$B$17:$B$21,'13_Descriptive_Q1'!$D$17:$D$21) -> 317390.55 | C21: =_xlfn.XLOOKUP($A21,'13_Descriptive_Q1'!$B$17:$B$21,'13_Descriptive_Q1'!$F$17:$F$21) -> 21900.789 | D21: =_xlfn.XLOOKUP($A21,'13_Descriptive_Q1'!$B$17:$B$21,'13_Descriptive_Q1'!$E$17:$E$21) -> 0.074116912 | E21: =SUBSTITUTE(_xlfn.XLOOKUP($A21,'14_Predictive_Q2'!$A$122:$A$126,'14_Predictive_Q2'!$E$122:$E$126)," 2035","") -> Technical Opportunities | F21: =MAX(_xlfn.XLOOKUP($A21,'14_Predictive_Q2'!$A$122:$A$126,'14_Predictive_Q2'!$B$122:$D$126)) -> 354173.44 | G21: =(F21-B21)/B21 -> 0.11589158 | H21: Very strong specialised signal - AI, Big Data, AI/ML roles | I21: Mixed: strong alignment in 3544 but lower broad growth; mixed evidence in 2133/3133 | J21: Moderate broad employment growth but exceptionally strong specialised Data/AI transformation signals from WEF.
A22: Cybersecurity | B22: =_xlfn.XLOOKUP($A22,'13_Descriptive_Q1'!$B$17:$B$21,'13_Descriptive_Q1'!$D$17:$D$21) -> 40037.732 | C22: =_xlfn.XLOOKUP($A22,'13_Descriptive_Q1'!$B$17:$B$21,'13_Descriptive_Q1'!$F$17:$F$21) -> 4003.0618 | D22: =_xlfn.XLOOKUP($A22,'13_Descriptive_Q1'!$B$17:$B$21,'13_Descriptive_Q1'!$E$17:$E$21) -> 0.11108918 | E22: =SUBSTITUTE(_xlfn.XLOOKUP($A22,'14_Predictive_Q2'!$A$122:$A$126,'14_Predictive_Q2'!$E$122:$E$126)," 2035","") -> Human-Centric | F22: =MAX(_xlfn.XLOOKUP($A22,'14_Predictive_Q2'!$A$122:$A$126,'14_Predictive_Q2'!$B$122:$D$126)) -> 46899.742 | G22: =(F22-B22)/B22 -> 0.17138857 | H22: Strong - Quantum/encryption + cybersecurity skills relevance | I22: High growth but substantial curriculum-gap concern in SOC 2135 | J22: Strong percentage growth and technology relevance, but smaller employment base and notable curriculum-gap concern.
A23: Web, Applications & UX/UI | B23: =_xlfn.XLOOKUP($A23,'13_Descriptive_Q1'!$B$17:$B$21,'13_Descriptive_Q1'!$D$17:$D$21) -> 85101.612 | C23: =_xlfn.XLOOKUP($A23,'13_Descriptive_Q1'!$B$17:$B$21,'13_Descriptive_Q1'!$F$17:$F$21) -> 8508.6492 | D23: =_xlfn.XLOOKUP($A23,'13_Descriptive_Q1'!$B$17:$B$21,'13_Descriptive_Q1'!$E$17:$E$21) -> 0.11108918 | E23: =SUBSTITUTE(_xlfn.XLOOKUP($A23,'14_Predictive_Q2'!$A$122:$A$126,'14_Predictive_Q2'!$E$122:$E$126)," 2035","") -> Human-Centric | F23: =MAX(_xlfn.XLOOKUP($A23,'14_Predictive_Q2'!$A$122:$A$126,'14_Predictive_Q2'!$B$122:$D$126)) -> 99687.056 | G23: =(F23-B23)/B23 -> 0.17138857 | H23: More limited direct WEF technology evidence | I23: Strong alignment in SOC 2141; generally low gap | J23: Strong percentage growth and curriculum alignment, but smaller employment scale and weaker direct WEF technology evidence.
A24: IT Infrastructure, Networks & Support | B24: =_xlfn.XLOOKUP($A24,'13_Descriptive_Q1'!$B$17:$B$21,'13_Descriptive_Q1'!$D$17:$D$21) -> 325423.34 | C24: =_xlfn.XLOOKUP($A24,'13_Descriptive_Q1'!$B$17:$B$21,'13_Descriptive_Q1'!$F$17:$F$21) -> 24872.141 | D24: =_xlfn.XLOOKUP($A24,'13_Descriptive_Q1'!$B$17:$B$21,'13_Descriptive_Q1'!$E$17:$E$21) -> 0.082755087 | E24: =SUBSTITUTE(_xlfn.XLOOKUP($A24,'14_Predictive_Q2'!$A$122:$A$126,'14_Predictive_Q2'!$E$122:$E$126)," 2035","") -> Technical Opportunities | F24: =MAX(_xlfn.XLOOKUP($A24,'14_Predictive_Q2'!$A$122:$A$126,'14_Predictive_Q2'!$B$122:$D$126)) -> 424066.86 | G24: =(F24-B24)/B24 -> 0.30312368 | H24: Strong - Semiconductors/computing + infrastructure exposure | I24: Mixed; some higher-gap SOCs, particularly support/operations | J24: Moderate baseline growth but substantial upside under the Technical Opportunities scenario, with mixed curriculum-gap evidence.
A26: Material Cross-Source Reconciliation
A27: Issue | B27: Reconciled Interpretation | F27: Key Limitation | I27: Decision Use
A28: Broad employment vs specialised growth | B28: DfE shows broad UK employment growth, while WEF highlights specialised and emerging roles. These are complementary views of future potential. | F28: WEF role-growth measures are not directly comparable with DfE Career Area Growth %. | I28: Distinguish broad employment opportunity from specialised emerging-role opportunity.
A29: Different analytical levels | B29: Career Areas, SOC Unit Groups, WEF roles and technology trends can support interpretation at different levels but are not one-to-one equivalents. | F29: No validated direct crosswalk exists for all WEF roles and technologies to the Career Areas. | I29: Use WEF evidence to contextualise Career Area profiles, not as direct occupational equivalence.
A30: Official projections vs employer expectations | B30: DfE primarily supports employment outlook; WEF supports employer expectations about future roles and technologies. | F30: Employer expectations are not observed or guaranteed future employment outcomes. | I30: Keep the two evidence types separate but complementary.
A31: Baseline vs scenario opportunity | B31: Baseline shows the central projected employment path, while alternative scenarios show possible upside or sensitivity. | F31: A favourable scenario is not a prediction that it will occur. | I31: Consider baseline strength and scenario opportunity as separate signals.
A32: Growth vs curriculum preparedness | B32: Employment growth and curriculum preparedness measure different dimensions of future potential. | F32: Q4 operates at SOC Unit Group level and uses exploratory clustering with a small sample. | I32: Use curriculum evidence to identify possible skills-development needs alongside growth opportunity.
A33: Mixed SOC 2133/2139 treatment | B33: Employment analyses proportionally allocate mixed SOCs, while curriculum analysis keeps them as mixed Unit Groups. | F33: Adzuna allocation shares are methodological proxies, not official employment weights. | I33: Use both evidence types while preserving their different methodological treatment.
A34: Reconciliation Summary: The evidence from DfE, WEF and the curriculum analysis provides complementary views of future career potential rather than directly equivalent measures. DfE projections are used primarily to assess broad UK employment growth and scenario outcomes, while WEF evidence adds information on employer expectations, emerging roles and technology-driven transformation. Curriculum evidence provides a separate view of preparedness and potential skills gaps. These dimensions are therefore interpreted together, but they are not numerically combined or treated as interchangeable.
A36: Future-Growth Decision Framework
A37: Dimension | C37: Role in Decision | D37: Main Evidence | E37: Interpretation
A38: Broad Employment Outlook | C38: Core | D38: Q1 | E38: Relative growth, job creation and future employment scale
A39: Scenario Opportunity | C39: Core | D39: Q2 | E39: Potential upside under alternative future scenarios
A40: Technology & Emerging-Role Outlook | C40: Core | D40: Q3 + WEF | E40: Technology-driven transformation and specialised/emerging opportunity
A41: Curriculum Preparedness / Skills Gap | C41: Qualifier | D41: Q4 | E41: Indicates preparedness or additional skills-development needs
A42: Decision Framework Note: The three core dimensions represent different aspects of future growth potential and are not treated as directly equivalent measures. Curriculum preparedness is used as a qualifying factor rather than as a measure of employment growth.
A44: Prescriptive Comparison by Career Area
A45: Career Area | B45: Broad Employment Outlook | D45: Scenario Opportunity | F45: Technology & Emerging-Role Outlook | H45: Curriculum Preparedness / Skills Gap | I45: Prescriptive Interpretation
A46: Software Development & Testing | B46: Strong broad growth, largest absolute job creation and largest 2035 employment base among the five areas. | D46: Strong upside under the Human-Centric scenario. | F46: Strong technology-related evidence, including automation/robotics and software-related transformation signals. | H46: Generally favourable, with several higher-growth SOCs showing low-to-moderate gaps. | I46: Offers the strongest evidence for broad and scalable employment opportunity, supported by positive scenario and technology signals.
A47: Data, Analytics & Databases | B47: Moderate broad Career Area growth compared with Software, Cybersecurity and Web/UX. | D47: Positive upside under the Technical Opportunities scenario, though smaller than Infrastructure. | F47: Very strong specialised evidence from WEF for AI, Big Data and related emerging roles. | H47: Mixed profile: strong alignment for SOC 3544, but mixed evidence across 2133/3133. | I47: Broad employment growth is more moderate, but specialised AI/Data evidence suggests strong opportunity in specific emerging roles.
A48: Cybersecurity | B48: Strong percentage growth, but from the smallest employment base and with limited absolute job creation. | D48: Strong upside under the Human-Centric scenario. | F48: Strong relevance from quantum/encryption and cybersecurity-related technology/skills evidence. | H48: High curriculum-gap concern in SOC 2135. | I48: Shows strong growth and technology relevance, but the opportunity is smaller in scale and may require additional skills development.
A49: Web, Applications & UX/UI | B49: Strong percentage growth, but smaller employment scale and absolute growth. | D49: Strong upside under the Human-Centric scenario. | F49: Limited direct WEF evidence in the material used. | H49: Strong curriculum alignment and generally low gap evidence for SOC 2141. | I49: Shows positive growth and favourable preparedness, but evidence for technology-driven emerging opportunity is less direct.
A50: IT Infrastructure, Networks & Support | B50: Moderate baseline growth with substantial employment scale. | D50: Strongest relative scenario upside, particularly under Technical Opportunities. | F50: Strong infrastructure-related evidence from semiconductors/computing technologies. | H50: Mixed curriculum profile, including higher-gap SOCs in support/operations. | I50: Offers moderate baseline growth but substantial scenario-sensitive upside, with some preparedness concerns across relevant occupations.
A51: Prescriptive Comparison Note: The Career Areas are compared using distinct dimensions of future potential rather than a single combined score. Differences between areas are interpreted only where supported by validated evidence, and limited evidence in one dimension is not treated as negative evidence.
A52: Key Prescriptive Finding: Future growth potential differs by type of opportunity rather than producing a single clear winner across all dimensions.
A54: Decision Outcome — Recommendation by Priority
A55: Student Priority | C55: Career Area with Strongest Supporting Evidence | F55: Evidence Basis | I55: Important Caveat
A56: Broad employment scale and job creation | C56: Software Development & Testing | F56: Largest 2035 employment base and largest absolute projected job creation in Q1 | I56: This does not mean it is strongest on every other dimension
A57: Specialised AI / Big Data opportunity | C57: Data, Analytics & Databases | F57: Strong WEF signals for AI, Big Data and related emerging roles | I57: Broad Career Area growth in DfE is more moderate
A58: Strong growth plus technology relevance | C58: Cybersecurity | F58: Strong projected Growth % together with cybersecurity / encryption-related technology evidence | I58: Smaller employment base and notable curriculum-gap concern
A59: Growth with favourable curriculum preparedness | C59: Web, Applications & UX/UI | F59: Strong projected Growth % and favourable SOC 2141 curriculum alignment | I59: Direct WEF emerging-role evidence is more limited in the material used
A60: Technology-driven scenario upside | C60: IT Infrastructure, Networks & Support | F60: Largest relative scenario uplift, particularly under Technical Opportunities | I60: Baseline growth is more moderate and curriculum evidence is mixed
A61: Decision Outcome: No single Career Area is supported as the strongest option across every future-growth dimension. Instead, the preferred alternative depends on the student’s priority. Software has the strongest evidence for broad employment scale and job creation; Data for specialised AI and Big Data opportunity; Cybersecurity for growth combined with technology relevance; Web/UX for growth with favourable curriculum preparedness; and Infrastructure for technology-driven scenario upside.
A62: Decision Note: These recommendations are conditional on the Future Growth & Industry Trends evidence analysed in this subtopic. They do not represent the final overall career recommendation, which should also consider the other project criteria.

Sheet 18_Key_Findings
A1: Q1 — Employment Growth and Job Creation
A2: Key Finding | B2: Evidence | C2: Interpretation
A3: Software combines the largest employment scale with the highest absolute job creation. | B3: Employment increases from 598,349 to 664,819, creating 66,470 jobs (+11.11%). | C3: Software shows the strongest combination of scale and absolute employment growth.
A4: Cybersecurity shows strong proportional growth from a much smaller employment base. | B4: Employment increases from 36,035 to 40,038, equivalent to +11.11% and +4,003 jobs. | C4: Percentage growth is strong, but the absolute number of additional jobs remains relatively small.
A5: Data and Infrastructure show moderate growth, with Infrastructure generating more absolute jobs. | B5: Data: +21,901 jobs; +7.41%. Infrastructure: +24,872 jobs; +8.28%. | C5: Both areas expand, but less strongly than Software in absolute job creation.
A6: Overall Q1 Finding: Future growth differs depending on whether potential is assessed by percentage growth, employment scale, or absolute job creation. Software shows the strongest combination of employment scale and job creation, while Cybersecurity shows strong proportional growth from a smaller base.
A9: Q2 — Future Trajectories & Forecasting
A10: Key Finding | B10: Evidence | C10: Interpretation
A11: All five Career Areas show positive long-term employment trajectories under the DfE Baseline. | B11: DfE projections increase across 2021–2035 for all five areas. | C11: The long-term outlook remains positive across the five Career Areas, although the scale and pace of growth differ.
A12: Alternative scenarios increase 2035 employment above the Baseline, with Infrastructure showing the strongest relative uplift. | B12: Scenario uplift vs Baseline in 2035 is approximately 17.14% for Software, 11.59% for Data, 17.14% for Cybersecurity, 17.14% for Web/UX, and 30.31% for Infrastructure. | C12: Infrastructure appears particularly sensitive to more favourable future conditions.
A13: The APS-based 2026 forecast is broadly close to the DfE Baseline for most areas, but Cybersecurity shows a substantial divergence. | B13: Selected methods based on the lowest MSE: SES α = 0.8 for Software, Data, Cybersecurity and Infrastructure; SES α = 0.2 for Web/UX. Difference vs DfE 2026: Software +6.66%, Data +6.63%, Cybersecurity +121.75%, Web/UX −0.95%, and Infrastructure −0.38%. | C13: Recent APS-based patterns broadly align with the DfE projection for four areas, while Cybersecurity shows a much stronger recent trajectory and should be interpreted cautiously.
A14: Overall Q2 Finding: Long-term projections remain positive across all five Career Areas, while scenario analysis shows that future outcomes vary in sensitivity to alternative conditions. The short-term APS-based forecast broadly supports the DfE outlook for most areas, but Cybersecurity shows a substantial divergence that highlights uncertainty between recent employment estimates and longer-term projections.
A16: Q3 — Technology Trends and UK vs Global
A17: Key Finding | B17: Evidence | C17: Interpretation
A18: UK technology trends closely follow global patterns. | B18: Regression between Global % and UK % gives r ≈ 0.985 and R² ≈ 0.969. | C18: UK employer expectations are strongly aligned with global technology trends.
A19: The relationship is strong, but should be interpreted as association rather than causation. | B19: Regression slope ≈ 0.975 with intercept ≈ 5.915 across 9 technology trends. | C19: Global technology trends are strongly associated with UK expectations, but the analysis does not prove that global trends directly cause UK outcomes.
A20: Technology-related signals reinforce the relevance of AI, data and digital transformation for future CS careers. | B20: WEF technology-trend evidence highlights strong employer expectations around AI, information processing and related technologies. | C20: Technology change strengthens the future relevance of several CS Career Areas, particularly those connected to AI, data, software and digital infrastructure.
A21: Overall 3 Finding: UK technology expectations are strongly aligned with global patterns, suggesting that major technology trends are likely to remain important drivers of future Computer Science career demand. However, the regression should be interpreted as evidence of association rather than causation.
A24: Q4 — Growth & Curriculum Preparedness
A25: Key Finding | B25: Evidence | C25: Interpretation
A26: Projected employment growth does not consistently correspond to lower curriculum gaps across SOC Unit Groups. | B26: The Growth % × Gap Share analysis shows both high-growth occupations with lower/moderate gaps and others with substantial curriculum-gap concerns. | C26: Strong labour-market growth does not automatically mean that current curriculum coverage is equally strong.
A27: Cybersecurity stands out as a high-growth occupation with a particularly high curriculum-gap share. | B27: SOC 2135 combines relatively strong projected growth with a high Gap Share in the Q4 analysis. | C27: Cybersecurity may offer strong future opportunity while also requiring greater attention to skills and curriculum preparedness.
A28: The exploratory cluster analysis confirms that growth and curriculum preparedness form different occupation profiles. | B28: k-Means with k=3 produced clusters representing higher growth/lower-to-moderate gap, higher curriculum-gap concern/mixed growth, and lower growth/low gap. | C28: Career potential should be evaluated using both employment outlook and preparedness, rather than growth alone.
A29: Overall Q4 Finding: Projected growth and curriculum preparedness do not move together consistently across occupations. Some high-growth roles appear relatively well aligned with current curriculum evidence, while others, particularly Cybersecurity, show substantial skills-gap concerns. This suggests that future career potential should be assessed by considering both labour-market growth and preparedness for the skills required.
A32: Overall Key Findings
A33: Which Computer Science Career Areas show the strongest future growth potential?
A34: Software Development & Testing → strongest combination of employment scale and absolute job creation.
A35: Cybersecurity → strong growth potential, but with substantial curriculum-gap concerns and higher uncertainty in short-term forecasting.
A36: Data, Analytics & Databases → moderate broad employment growth, but strong relevance from AI/data technology trends.
A37: IT Infrastructure, Networks & Support → moderate baseline growth but strongest uplift under favourable scenarios.
A38: Overall conclusion → there is no single winner across all dimensions; future potential depends on whether the priority is scale, growth rate, technology exposure, scenario upside, or curriculum preparedness.
A39: Cross-source finding: Official UK employment projections identify Software Development & Testing as the strongest Career Area for broad employment scale and absolute job creation. In contrast, WEF employer evidence highlights specialised Data and AI occupations—particularly Big Data Specialists and AI and Machine Learning Specialists—as areas of particularly strong expected growth and transformation. These findings are not contradictory because they represent different levels and measures: the DfE projections assess broad Career Area employment, while the WEF evidence focuses on employer expectations for specific emerging occupations. Therefore, Data shows more moderate growth at the broad Career Area level while still containing specialised AI and data roles with strong future-growth signals.

Sheet 19_Visual_Summary
A1: Future Growth & Industry Trends in Computer Science Careers
A2: Research Question: Which Computer Science Career Areas show the strongest future growth potential?
A4: Where is the strongest employment growth?
